Workbook

Sheet Lisez-moi
B3: CATALOGUE TCE — PRIX FOURNISSEURS RÉELS
B4: ANELEC Groupe / Blueseatra · version du 09/09/2026 · document interne
B6: 547 | C6: 526 | D6: 289 | E6: 21
B7: articles au catalogue | C7: prix réels relevés | D7: articles comparés sur 2 enseignes ou plus | E7: lignes à compléter
B9: Comment lire ce catalogue | C9: Une feuille par corps d'état. Chaque ligne porte un produit réellement vendu par l'un de vos huit fournisseurs, avec sa marque, ses références, son prix d'achat HT horodaté et le lien vers la fiche. Les colonnes « Conditionnement » et « Point de contrôle » signalent ce qui reste à arbitrer.
B10: Prix retenu | C10: La colonne « Prix achat HT » contient toujours le meilleur prix disponible : votre tarif négocié quand vos comptes le donnent, sinon le prix public relevé. La colonne « Type de prix » précise lequel, et « Remise » chiffre l'écart quand les deux sont connus.
B11: Vos comptes pro | C11: Huit fournisseurs interrogés le même jour. Vos tarifs de compte : Point.P (fichier tarif de l'agence Aubervilliers, 58 250 références), YESSS Électrique (export de 14 rubriques), Rexel (n° 6564380), La Plateforme du Bâtiment (dépôt Aubervilliers), Prolians (Paris Aubervilliers) et SFIC (Pantin). Prix publics : Au Forum du Bâtiment, Chausson Matériaux et Icilux. Ces prix sont vos conditions commerciales : ils restent internes et ne figurent jamais sur un PDF client.
B12: Contrôles avant devis | C12: La feuille « Contrôles qualité » liste chaque ligne qui demande un arbitrage : unité fournisseur différente de votre unité de métré, prix donné pour un conditionnement complet, ou correspondance article/produit encore imparfaite. À traiter avant toute reprise en devis client.
B13: Aucun prix estimé | C13: Aucun prix moyen, indicatif ou reconstitué n'existe dans ce fichier. Une ligne sans prix vérifié reste vide et part en feuille « 99 · À compléter ».
B14: Marges et prix de vente | C14: Les colonnes Marge % et Prix vente HT sont volontairement vides. Saisissez une marge et le prix de vente se calcule automatiquement sur la ligne.
B15: TVA | C15: 20 % par défaut sur les fournitures. Les taux 10 % et 5,5 % s'appliquent à la prestation posée selon la nature des travaux et l'ancienneté du bâtiment, attestation client à l'appui.
B16: Gel des prix | C16: Les prix sont horodatés. Dès qu'un devis est validé, son prix doit être figé (pricing_snapshot) : une évolution ultérieure du catalogue ne modifie jamais un devis déjà validé.
B18: CODE COULEUR
B19: Votre tarif de compte | C19: Prix négocié issu de vos comptes Point.P, YESSS, Rexel, La Plateforme, Prolians ou SFIC.
B20: À vérifier / à valider | C20: Prix réel relevé, mais la correspondance avec votre libellé interne est partielle : ouvrir la fiche avant de l'utiliser en devis.
B21: À compléter | C21: Aucun produit correspondant trouvé chez vos huit fournisseurs.
B22: Prix public | C22: Relevé chez Au Forum du Bâtiment, Chausson Matériaux ou Icilux.

Sheet Recherche
A1: RECHERCHE D'UN ARTICLE
A2: Tapez un mot en B4 (ex. « disjoncteur », « BA13 », « mitigeur ») : toutes les offres correspondantes s'affichent, tous fournisseurs confondus. Pour un même article, l'offre la moins chère apparaît en premier.
A4: Je cherche : | B4: disjoncteur | E4: La recherche porte sur l'article ET sur la désignation du fournisseur.
A6: Article | B6: Fournisseur | C6: Prix HT | D6: Type de prix | E6: Désignation fournisseur | F6: Réf. | G6: Unité de vente | H6: Retrait / disponibilité | I6: Fiabilité | J6: Lot
A7: =IFERROR(IF(INDEX('Base articles'!$D$2:$D$1153,MATCH(1,'Base articles'!$T$2:$T$1153,0))="","",INDEX('Base articles'!$D$2:$D$1153,MATCH(1,'Base articles'!$T$2:$T$1153,0))),"") -> Disjoncteur ph+N 10 A courbe C | B7: =IFERROR(IF(INDEX('Base articles'!$F$2:$F$1153,MATCH(1,'Base articles'!$T$2:$T$1153,0))="","",INDEX('Base articles'!$F$2:$F$1153,MATCH(1,'Base articles'!$T$2:$T$1153,0))),"") -> Au Forum du Bâtiment | C7: =IFERROR(INDEX('Base articles'!$H$2:$H$1153,MATCH(1,'Base articles'!$T$2:$T$1153,0)),"") -> 8.46 | D7: =IFERROR(IF(INDEX('Base articles'!$G$2:$G$1153,MATCH(1,'Base articles'!$T$2:$T$1153,0))="","",INDEX('Base articles'!$G$2:$G$1153,MATCH(1,'Base articles'!$T$2:$T$1153,0))),"") -> Prix public HT | E7: =IFERROR(IF(INDEX('Base articles'!$K$2:$K$1153,MATCH(1,'Base articles'!$T$2:$T$1153,0))="","",INDEX('Base articles'!$K$2:$K$1153,MATCH(1,'Base articles'!$T$2:$T$1153,0))),"") -> Disjoncteur FIXMATIC AUTO 10 A courbe C Phase + Neutre GEWISS GW90606F | F7: =IFERROR(IF(INDEX('Base articles'!$M$2:$M$1153,MATCH(1,'Base articles'!$T$2:$T$1153,0))="","",INDEX('Base articles'!$M$2:$M$1153,MATCH(1,'Base articles'!$T$2:$T$1153,0))),"") -> 753206 | G7: =IFERROR(IF(INDEX('Base articles'!$N$2:$N$1153,MATCH(1,'Base articles'!$T$2:$T$1153,0))="","",INDEX('Base articles'!$N$2:$N$1153,MATCH(1,'Base articles'!$T$2:$T$1153,0))),"") -> u | H7: =IFERROR(IF(INDEX('Base articles'!$P$2:$P$1153,MATCH(1,'Base articles'!$T$2:$T$1153,0))="","",INDEX('Base articles'!$P$2:$P$1153,MATCH(1,'Base articles'!$T$2:$T$1153,0))),"") -> Retrait agence · Livraison selon agence | I7: =IFERROR(IF(INDEX('Base articles'!$Q$2:$Q$1153,MATCH(1,'Base articles'!$T$2:$T$1153,0))="","",INDEX('Base articles'!$Q$2:$Q$1153,MATCH(1,'Base articles'!$T$2:$T$1153,0))),"") -> Élevée | J7: =IFERROR(IF(INDEX('Base articles'!$B$2:$B$1153,MATCH(1,'Base articles'!$T$2:$T$1153,0))="","",INDEX('Base articles'!$B$2:$B$1153,MATCH(1,'Base articles'!$T$2:$T$1153,0))),"") -> 01 · Électricité CFO
A8: =IFERROR(IF(INDEX('Base articles'!$D$2:$D$1153,MATCH(2,'Base articles'!$T$2:$T$1153,0))="","",INDEX('Base articles'!$D$2:$D$1153,MATCH(2,'Base articles'!$T$2:$T$1153,0))),"") -> Disjoncteur ph+N 10 A courbe C | B8: =IFERROR(IF(INDEX('Base articles'!$F$2:$F$1153,MATCH(2,'Base articles'!$T$2:$T$1153,0))="","",INDEX('Base articles'!$F$2:$F$1153,MATCH(2,'Base articles'!$T$2:$T$1153,0))),"") -> Rexel | C8: =IFERROR(INDEX('Base articles'!$H$2:$H$1153,MATCH(2,'Base articles'!$T$2:$T$1153,0)),"") -> 8.78 | D8: =IFERROR(IF(INDEX('Base articles'!$G$2:$G$1153,MATCH(2,'Base articles'!$T$2:$T$1153,0))="","",INDEX('Base articles'!$G$2:$G$1153,MATCH(2,'Base articles'!$T$2:$T$1153,0))),"") -> Votre tarif client | E8: =IFERROR(IF(INDEX('Base articles'!$K$2:$K$1153,MATCH(2,'Base articles'!$T$2:$T$1153,0))="","",INDEX('Base articles'!$K$2:$K$1153,MATCH(2,'Base articles'!$T$2:$T$1153,0))),"") -> HAGER Disjoncteur Phase + Neutre 10A 3kA Courbe C bornes à vis 1 Module | F8: =IFERROR(IF(INDEX('Base articles'!$M$2:$M$1153,MATCH(2,'Base articles'!$T$2:$T$1153,0))="","",INDEX('Base articles'!$M$2:$M$1153,MATCH(2,'Base articles'!$T$2:$T$1153,0))),"") -> HAGMFN710 | G8: =IFERROR(IF(INDEX('Base articles'!$N$2:$N$1153,MATCH(2,'Base articles'!$T$2:$T$1153,0))="","",INDEX('Base articles'!$N$2:$N$1153,MATCH(2,'Base articles'!$T$2:$T$1153,0))),"") | H8: =IFERROR(IF(INDEX('Base articles'!$P$2:$P$1153,MATCH(2,'Base articles'!$T$2:$T$1153,0))="","",INDEX('Base articles'!$P$2:$P$1153,MATCH(2,'Base articles'!$T$2:$T$1153,0))),"") -> Retrait agence · Livraison selon agence | I8: =IFERROR(IF(INDEX('Base articles'!$Q$2:$Q$1153,MATCH(2,'Base articles'!$T$2:$T$1153,0))="","",INDEX('Base articles'!$Q$2:$Q$1153,MATCH(2,'Base articles'!$T$2:$T$1153,0))),"") -> Votre tarif — Rexel | J8: =IFERROR(IF(INDEX('Base articles'!$B$2:$B$1153,MATCH(2,'Base articles'!$T$2:$T$1153,0))="","",INDEX('Base articles'!$B$2:$B$1153,MATCH(2,'Base articles'!$T$2:$T$1153,0))),"") -> 01 · Électricité CFO
A9: =IFERROR(IF(INDEX('Base articles'!$D$2:$D$1153,MATCH(3,'Base articles'!$T$2:$T$1153,0))="","",INDEX('Base articles'!$D$2:$D$1153,MATCH(3,'Base articles'!$T$2:$T$1153,0))),"") -> Disjoncteur ph+N 16 A courbe C | B9: =IFERROR(IF(INDEX('Base articles'!$F$2:$F$1153,MATCH(3,'Base articles'!$T$2:$T$1153,0))="","",INDEX('Base articles'!$F$2:$F$1153,MATCH(3,'Base articles'!$T$2:$T$1153,0))),"") -> Rexel | C9: =IFERROR(INDEX('Base articles'!$H$2:$H$1153,MATCH(3,'Base articles'!$T$2:$T$1153,0)),"") -> 6.89 | D9: =IFERROR(IF(INDEX('Base articles'!$G$2:$G$1153,MATCH(3,'Base articles'!$T$2:$T$1153,0))="","",INDEX('Base articles'!$G$2:$G$1153,MATCH(3,'Base articles'!$T$2:$T$1153,0))),"") -> Votre tarif client | E9: =IFERROR(IF(INDEX('Base articles'!$K$2:$K$1153,MATCH(3,'Base articles'!$T$2:$T$1153,0))="","",INDEX('Base articles'!$K$2:$K$1153,MATCH(3,'Base articles'!$T$2:$T$1153,0))),"") -> ABB SN201L Disjoncteur modulaire - 1P+N - 16A - courbe C - 4500A/6kA - peignable | F9: =IFERROR(IF(INDEX('Base articles'!$M$2:$M$1153,MATCH(3,'Base articles'!$T$2:$T$1153,0))="","",INDEX('Base articles'!$M$2:$M$1153,MATCH(3,'Base articles'!$T$2:$T$1153,0))),"") -> ABB470238 | G9: =IFERROR(IF(INDEX('Base articles'!$N$2:$N$1153,MATCH(3,'Base articles'!$T$2:$T$1153,0))="","",INDEX('Base articles'!$N$2:$N$1153,MATCH(3,'Base articles'!$T$2:$T$1153,0))),"") -> u | H9: =IFERROR(IF(INDEX('Base articles'!$P$2:$P$1153,MATCH(3,'Base articles'!$T$2:$T$1153,0))="","",INDEX('Base articles'!$P$2:$P$1153,MATCH(3,'Base articles'!$T$2:$T$1153,0))),"") -> Retrait agence · Livraison selon agence | I9: =IFERROR(IF(INDEX('Base articles'!$Q$2:$Q$1153,MATCH(3,'Base articles'!$T$2:$T$1153,0))="","",INDEX('Base articles'!$Q$2:$Q$1153,MATCH(3,'Base articles'!$T$2:$T$1153,0))),"") -> Votre tarif — Rexel | J9: =IFERROR(IF(INDEX('Base articles'!$B$2:$B$1153,MATCH(3,'Base articles'!$T$2:$T$1153,0))="","",INDEX('Base articles'!$B$2:$B$1153,MATCH(3,'Base articles'!$T$2:$T$1153,0))),"") -> 01 · Électricité CFO
A10: =IFERROR(IF(INDEX('Base articles'!$D$2:$D$1153,MATCH(4,'Base articles'!$T$2:$T$1153,0))="","",INDEX('Base articles'!$D$2:$D$1153,MATCH(4,'Base articles'!$T$2:$T$1153,0))),"") -> Disjoncteur ph+N 16 A courbe C | B10: =IFERROR(IF(INDEX('Base articles'!$F$2:$F$1153,MATCH(4,'Base articles'!$T$2:$T$1153,0))="","",INDEX('Base articles'!$F$2:$F$1153,MATCH(4,'Base articles'!$T$2:$T$1153,0))),"") -> Au Forum du Bâtiment | C10: =IFERROR(INDEX('Base articles'!$H$2:$H$1153,MATCH(4,'Base articles'!$T$2:$T$1153,0)),"") -> 8.09 | D10: =IFERROR(IF(INDEX('Base articles'!$G$2:$G$1153,MATCH(4,'Base articles'!$T$2:$T$1153,0))="","",INDEX('Base articles'!$G$2:$G$1153,MATCH(4,'Base articles'!$T$2:$T$1153,0))),"") -> Prix public HT | E10: =IFERROR(IF(INDEX('Base articles'!$K$2:$K$1153,MATCH(4,'Base articles'!$T$2:$T$1153,0))="","",INDEX('Base articles'!$K$2:$K$1153,MATCH(4,'Base articles'!$T$2:$T$1153,0))),"") -> Disjoncteur 16 A courbe C Phase + neutre GEWISS GW90607 | F10: =IFERROR(IF(INDEX('Base articles'!$M$2:$M$1153,MATCH(4,'Base articles'!$T$2:$T$1153,0))="","",INDEX('Base articles'!$M$2:$M$1153,MATCH(4,'Base articles'!$T$2:$T$1153,0))),"") -> 753207 | G10: =IFERROR(IF(INDEX('Base articles'!$N$2:$N$1153,MATCH(4,'Base articles'!$T$2:$T$1153,0))="","",INDEX('Base articles'!$N$2:$N$1153,MATCH(4,'Base articles'!$T$2:$T$1153,0))),"") -> u | H10: =IFERROR(IF(INDEX('Base articles'!$P$2:$P$1153,MATCH(4,'Base articles'!$T$2:$T$1153,0))="","",INDEX('Base articles'!$P$2:$P$1153,MATCH(4,'Base articles'!$T$2:$T$1153,0))),"") -> Retrait agence · Livraison selon agence | I10: =IFERROR(IF(INDEX('Base articles'!$Q$2:$Q$1153,MATCH(4,'Base articles'!$T$2:$T$1153,0))="","",INDEX('Base articles'!$Q$2:$Q$1153,MATCH(4,'Base articles'!$T$2:$T$1153,0))),"") -> Élevée | J10: =IFERROR(IF(INDEX('Base articles'!$B$2:$B$1153,MATCH(4,'Base articles'!$T$2:$T$1153,0))="","",INDEX('Base articles'!$B$2:$B$1153,MATCH(4,'Base articles'!$T$2:$T$1153,0))),"") -> 01 · Électricité CFO
A11: =IFERROR(IF(INDEX('Base articles'!$D$2:$D$1153,MATCH(5,'Base articles'!$T$2:$T$1153,0))="","",INDEX('Base articles'!$D$2:$D$1153,MATCH(5,'Base articles'!$T$2:$T$1153,0))),"") -> Disjoncteur ph+N 20 A courbe C | B11: =IFERROR(IF(INDEX('Base articles'!$F$2:$F$1153,MATCH(5,'Base articles'!$T$2:$T$1153,0))="","",INDEX('Base articles'!$F$2:$F$1153,MATCH(5,'Base articles'!$T$2:$T$1153,0))),"") -> Au Forum du Bâtiment | C11: =IFERROR(INDEX('Base articles'!$H$2:$H$1153,MATCH(5,'Base articles'!$T$2:$T$1153,0)),"") -> 5.9 | D11: =IFERROR(IF(INDEX('Base articles'!$G$2:$G$1153,MATCH(5,'Base articles'!$T$2:$T$1153,0))="","",INDEX('Base articles'!$G$2:$G$1153,MATCH(5,'Base articles'!$T$2:$T$1153,0))),"") -> Prix public HT | E11: =IFERROR(IF(INDEX('Base articles'!$K$2:$K$1153,MATCH(5,'Base articles'!$T$2:$T$1153,0))="","",INDEX('Base articles'!$K$2:$K$1153,MATCH(5,'Base articles'!$T$2:$T$1153,0))),"") -> Disjoncteur 20 A courbe C Phase + neutre GEWISS GW90608 | F11: =IFERROR(IF(INDEX('Base articles'!$M$2:$M$1153,MATCH(5,'Base articles'!$T$2:$T$1153,0))="","",INDEX('Base articles'!$M$2:$M$1153,MATCH(5,'Base articles'!$T$2:$T$1153,0))),"") -> 753209 | G11: =IFERROR(IF(INDEX('Base articles'!$N$2:$N$1153,MATCH(5,'Base articles'!$T$2:$T$1153,0))="","",INDEX('Base articles'!$N$2:$N$1153,MATCH(5,'Base articles'!$T$2:$T$1153,0))),"") -> u | H11: =IFERROR(IF(INDEX('Base articles'!$P$2:$P$1153,MATCH(5,'Base articles'!$T$2:$T$1153,0))="","",INDEX('Base articles'!$P$2:$P$1153,MATCH(5,'Base articles'!$T$2:$T$1153,0))),"") -> Retrait agence · Livraison selon agence | I11: =IFERROR(IF(INDEX('Base articles'!$Q$2:$Q$1153,MATCH(5,'Base articles'!$T$2:$T$1153,0))="","",INDEX('Base articles'!$Q$2:$Q$1153,MATCH(5,'Base articles'!$T$2:$T$1153,0))),"") -> Élevée | J11: =IFERROR(IF(INDEX('Base articles'!$B$2:$B$1153,MATCH(5,'Base articles'!$T$2:$T$1153,0))="","",INDEX('Base articles'!$B$2:$B$1153,MATCH(5,'Base articles'!$T$2:$T$1153,0))),"") -> 01 · Électricité CFO
A12: =IFERROR(IF(INDEX('Base articles'!$D$2:$D$1153,MATCH(6,'Base articles'!$T$2:$T$1153,0))="","",INDEX('Base articles'!$D$2:$D$1153,MATCH(6,'Base articles'!$T$2:$T$1153,0))),"") -> Disjoncteur ph+N 20 A courbe C | B12: =IFERROR(IF(INDEX('Base articles'!$F$2:$F$1153,MATCH(6,'Base articles'!$T$2:$T$1153,0))="","",INDEX('Base articles'!$F$2:$F$1153,MATCH(6,'Base articles'!$T$2:$T$1153,0))),"") -> Rexel | C12: =IFERROR(INDEX('Base articles'!$H$2:$H$1153,MATCH(6,'Base articles'!$T$2:$T$1153,0)),"") -> 6.82 | D12: =IFERROR(IF(INDEX('Base articles'!$G$2:$G$1153,MATCH(6,'Base articles'!$T$2:$T$1153,0))="","",INDEX('Base articles'!$G$2:$G$1153,MATCH(6,'Base articles'!$T$2:$T$1153,0))),"") -> Votre tarif client | E12: =IFERROR(IF(INDEX('Base articles'!$K$2:$K$1153,MATCH(6,'Base articles'!$T$2:$T$1153,0))="","",INDEX('Base articles'!$K$2:$K$1153,MATCH(6,'Base articles'!$T$2:$T$1153,0))),"") -> ABB SN201SL Disjoncteur modulaire - 1P+N - 20A - courbe C- 4500A/6kA-peignable-Auto | F12: =IFERROR(IF(INDEX('Base articles'!$M$2:$M$1153,MATCH(6,'Base articles'!$T$2:$T$1153,0))="","",INDEX('Base articles'!$M$2:$M$1153,MATCH(6,'Base articles'!$T$2:$T$1153,0))),"") -> ABB470439 | G12: =IFERROR(IF(INDEX('Base articles'!$N$2:$N$1153,MATCH(6,'Base articles'!$T$2:$T$1153,0))="","",INDEX('Base articles'!$N$2:$N$1153,MATCH(6,'Base articles'!$T$2:$T$1153,0))),"") | H12: =IFERROR(IF(INDEX('Base articles'!$P$2:$P$1153,MATCH(6,'Base articles'!$T$2:$T$1153,0))="","",INDEX('Base articles'!$P$2:$P$1153,MATCH(6,'Base articles'!$T$2:$T$1153,0))),"") -> Retrait agence · Livraison selon agence | I12: =IFERROR(IF(INDEX('Base articles'!$Q$2:$Q$1153,MATCH(6,'Base articles'!$T$2:$T$1153,0))="","",INDEX('Base articles'!$Q$2:$Q$1153,MATCH(6,'Base articles'!$T$2:$T$1153,0))),"") -> Votre tarif — Rexel | J12: =IFERROR(IF(INDEX('Base articles'!$B$2:$B$1153,MATCH(6,'Base articles'!$T$2:$T$1153,0))="","",INDEX('Base articles'!$B$2:$B$1153,MATCH(6,'Base articles'!$T$2:$T$1153,0))),"") -> 01 · Électricité CFO
A13: =IFERROR(IF(INDEX('Base articles'!$D$2:$D$1153,MATCH(7,'Base articles'!$T$2:$T$1153,0))="","",INDEX('Base articles'!$D$2:$D$1153,MATCH(7,'Base articles'!$T$2:$T$1153,0))),"") -> Disjoncteur ph+N 32 A courbe C | B13: =IFERROR(IF(INDEX('Base articles'!$F$2:$F$1153,MATCH(7,'Base articles'!$T$2:$T$1153,0))="","",INDEX('Base articles'!$F$2:$F$1153,MATCH(7,'Base articles'!$T$2:$T$1153,0))),"") -> Au Forum du Bâtiment | C13: =IFERROR(INDEX('Base articles'!$H$2:$H$1153,MATCH(7,'Base articles'!$T$2:$T$1153,0)),"") -> 10.61 | D13: =IFERROR(IF(INDEX('Base articles'!$G$2:$G$1153,MATCH(7,'Base articles'!$T$2:$T$1153,0))="","",INDEX('Base articles'!$G$2:$G$1153,MATCH(7,'Base articles'!$T$2:$T$1153,0))),"") -> Prix public HT | E13: =IFERROR(IF(INDEX('Base articles'!$K$2:$K$1153,MATCH(7,'Base articles'!$T$2:$T$1153,0))="","",INDEX('Base articles'!$K$2:$K$1153,MATCH(7,'Base articles'!$T$2:$T$1153,0))),"") -> Disjoncteur 32 A courbe C Phase + neutre GEWISS GW90610 | F13: =IFERROR(IF(INDEX('Base articles'!$M$2:$M$1153,MATCH(7,'Base articles'!$T$2:$T$1153,0))="","",INDEX('Base articles'!$M$2:$M$1153,MATCH(7,'Base articles'!$T$2:$T$1153,0))),"") -> 753211 | G13: =IFERROR(IF(INDEX('Base articles'!$N$2:$N$1153,MATCH(7,'Base articles'!$T$2:$T$1153,0))="","",INDEX('Base articles'!$N$2:$N$1153,MATCH(7,'Base articles'!$T$2:$T$1153,0))),"") -> u | H13: =IFERROR(IF(INDEX('Base articles'!$P$2:$P$1153,MATCH(7,'Base articles'!$T$2:$T$1153,0))="","",INDEX('Base articles'!$P$2:$P$1153,MATCH(7,'Base articles'!$T$2:$T$1153,0))),"") -> Retrait agence · Livraison selon agence | I13: =IFERROR(IF(INDEX('Base articles'!$Q$2:$Q$1153,MATCH(7,'Base articles'!$T$2:$T$1153,0))="","",INDEX('Base articles'!$Q$2:$Q$1153,MATCH(7,'Base articles'!$T$2:$T$1153,0))),"") -> Élevée | J13: =IFERROR(IF(INDEX('Base articles'!$B$2:$B$1153,MATCH(7,'Base articles'!$T$2:$T$1153,0))="","",INDEX('Base articles'!$B$2:$B$1153,MATCH(7,'Base articles'!$T$2:$T$1153,0))),"") -> 01 · Électricité CFO
A14: =IFERROR(IF(INDEX('Base articles'!$D$2:$D$1153,MATCH(8,'Base articles'!$T$2:$T$1153,0))="","",INDEX('Base articles'!$D$2:$D$1153,MATCH(8,'Base articles'!$T$2:$T$1153,0))),"") -> Disjoncteur ph+N 32 A courbe C | B14: =IFERROR(IF(INDEX('Base articles'!$F$2:$F$1153,MATCH(8,'Base articles'!$T$2:$T$1153,0))="","",INDEX('Base articles'!$F$2:$F$1153,MATCH(8,'Base articles'!$T$2:$T$1153,0))),"") -> Rexel | C14: =IFERROR(INDEX('Base articles'!$H$2:$H$1153,MATCH(8,'Base articles'!$T$2:$T$1153,0)),"") -> 13.1 | D14: =IFERROR(IF(INDEX('Base articles'!$G$2:$G$1153,MATCH(8,'Base articles'!$T$2:$T$1153,0))="","",INDEX('Base articles'!$G$2:$G$1153,MATCH(8,'Base articles'!$T$2:$T$1153,0))),"") -> Votre tarif client | E14: =IFERROR(IF(INDEX('Base articles'!$K$2:$K$1153,MATCH(8,'Base articles'!$T$2:$T$1153,0))="","",INDEX('Base articles'!$K$2:$K$1153,MATCH(8,'Base articles'!$T$2:$T$1153,0))),"") -> HAGER Disjoncteur Phase + Neutre 32A 3kA Courbe C bornes à vis 1 Module | F14: =IFERROR(IF(INDEX('Base articles'!$M$2:$M$1153,MATCH(8,'Base articles'!$T$2:$T$1153,0))="","",INDEX('Base articles'!$M$2:$M$1153,MATCH(8,'Base articles'!$T$2:$T$1153,0))),"") -> HAGMFN732 | G14: =IFERROR(IF(INDEX('Base articles'!$N$2:$N$1153,MATCH(8,'Base articles'!$T$2:$T$1153,0))="","",INDEX('Base articles'!$N$2:$N$1153,MATCH(8,'Base articles'!$T$2:$T$1153,0))),"") | H14: =IFERROR(IF(INDEX('Base articles'!$P$2:$P$1153,MATCH(8,'Base articles'!$T$2:$T$1153,0))="","",INDEX('Base articles'!$P$2:$P$1153,MATCH(8,'Base articles'!$T$2:$T$1153,0))),"") -> Retrait agence · Livraison selon agence | I14: =IFERROR(IF(INDEX('Base articles'!$Q$2:$Q$1153,MATCH(8,'Base articles'!$T$2:$T$1153,0))="","",INDEX('Base articles'!$Q$2:$Q$1153,MATCH(8,'Base articles'!$T$2:$T$1153,0))),"") -> Votre tarif — Rexel | J14: =IFERROR(IF(INDEX('Base articles'!$B$2:$B$1153,MATCH(8,'Base articles'!$T$2:$T$1153,0))="","",INDEX('Base articles'!$B$2:$B$1153,MATCH(8,'Base articles'!$T$2:$T$1153,0))),"") -> 01 · Électricité CFO
A15: =IFERROR(IF(INDEX('Base articles'!$D$2:$D$1153,MATCH(9,'Base articles'!$T$2:$T$1153,0))="","",INDEX('Base articles'!$D$2:$D$1153,MATCH(9,'Base articles'!$T$2:$T$1153,0))),"") -> Disjoncteur tetrapolaire 4P 32 A courbe C | B15: =IFERROR(IF(INDEX('Base articles'!$F$2:$F$1153,MATCH(9,'Base articles'!$T$2:$T$1153,0))="","",INDEX('Base articles'!$F$2:$F$1153,MATCH(9,'Base articles'!$T$2:$T$1153,0))),"") -> Au Forum du Bâtiment | C15: =IFERROR(INDEX('Base articles'!$H$2:$H$1153,MATCH(9,'Base articles'!$T$2:$T$1153,0)),"") -> 107.92 | D15: =IFERROR(IF(INDEX('Base articles'!$G$2:$G$1153,MATCH(9,'Base articles'!$T$2:$T$1153,0))="","",INDEX('Base articles'!$G$2:$G$1153,MATCH(9,'Base articles'!$T$2:$T$1153,0))),"") -> Prix public HT | E15: =IFERROR(IF(INDEX('Base articles'!$K$2:$K$1153,MATCH(9,'Base articles'!$T$2:$T$1153,0))="","",INDEX('Base articles'!$K$2:$K$1153,MATCH(9,'Base articles'!$T$2:$T$1153,0))),"") -> Disjoncteur ACTI9 IC60N 4P courbe C 32 A SCHNEIDER ELECTRIC A9F77432 | F15: =IFERROR(IF(INDEX('Base articles'!$M$2:$M$1153,MATCH(9,'Base articles'!$T$2:$T$1153,0))="","",INDEX('Base articles'!$M$2:$M$1153,MATCH(9,'Base articles'!$T$2:$T$1153,0))),"") -> 610554 | G15: =IFERROR(IF(INDEX('Base articles'!$N$2:$N$1153,MATCH(9,'Base articles'!$T$2:$T$1153,0))="","",INDEX('Base articles'!$N$2:$N$1153,MATCH(9,'Base articles'!$T$2:$T$1153,0))),"") -> u | H15: =IFERROR(IF(INDEX('Base articles'!$P$2:$P$1153,MATCH(9,'Base articles'!$T$2:$T$1153,0))="","",INDEX('Base articles'!$P$2:$P$1153,MATCH(9,'Base articles'!$T$2:$T$1153,0))),"") -> Retrait agence · Livraison selon agence | I15: =IFERROR(IF(INDEX('Base articles'!$Q$2:$Q$1153,MATCH(9,'Base articles'!$T$2:$T$1153,0))="","",INDEX('Base articles'!$Q$2:$Q$1153,MATCH(9,'Base articles'!$T$2:$T$1153,0))),"") -> À vérifier | J15: =IFERROR(IF(INDEX('Base articles'!$B$2:$B$1153,MATCH(9,'Base articles'!$T$2:$T$1153,0))="","",INDEX('Base articles'!$B$2:$B$1153,MATCH(9,'Base articles'!$T$2:$T$1153,0))),"") -> 01 · Électricité CFO
A16: =IFERROR(IF(INDEX('Base articles'!$D$2:$D$1153,MATCH(10,'Base articles'!$T$2:$T$1153,0))="","",INDEX('Base articles'!$D$2:$D$1153,MATCH(10,'Base articles'!$T$2:$T$1153,0))),"") -> Disjoncteur differentiel 20 A 30 mA | B16: =IFERROR(IF(INDEX('Base articles'!$F$2:$F$1153,MATCH(10,'Base articles'!$T$2:$T$1153,0))="","",INDEX('Base articles'!$F$2:$F$1153,MATCH(10,'Base articles'!$T$2:$T$1153,0))),"") -> Rexel | C16: =IFERROR(INDEX('Base articles'!$H$2:$H$1153,MATCH(10,'Base articles'!$T$2:$T$1153,0)),"") -> 135.9 | D16: =IFERROR(IF(INDEX('Base articles'!$G$2:$G$1153,MATCH(10,'Base articles'!$T$2:$T$1153,0))="","",INDEX('Base articles'!$G$2:$G$1153,MATCH(10,'Base articles'!$T$2:$T$1153,0))),"") -> Votre tarif client | E16: =IFERROR(IF(INDEX('Base articles'!$K$2:$K$1153,MATCH(10,'Base articles'!$T$2:$T$1153,0))="","",INDEX('Base articles'!$K$2:$K$1153,MATCH(10,'Base articles'!$T$2:$T$1153,0))),"") -> LEGRAND Disjoncteur diff DX³ 4500 - vis/vis -U+N 230V~ 20A - typeAC -30mA -courbe C - 2M | F16: =IFERROR(IF(INDEX('Base articles'!$M$2:$M$1153,MATCH(10,'Base articles'!$T$2:$T$1153,0))="","",INDEX('Base articles'!$M$2:$M$1153,MATCH(10,'Base articles'!$T$2:$T$1153,0))),"") -> LEG410706 | G16: =IFERROR(IF(INDEX('Base articles'!$N$2:$N$1153,MATCH(10,'Base articles'!$T$2:$T$1153,0))="","",INDEX('Base articles'!$N$2:$N$1153,MATCH(10,'Base articles'!$T$2:$T$1153,0))),"") -> u | H16: =IFERROR(IF(INDEX('Base articles'!$P$2:$P$1153,MATCH(10,'Base articles'!$T$2:$T$1153,0))="","",INDEX('Base articles'!$P$2:$P$1153,MATCH(10,'Base articles'!$T$2:$T$1153,0))),"") -> Retrait agence · Livraison selon agence | I16: =IFERROR(IF(INDEX('Base articles'!$Q$2:$Q$1153,MATCH(10,'Base articles'!$T$2:$T$1153,0))="","",INDEX('Base articles'!$Q$2:$Q$1153,MATCH(10,'Base articles'!$T$2:$T$1153,0))),"") -> Votre tarif — Rexel | J16: =IFERROR(IF(INDEX('Base articles'!$B$2:$B$1153,MATCH(10,'Base articles'!$T$2:$T$1153,0))="","",INDEX('Base articles'!$B$2:$B$1153,MATCH(10,'Base articles'!$T$2:$T$1153,0))),"") -> 01 · Électricité CFO
A17: =IFERROR(IF(INDEX('Base articles'!$D$2:$D$1153,MATCH(11,'Base articles'!$T$2:$T$1153,0))="","",INDEX('Base articles'!$D$2:$D$1153,MATCH(11,'Base articles'!$T$2:$T$1153,0))),"") -> Disjoncteur differentiel 20 A 30 mA | B17: =IFERROR(IF(INDEX('Base articles'!$F$2:$F$1153,MATCH(11,'Base articles'!$T$2:$T$1153,0))="","",INDEX('Base articles'!$F$2:$F$1153,MATCH(11,'Base articles'!$T$2:$T$1153,0))),"") -> Au Forum du Bâtiment | C17: =IFERROR(INDEX('Base articles'!$H$2:$H$1153,MATCH(11,'Base articles'!$T$2:$T$1153,0)),"") -> 140.64 | D17: =IFERROR(IF(INDEX('Base articles'!$G$2:$G$1153,MATCH(11,'Base articles'!$T$2:$T$1153,0))="","",INDEX('Base articles'!$G$2:$G$1153,MATCH(11,'Base articles'!$T$2:$T$1153,0))),"") -> Prix public HT | E17: =IFERROR(IF(INDEX('Base articles'!$K$2:$K$1153,MATCH(11,'Base articles'!$T$2:$T$1153,0))="","",INDEX('Base articles'!$K$2:$K$1153,MATCH(11,'Base articles'!$T$2:$T$1153,0))),"") -> Disjoncteur différentiel RESI9 1P+N 30mA courbe C type Fsi 20A - SCHNEIDER ELECTRIC - R9PDCF20 | F17: =IFERROR(IF(INDEX('Base articles'!$M$2:$M$1153,MATCH(11,'Base articles'!$T$2:$T$1153,0))="","",INDEX('Base articles'!$M$2:$M$1153,MATCH(11,'Base articles'!$T$2:$T$1153,0))),"") -> 750704 | G17: =IFERROR(IF(INDEX('Base articles'!$N$2:$N$1153,MATCH(11,'Base articles'!$T$2:$T$1153,0))="","",INDEX('Base articles'!$N$2:$N$1153,MATCH(11,'Base articles'!$T$2:$T$1153,0))),"") -> u | H17: =IFERROR(IF(INDEX('Base articles'!$P$2:$P$1153,MATCH(11,'Base articles'!$T$2:$T$1153,0))="","",INDEX('Base articles'!$P$2:$P$1153,MATCH(11,'Base articles'!$T$2:$T$1153,0))),"") -> Retrait agence · Livraison selon agence | I17: =IFERROR(IF(INDEX('Base articles'!$Q$2:$Q$1153,MATCH(11,'Base articles'!$T$2:$T$1153,0))="","",INDEX('Base articles'!$Q$2:$Q$1153,MATCH(11,'Base articles'!$T$2:$T$1153,0))),"") -> Élevée | J17: =IFERROR(IF(INDEX('Base articles'!$B$2:$B$1153,MATCH(11,'Base articles'!$T$2:$T$1153,0))="","",INDEX('Base articles'!$B$2:$B$1153,MATCH(11,'Base articles'!$T$2:$T$1153,0))),"") -> 01 · Électricité CFO
A18: =IFERROR(IF(INDEX('Base articles'!$D$2:$D$1153,MATCH(12,'Base articles'!$T$2:$T$1153,0))="","",INDEX('Base articles'!$D$2:$D$1153,MATCH(12,'Base articles'!$T$2:$T$1153,0))),"") -> Disjoncteur differentiel 20 A 30 mA | B18: =IFERROR(IF(INDEX('Base articles'!$F$2:$F$1153,MATCH(12,'Base articles'!$T$2:$T$1153,0))="","",INDEX('Base articles'!$F$2:$F$1153,MATCH(12,'Base articles'!$T$2:$T$1153,0))),"") -> YESSS Électrique | C18: =IFERROR(INDEX('Base articles'!$H$2:$H$1153,MATCH(12,'Base articles'!$T$2:$T$1153,0)),"") -> 251.34 | D18: =IFERROR(IF(INDEX('Base articles'!$G$2:$G$1153,MATCH(12,'Base articles'!$T$2:$T$1153,0))="","",INDEX('Base articles'!$G$2:$G$1153,MATCH(12,'Base articles'!$T$2:$T$1153,0))),"") -> Votre tarif net | E18: =IFERROR(IF(INDEX('Base articles'!$K$2:$K$1153,MATCH(12,'Base articles'!$T$2:$T$1153,0))="","",INDEX('Base articles'!$K$2:$K$1153,MATCH(12,'Base articles'!$T$2:$T$1153,0))),"") -> Disjoncteur différentiel Uni+Neutre 230V~ 16A 30mA Mosaic 2 modules - blanc | F18: =IFERROR(IF(INDEX('Base articles'!$M$2:$M$1153,MATCH(12,'Base articles'!$T$2:$T$1153,0))="","",INDEX('Base articles'!$M$2:$M$1153,MATCH(12,'Base articles'!$T$2:$T$1153,0))),"") -> 077532 | G18: =IFERROR(IF(INDEX('Base articles'!$N$2:$N$1153,MATCH(12,'Base articles'!$T$2:$T$1153,0))="","",INDEX('Base articles'!$N$2:$N$1153,MATCH(12,'Base articles'!$T$2:$T$1153,0))),"") -> u | H18: =IFERROR(IF(INDEX('Base articles'!$P$2:$P$1153,MATCH(12,'Base articles'!$T$2:$T$1153,0))="","",INDEX('Base articles'!$P$2:$P$1153,MATCH(12,'Base articles'!$T$2:$T$1153,0))),"") -> Retrait agence Aubervilliers · Livraison selon agence | I18: =IFERROR(IF(INDEX('Base articles'!$Q$2:$Q$1153,MATCH(12,'Base articles'!$T$2:$T$1153,0))="","",INDEX('Base articles'!$Q$2:$Q$1153,MATCH(12,'Base articles'!$T$2:$T$1153,0))),"") -> Votre tarif — YESSS Électrique | J18: =IFERROR(IF(INDEX('Base articles'!$B$2:$B$1153,MATCH(12,'Base articles'!$T$2:$T$1153,0))="","",INDEX('Base articles'!$B$2:$B$1153,MATCH(12,'Base articles'!$T$2:$T$1153,0))),"") -> 01 · Électricité CFO
A19: =IFERROR(IF(INDEX('Base articles'!$D$2:$D$1153,MATCH(13,'Base articles'!$T$2:$T$1153,0))="","",INDEX('Base articles'!$D$2:$D$1153,MATCH(13,'Base articles'!$T$2:$T$1153,0))),"") -> Borne de connexion automatique 3 entrees | B19: =IFERROR(IF(INDEX('Base articles'!$F$2:$F$1153,MATCH(13,'Base articles'!$T$2:$T$1153,0))="","",INDEX('Base articles'!$F$2:$F$1153,MATCH(13,'Base articles'!$T$2:$T$1153,0))),"") -> YESSS Électrique | C19: =IFERROR(INDEX('Base articles'!$H$2:$H$1153,MATCH(13,'Base articles'!$T$2:$T$1153,0)),"") -> 48.01 | D19: =IFERROR(IF(INDEX('Base articles'!$G$2:$G$1153,MATCH(13,'Base articles'!$T$2:$T$1153,0))="","",INDEX('Base articles'!$G$2:$G$1153,MATCH(13,'Base articles'!$T$2:$T$1153,0))),"") -> Votre tarif net | E19: =IFERROR(IF(INDEX('Base articles'!$K$2:$K$1153,MATCH(13,'Base articles'!$T$2:$T$1153,0))="","",INDEX('Base articles'!$K$2:$K$1153,MATCH(13,'Base articles'!$T$2:$T$1153,0))),"") -> Borne de raccordement pour disjoncteur DX³ 3P+N à connexion automatique - section 6mm² à 25mm² - IP2X | F19: =IFERROR(IF(INDEX('Base articles'!$M$2:$M$1153,MATCH(13,'Base articles'!$T$2:$T$1153,0))="","",INDEX('Base articles'!$M$2:$M$1153,MATCH(13,'Base articles'!$T$2:$T$1153,0))),"") -> 405206 | G19: =IFERROR(IF(INDEX('Base articles'!$N$2:$N$1153,MATCH(13,'Base articles'!$T$2:$T$1153,0))="","",INDEX('Base articles'!$N$2:$N$1153,MATCH(13,'Base articles'!$T$2:$T$1153,0))),"") -> u | H19: =IFERROR(IF(INDEX('Base articles'!$P$2:$P$1153,MATCH(13,'Base articles'!$T$2:$T$1153,0))="","",INDEX('Base articles'!$P$2:$P$1153,MATCH(13,'Base articles'!$T$2:$T$1153,0))),"") -> Retrait agence Aubervilliers · Livraison selon agence | I19: =IFERROR(IF(INDEX('Base articles'!$Q$2:$Q$1153,MATCH(13,'Base articles'!$T$2:$T$1153,0))="","",INDEX('Base articles'!$Q$2:$Q$1153,MATCH(13,'Base articles'!$T$2:$T$1153,0))),"") -> Votre tarif — YESSS Électrique | J19: =IFERROR(IF(INDEX('Base articles'!$B$2:$B$1153,MATCH(13,'Base articles'!$T$2:$T$1153,0))="","",INDEX('Base articles'!$B$2:$B$1153,MATCH(13,'Base articles'!$T$2:$T$1153,0))),"") -> 01 · Électricité CFO
A20: =IFERROR(IF(INDEX('Base articles'!$D$2:$D$1153,MATCH(14,'Base articles'!$T$2:$T$1153,0))="","",INDEX('Base articles'!$D$2:$D$1153,MATCH(14,'Base articles'!$T$2:$T$1153,0))),"") | B20: =IFERROR(IF(INDEX('Base articles'!$F$2:$F$1153,MATCH(14,'Base articles'!$T$2:$T$1153,0))="","",INDEX('Base articles'!$F$2:$F$1153,MATCH(14,'Base articles'!$T$2:$T$1153,0))),"") | C20: =IFERROR(INDEX('Base articles'!$H$2:$H$1153,MATCH(14,'Base articles'!$T$2:$T$1153,0)),"") | D20: =IFERROR(IF(INDEX('Base articles'!$G$2:$G$1153,MATCH(14,'Base articles'!$T$2:$T$1153,0))="","",INDEX('Base articles'!$G$2:$G$1153,MATCH(14,'Base articles'!$T$2:$T$1153,0))),"") | E20: =IFERROR(IF(INDEX('Base articles'!$K$2:$K$1153,MATCH(14,'Base articles'!$T$2:$T$1153,0))="","",INDEX('Base articles'!$K$2:$K$1153,MATCH(14,'Base articles'!$T$2:$T$1153,0))),"") | F20: =IFERROR(IF(INDEX('Base articles'!$M$2:$M$1153,MATCH(14,'Base articles'!$T$2:$T$1153,0))="","",INDEX('Base articles'!$M$2:$M$1153,MATCH(14,'Base articles'!$T$2:$T$1153,0))),"") | G20: =IFERROR(IF(INDEX('Base articles'!$N$2:$N$1153,MATCH(14,'Base articles'!$T$2:$T$1153,0))="","",INDEX('Base articles'!$N$2:$N$1153,MATCH(14,'Base articles'!$T$2:$T$1153,0))),"") | H20: =IFERROR(IF(INDEX('Base articles'!$P$2:$P$1153,MATCH(14,'Base articles'!$T$2:$T$1153,0))="","",INDEX('Base articles'!$P$2:$P$1153,MATCH(14,'Base articles'!$T$2:$T$1153,0))),"") | I20: =IFERROR(IF(INDEX('Base articles'!$Q$2:$Q$1153,MATCH(14,'Base articles'!$T$2:$T$1153,0))="","",INDEX('Base articles'!$Q$2:$Q$1153,MATCH(14,'Base articles'!$T$2:$T$1153,0))),"") | J20: =IFERROR(IF(INDEX('Base articles'!$B$2:$B$1153,MATCH(14,'Base articles'!$T$2:$T$1153,0))="","",INDEX('Base articles'!$B$2:$B$1153,MATCH(14,'Base articles'!$T$2:$T$1153,0))),"")
A21: =IFERROR(IF(INDEX('Base articles'!$D$2:$D$1153,MATCH(15,'Base articles'!$T$2:$T$1153,0))="","",INDEX('Base articles'!$D$2:$D$1153,MATCH(15,'Base articles'!$T$2:$T$1153,0))),"") | B21: =IFERROR(IF(INDEX('Base articles'!$F$2:$F$1153,MATCH(15,'Base articles'!$T$2:$T$1153,0))="","",INDEX('Base articles'!$F$2:$F$1153,MATCH(15,'Base articles'!$T$2:$T$1153,0))),"") | C21: =IFERROR(INDEX('Base articles'!$H$2:$H$1153,MATCH(15,'Base articles'!$T$2:$T$1153,0)),"") | D21: =IFERROR(IF(INDEX('Base articles'!$G$2:$G$1153,MATCH(15,'Base articles'!$T$2:$T$1153,0))="","",INDEX('Base articles'!$G$2:$G$1153,MATCH(15,'Base articles'!$T$2:$T$1153,0))),"") | E21: =IFERROR(IF(INDEX('Base articles'!$K$2:$K$1153,MATCH(15,'Base articles'!$T$2:$T$1153,0))="","",INDEX('Base articles'!$K$2:$K$1153,MATCH(15,'Base articles'!$T$2:$T$1153,0))),"") | F21: =IFERROR(IF(INDEX('Base articles'!$M$2:$M$1153,MATCH(15,'Base articles'!$T$2:$T$1153,0))="","",INDEX('Base articles'!$M$2:$M$1153,MATCH(15,'Base articles'!$T$2:$T$1153,0))),"") | G21: =IFERROR(IF(INDEX('Base articles'!$N$2:$N$1153,MATCH(15,'Base articles'!$T$2:$T$1153,0))="","",INDEX('Base articles'!$N$2:$N$1153,MATCH(15,'Base articles'!$T$2:$T$1153,0))),"") | H21: =IFERROR(IF(INDEX('Base articles'!$P$2:$P$1153,MATCH(15,'Base articles'!$T$2:$T$1153,0))="","",INDEX('Base articles'!$P$2:$P$1153,MATCH(15,'Base articles'!$T$2:$T$1153,0))),"") | I21: =IFERROR(IF(INDEX('Base articles'!$Q$2:$Q$1153,MATCH(15,'Base articles'!$T$2:$T$1153,0))="","",INDEX('Base articles'!$Q$2:$Q$1153,MATCH(15,'Base articles'!$T$2:$T$1153,0))),"") | J21: =IFERROR(IF(INDEX('Base articles'!$B$2:$B$1153,MATCH(15,'Base articles'!$T$2:$T$1153,0))="","",INDEX('Base articles'!$B$2:$B$1153,MATCH(15,'Base articles'!$T$2:$T$1153,0))),"")
A22: =IFERROR(IF(INDEX('Base articles'!$D$2:$D$1153,MATCH(16,'Base articles'!$T$2:$T$1153,0))="","",INDEX('Base articles'!$D$2:$D$1153,MATCH(16,'Base articles'!$T$2:$T$1153,0))),"") | B22: =IFERROR(IF(INDEX('Base articles'!$F$2:$F$1153,MATCH(16,'Base articles'!$T$2:$T$1153,0))="","",INDEX('Base articles'!$F$2:$F$1153,MATCH(16,'Base articles'!$T$2:$T$1153,0))),"") | C22: =IFERROR(INDEX('Base articles'!$H$2:$H$1153,MATCH(16,'Base articles'!$T$2:$T$1153,0)),"") | D22: =IFERROR(IF(INDEX('Base articles'!$G$2:$G$1153,MATCH(16,'Base articles'!$T$2:$T$1153,0))="","",INDEX('Base articles'!$G$2:$G$1153,MATCH(16,'Base articles'!$T$2:$T$1153,0))),"") | E22: =IFERROR(IF(INDEX('Base articles'!$K$2:$K$1153,MATCH(16,'Base articles'!$T$2:$T$1153,0))="","",INDEX('Base articles'!$K$2:$K$1153,MATCH(16,'Base articles'!$T$2:$T$1153,0))),"") | F22: =IFERROR(IF(INDEX('Base articles'!$M$2:$M$1153,MATCH(16,'Base articles'!$T$2:$T$1153,0))="","",INDEX('Base articles'!$M$2:$M$1153,MATCH(16,'Base articles'!$T$2:$T$1153,0))),"") | G22: =IFERROR(IF(INDEX('Base articles'!$N$2:$N$1153,MATCH(16,'Base articles'!$T$2:$T$1153,0))="","",INDEX('Base articles'!$N$2:$N$1153,MATCH(16,'Base articles'!$T$2:$T$1153,0))),"") | H22: =IFERROR(IF(INDEX('Base articles'!$P$2:$P$1153,MATCH(16,'Base articles'!$T$2:$T$1153,0))="","",INDEX('Base articles'!$P$2:$P$1153,MATCH(16,'Base articles'!$T$2:$T$1153,0))),"") | I22: =IFERROR(IF(INDEX('Base articles'!$Q$2:$Q$1153,MATCH(16,'Base articles'!$T$2:$T$1153,0))="","",INDEX('Base articles'!$Q$2:$Q$1153,MATCH(16,'Base articles'!$T$2:$T$1153,0))),"") | J22: =IFERROR(IF(INDEX('Base articles'!$B$2:$B$1153,MATCH(16,'Base articles'!$T$2:$T$1153,0))="","",INDEX('Base articles'!$B$2:$B$1153,MATCH(16,'Base articles'!$T$2:$T$1153,0))),"")
A23: =IFERROR(IF(INDEX('Base articles'!$D$2:$D$1153,MATCH(17,'Base articles'!$T$2:$T$1153,0))="","",INDEX('Base articles'!$D$2:$D$1153,MATCH(17,'Base articles'!$T$2:$T$1153,0))),"") | B23: =IFERROR(IF(INDEX('Base articles'!$F$2:$F$1153,MATCH(17,'Base articles'!$T$2:$T$1153,0))="","",INDEX('Base articles'!$F$2:$F$1153,MATCH(17,'Base articles'!$T$2:$T$1153,0))),"") | C23: =IFERROR(INDEX('Base articles'!$H$2:$H$1153,MATCH(17,'Base articles'!$T$2:$T$1153,0)),"") | D23: =IFERROR(IF(INDEX('Base articles'!$G$2:$G$1153,MATCH(17,'Base articles'!$T$2:$T$1153,0))="","",INDEX('Base articles'!$G$2:$G$1153,MATCH(17,'Base articles'!$T$2:$T$1153,0))),"") | E23: =IFERROR(IF(INDEX('Base articles'!$K$2:$K$1153,MATCH(17,'Base articles'!$T$2:$T$1153,0))="","",INDEX('Base articles'!$K$2:$K$1153,MATCH(17,'Base articles'!$T$2:$T$1153,0))),"") | F23: =IFERROR(IF(INDEX('Base articles'!$M$2:$M$1153,MATCH(17,'Base articles'!$T$2:$T$1153,0))="","",INDEX('Base articles'!$M$2:$M$1153,MATCH(17,'Base articles'!$T$2:$T$1153,0))),"") | G23: =IFERROR(IF(INDEX('Base articles'!$N$2:$N$1153,MATCH(17,'Base articles'!$T$2:$T$1153,0))="","",INDEX('Base articles'!$N$2:$N$1153,MATCH(17,'Base articles'!$T$2:$T$1153,0))),"") | H23: =IFERROR(IF(INDEX('Base articles'!$P$2:$P$1153,MATCH(17,'Base articles'!$T$2:$T$1153,0))="","",INDEX('Base articles'!$P$2:$P$1153,MATCH(17,'Base articles'!$T$2:$T$1153,0))),"") | I23: =IFERROR(IF(INDEX('Base articles'!$Q$2:$Q$1153,MATCH(17,'Base articles'!$T$2:$T$1153,0))="","",INDEX('Base articles'!$Q$2:$Q$1153,MATCH(17,'Base articles'!$T$2:$T$1153,0))),"") | J23: =IFERROR(IF(INDEX('Base articles'!$B$2:$B$1153,MATCH(17,'Base articles'!$T$2:$T$1153,0))="","",INDEX('Base articles'!$B$2:$B$1153,MATCH(17,'Base articles'!$T$2:$T$1153,0))),"")
A24: =IFERROR(IF(INDEX('Base articles'!$D$2:$D$1153,MATCH(18,'Base articles'!$T$2:$T$1153,0))="","",INDEX('Base articles'!$D$2:$D$1153,MATCH(18,'Base articles'!$T$2:$T$1153,0))),"") | B24: =IFERROR(IF(INDEX('Base articles'!$F$2:$F$1153,MATCH(18,'Base articles'!$T$2:$T$1153,0))="","",INDEX('Base articles'!$F$2:$F$1153,MATCH(18,'Base articles'!$T$2:$T$1153,0))),"") | C24: =IFERROR(INDEX('Base articles'!$H$2:$H$1153,MATCH(18,'Base articles'!$T$2:$T$1153,0)),"") | D24: =IFERROR(IF(INDEX('Base articles'!$G$2:$G$1153,MATCH(18,'Base articles'!$T$2:$T$1153,0))="","",INDEX('Base articles'!$G$2:$G$1153,MATCH(18,'Base articles'!$T$2:$T$1153,0))),"") | E24: =IFERROR(IF(INDEX('Base articles'!$K$2:$K$1153,MATCH(18,'Base articles'!$T$2:$T$1153,0))="","",INDEX('Base articles'!$K$2:$K$1153,MATCH(18,'Base articles'!$T$2:$T$1153,0))),"") | F24: =IFERROR(IF(INDEX('Base articles'!$M$2:$M$1153,MATCH(18,'Base articles'!$T$2:$T$1153,0))="","",INDEX('Base articles'!$M$2:$M$1153,MATCH(18,'Base articles'!$T$2:$T$1153,0))),"") | G24: =IFERROR(IF(INDEX('Base articles'!$N$2:$N$1153,MATCH(18,'Base articles'!$T$2:$T$1153,0))="","",INDEX('Base articles'!$N$2:$N$1153,MATCH(18,'Base articles'!$T$2:$T$1153,0))),"") | H24: =IFERROR(IF(INDEX('Base articles'!$P$2:$P$1153,MATCH(18,'Base articles'!$T$2:$T$1153,0))="","",INDEX('Base articles'!$P$2:$P$1153,MATCH(18,'Base articles'!$T$2:$T$1153,0))),"") | I24: =IFERROR(IF(INDEX('Base articles'!$Q$2:$Q$1153,MATCH(18,'Base articles'!$T$2:$T$1153,0))="","",INDEX('Base articles'!$Q$2:$Q$1153,MATCH(18,'Base articles'!$T$2:$T$1153,0))),"") | J24: =IFERROR(IF(INDEX('Base articles'!$B$2:$B$1153,MATCH(18,'Base articles'!$T$2:$T$1153,0))="","",INDEX('Base articles'!$B$2:$B$1153,MATCH(18,'Base articles'!$T$2:$T$1153,0))),"")
A25: =IFERROR(IF(INDEX('Base articles'!$D$2:$D$1153,MATCH(19,'Base articles'!$T$2:$T$1153,0))="","",INDEX('Base articles'!$D$2:$D$1153,MATCH(19,'Base articles'!$T$2:$T$1153,0))),"") | B25: =IFERROR(IF(INDEX('Base articles'!$F$2:$F$1153,MATCH(19,'Base articles'!$T$2:$T$1153,0))="","",INDEX('Base articles'!$F$2:$F$1153,MATCH(19,'Base articles'!$T$2:$T$1153,0))),"") | C25: =IFERROR(INDEX('Base articles'!$H$2:$H$1153,MATCH(19,'Base articles'!$T$2:$T$1153,0)),"") | D25: =IFERROR(IF(INDEX('Base articles'!$G$2:$G$1153,MATCH(19,'Base articles'!$T$2:$T$1153,0))="","",INDEX('Base articles'!$G$2:$G$1153,MATCH(19,'Base articles'!$T$2:$T$1153,0))),"") | E25: =IFERROR(IF(INDEX('Base articles'!$K$2:$K$1153,MATCH(19,'Base articles'!$T$2:$T$1153,0))="","",INDEX('Base articles'!$K$2:$K$1153,MATCH(19,'Base articles'!$T$2:$T$1153,0))),"") | F25: =IFERROR(IF(INDEX('Base articles'!$M$2:$M$1153,MATCH(19,'Base articles'!$T$2:$T$1153,0))="","",INDEX('Base articles'!$M$2:$M$1153,MATCH(19,'Base articles'!$T$2:$T$1153,0))),"") | G25: =IFERROR(IF(INDEX('Base articles'!$N$2:$N$1153,MATCH(19,'Base articles'!$T$2:$T$1153,0))="","",INDEX('Base articles'!$N$2:$N$1153,MATCH(19,'Base articles'!$T$2:$T$1153,0))),"") | H25: =IFERROR(IF(INDEX('Base articles'!$P$2:$P$1153,MATCH(19,'Base articles'!$T$2:$T$1153,0))="","",INDEX('Base articles'!$P$2:$P$1153,MATCH(19,'Base articles'!$T$2:$T$1153,0))),"") | I25: =IFERROR(IF(INDEX('Base articles'!$Q$2:$Q$1153,MATCH(19,'Base articles'!$T$2:$T$1153,0))="","",INDEX('Base articles'!$Q$2:$Q$1153,MATCH(19,'Base articles'!$T$2:$T$1153,0))),"") | J25: =IFERROR(IF(INDEX('Base articles'!$B$2:$B$1153,MATCH(19,'Base articles'!$T$2:$T$1153,0))="","",INDEX('Base articles'!$B$2:$B$1153,MATCH(19,'Base articles'!$T$2:$T$1153,0))),"")
A26: =IFERROR(IF(INDEX('Base articles'!$D$2:$D$1153,MATCH(20,'Base articles'!$T$2:$T$1153,0))="","",INDEX('Base articles'!$D$2:$D$1153,MATCH(20,'Base articles'!$T$2:$T$1153,0))),"") | B26: =IFERROR(IF(INDEX('Base articles'!$F$2:$F$1153,MATCH(20,'Base articles'!$T$2:$T$1153,0))="","",INDEX('Base articles'!$F$2:$F$1153,MATCH(20,'Base articles'!$T$2:$T$1153,0))),"") | C26: =IFERROR(INDEX('Base articles'!$H$2:$H$1153,MATCH(20,'Base articles'!$T$2:$T$1153,0)),"") | D26: =IFERROR(IF(INDEX('Base articles'!$G$2:$G$1153,MATCH(20,'Base articles'!$T$2:$T$1153,0))="","",INDEX('Base articles'!$G$2:$G$1153,MATCH(20,'Base articles'!$T$2:$T$1153,0))),"") | E26: =IFERROR(IF(INDEX('Base articles'!$K$2:$K$1153,MATCH(20,'Base articles'!$T$2:$T$1153,0))="","",INDEX('Base articles'!$K$2:$K$1153,MATCH(20,'Base articles'!$T$2:$T$1153,0))),"") | F26: =IFERROR(IF(INDEX('Base articles'!$M$2:$M$1153,MATCH(20,'Base articles'!$T$2:$T$1153,0))="","",INDEX('Base articles'!$M$2:$M$1153,MATCH(20,'Base articles'!$T$2:$T$1153,0))),"") | G26: =IFERROR(IF(INDEX('Base articles'!$N$2:$N$1153,MATCH(20,'Base articles'!$T$2:$T$1153,0))="","",INDEX('Base articles'!$N$2:$N$1153,MATCH(20,'Base articles'!$T$2:$T$1153,0))),"") | H26: =IFERROR(IF(INDEX('Base articles'!$P$2:$P$1153,MATCH(20,'Base articles'!$T$2:$T$1153,0))="","",INDEX('Base articles'!$P$2:$P$1153,MATCH(20,'Base articles'!$T$2:$T$1153,0))),"") | I26: =IFERROR(IF(INDEX('Base articles'!$Q$2:$Q$1153,MATCH(20,'Base articles'!$T$2:$T$1153,0))="","",INDEX('Base articles'!$Q$2:$Q$1153,MATCH(20,'Base articles'!$T$2:$T$1153,0))),"") | J26: =IFERROR(IF(INDEX('Base articles'!$B$2:$B$1153,MATCH(20,'Base articles'!$T$2:$T$1153,0))="","",INDEX('Base articles'!$B$2:$B$1153,MATCH(20,'Base articles'!$T$2:$T$1153,0))),"")
A27: =IFERROR(IF(INDEX('Base articles'!$D$2:$D$1153,MATCH(21,'Base articles'!$T$2:$T$1153,0))="","",INDEX('Base articles'!$D$2:$D$1153,MATCH(21,'Base articles'!$T$2:$T$1153,0))),"") | B27: =IFERROR(IF(INDEX('Base articles'!$F$2:$F$1153,MATCH(21,'Base articles'!$T$2:$T$1153,0))="","",INDEX('Base articles'!$F$2:$F$1153,MATCH(21,'Base articles'!$T$2:$T$1153,0))),"") | C27: =IFERROR(INDEX('Base articles'!$H$2:$H$1153,MATCH(21,'Base articles'!$T$2:$T$1153,0)),"") | D27: =IFERROR(IF(INDEX('Base articles'!$G$2:$G$1153,MATCH(21,'Base articles'!$T$2:$T$1153,0))="","",INDEX('Base articles'!$G$2:$G$1153,MATCH(21,'Base articles'!$T$2:$T$1153,0))),"") | E27: =IFERROR(IF(INDEX('Base articles'!$K$2:$K$1153,MATCH(21,'Base articles'!$T$2:$T$1153,0))="","",INDEX('Base articles'!$K$2:$K$1153,MATCH(21,'Base articles'!$T$2:$T$1153,0))),"") | F27: =IFERROR(IF(INDEX('Base articles'!$M$2:$M$1153,MATCH(21,'Base articles'!$T$2:$T$1153,0))="","",INDEX('Base articles'!$M$2:$M$1153,MATCH(21,'Base articles'!$T$2:$T$1153,0))),"") | G27: =IFERROR(IF(INDEX('Base articles'!$N$2:$N$1153,MATCH(21,'Base articles'!$T$2:$T$1153,0))="","",INDEX('Base articles'!$N$2:$N$1153,MATCH(21,'Base articles'!$T$2:$T$1153,0))),"") | H27: =IFERROR(IF(INDEX('Base articles'!$P$2:$P$1153,MATCH(21,'Base articles'!$T$2:$T$1153,0))="","",INDEX('Base articles'!$P$2:$P$1153,MATCH(21,'Base articles'!$T$2:$T$1153,0))),"") | I27: =IFERROR(IF(INDEX('Base articles'!$Q$2:$Q$1153,MATCH(21,'Base articles'!$T$2:$T$1153,0))="","",INDEX('Base articles'!$Q$2:$Q$1153,MATCH(21,'Base articles'!$T$2:$T$1153,0))),"") | J27: =IFERROR(IF(INDEX('Base articles'!$B$2:$B$1153,MATCH(21,'Base articles'!$T$2:$T$1153,0))="","",INDEX('Base articles'!$B$2:$B$1153,MATCH(21,'Base articles'!$T$2:$T$1153,0))),"")
A28: =IFERROR(IF(INDEX('Base articles'!$D$2:$D$1153,MATCH(22,'Base articles'!$T$2:$T$1153,0))="","",INDEX('Base articles'!$D$2:$D$1153,MATCH(22,'Base articles'!$T$2:$T$1153,0))),"") | B28: =IFERROR(IF(INDEX('Base articles'!$F$2:$F$1153,MATCH(22,'Base articles'!$T$2:$T$1153,0))="","",INDEX('Base articles'!$F$2:$F$1153,MATCH(22,'Base articles'!$T$2:$T$1153,0))),"") | C28: =IFERROR(INDEX('Base articles'!$H$2:$H$1153,MATCH(22,'Base articles'!$T$2:$T$1153,0)),"") | D28: =IFERROR(IF(INDEX('Base articles'!$G$2:$G$1153,MATCH(22,'Base articles'!$T$2:$T$1153,0))="","",INDEX('Base articles'!$G$2:$G$1153,MATCH(22,'Base articles'!$T$2:$T$1153,0))),"") | E28: =IFERROR(IF(INDEX('Base articles'!$K$2:$K$1153,MATCH(22,'Base articles'!$T$2:$T$1153,0))="","",INDEX('Base articles'!$K$2:$K$1153,MATCH(22,'Base articles'!$T$2:$T$1153,0))),"") | F28: =IFERROR(IF(INDEX('Base articles'!$M$2:$M$1153,MATCH(22,'Base articles'!$T$2:$T$1153,0))="","",INDEX('Base articles'!$M$2:$M$1153,MATCH(22,'Base articles'!$T$2:$T$1153,0))),"") | G28: =IFERROR(IF(INDEX('Base articles'!$N$2:$N$1153,MATCH(22,'Base articles'!$T$2:$T$1153,0))="","",INDEX('Base articles'!$N$2:$N$1153,MATCH(22,'Base articles'!$T$2:$T$1153,0))),"") | H28: =IFERROR(IF(INDEX('Base articles'!$P$2:$P$1153,MATCH(22,'Base articles'!$T$2:$T$1153,0))="","",INDEX('Base articles'!$P$2:$P$1153,MATCH(22,'Base articles'!$T$2:$T$1153,0))),"") | I28: =IFERROR(IF(INDEX('Base articles'!$Q$2:$Q$1153,MATCH(22,'Base articles'!$T$2:$T$1153,0))="","",INDEX('Base articles'!$Q$2:$Q$1153,MATCH(22,'Base articles'!$T$2:$T$1153,0))),"") | J28: =IFERROR(IF(INDEX('Base articles'!$B$2:$B$1153,MATCH(22,'Base articles'!$T$2:$T$1153,0))="","",INDEX('Base articles'!$B$2:$B$1153,MATCH(22,'Base articles'!$T$2:$T$1153,0))),"")
A29: =IFERROR(IF(INDEX('Base articles'!$D$2:$D$1153,MATCH(23,'Base articles'!$T$2:$T$1153,0))="","",INDEX('Base articles'!$D$2:$D$1153,MATCH(23,'Base articles'!$T$2:$T$1153,0))),"") | B29: =IFERROR(IF(INDEX('Base articles'!$F$2:$F$1153,MATCH(23,'Base articles'!$T$2:$T$1153,0))="","",INDEX('Base articles'!$F$2:$F$1153,MATCH(23,'Base articles'!$T$2:$T$1153,0))),"") | C29: =IFERROR(INDEX('Base articles'!$H$2:$H$1153,MATCH(23,'Base articles'!$T$2:$T$1153,0)),"") | D29: =IFERROR(IF(INDEX('Base articles'!$G$2:$G$1153,MATCH(23,'Base articles'!$T$2:$T$1153,0))="","",INDEX('Base articles'!$G$2:$G$1153,MATCH(23,'Base articles'!$T$2:$T$1153,0))),"") | E29: =IFERROR(IF(INDEX('Base articles'!$K$2:$K$1153,MATCH(23,'Base articles'!$T$2:$T$1153,0))="","",INDEX('Base articles'!$K$2:$K$1153,MATCH(23,'Base articles'!$T$2:$T$1153,0))),"") | F29: =IFERROR(IF(INDEX('Base articles'!$M$2:$M$1153,MATCH(23,'Base articles'!$T$2:$T$1153,0))="","",INDEX('Base articles'!$M$2:$M$1153,MATCH(23,'Base articles'!$T$2:$T$1153,0))),"") | G29: =IFERROR(IF(INDEX('Base articles'!$N$2:$N$1153,MATCH(23,'Base articles'!$T$2:$T$1153,0))="","",INDEX('Base articles'!$N$2:$N$1153,MATCH(23,'Base articles'!$T$2:$T$1153,0))),"") | H29: =IFERROR(IF(INDEX('Base articles'!$P$2:$P$1153,MATCH(23,'Base articles'!$T$2:$T$1153,0))="","",INDEX('Base articles'!$P$2:$P$1153,MATCH(23,'Base articles'!$T$2:$T$1153,0))),"") | I29: =IFERROR(IF(INDEX('Base articles'!$Q$2:$Q$1153,MATCH(23,'Base articles'!$T$2:$T$1153,0))="","",INDEX('Base articles'!$Q$2:$Q$1153,MATCH(23,'Base articles'!$T$2:$T$1153,0))),"") | J29: =IFERROR(IF(INDEX('Base articles'!$B$2:$B$1153,MATCH(23,'Base articles'!$T$2:$T$1153,0))="","",INDEX('Base articles'!$B$2:$B$1153,MATCH(23,'Base articles'!$T$2:$T$1153,0))),"")
A30: =IFERROR(IF(INDEX('Base articles'!$D$2:$D$1153,MATCH(24,'Base articles'!$T$2:$T$1153,0))="","",INDEX('Base articles'!$D$2:$D$1153,MATCH(24,'Base articles'!$T$2:$T$1153,0))),"") | B30: =IFERROR(IF(INDEX('Base articles'!$F$2:$F$1153,MATCH(24,'Base articles'!$T$2:$T$1153,0))="","",INDEX('Base articles'!$F$2:$F$1153,MATCH(24,'Base articles'!$T$2:$T$1153,0))),"") | C30: =IFERROR(INDEX('Base articles'!$H$2:$H$1153,MATCH(24,'Base articles'!$T$2:$T$1153,0)),"") | D30: =IFERROR(IF(INDEX('Base articles'!$G$2:$G$1153,MATCH(24,'Base articles'!$T$2:$T$1153,0))="","",INDEX('Base articles'!$G$2:$G$1153,MATCH(24,'Base articles'!$T$2:$T$1153,0))),"") | E30: =IFERROR(IF(INDEX('Base articles'!$K$2:$K$1153,MATCH(24,'Base articles'!$T$2:$T$1153,0))="","",INDEX('Base articles'!$K$2:$K$1153,MATCH(24,'Base articles'!$T$2:$T$1153,0))),"") | F30: =IFERROR(IF(INDEX('Base articles'!$M$2:$M$1153,MATCH(24,'Base articles'!$T$2:$T$1153,0))="","",INDEX('Base articles'!$M$2:$M$1153,MATCH(24,'Base articles'!$T$2:$T$1153,0))),"") | G30: =IFERROR(IF(INDEX('Base articles'!$N$2:$N$1153,MATCH(24,'Base articles'!$T$2:$T$1153,0))="","",INDEX('Base articles'!$N$2:$N$1153,MATCH(24,'Base articles'!$T$2:$T$1153,0))),"") | H30: =IFERROR(IF(INDEX('Base articles'!$P$2:$P$1153,MATCH(24,'Base articles'!$T$2:$T$1153,0))="","",INDEX('Base articles'!$P$2:$P$1153,MATCH(24,'Base articles'!$T$2:$T$1153,0))),"") | I30: =IFERROR(IF(INDEX('Base articles'!$Q$2:$Q$1153,MATCH(24,'Base articles'!$T$2:$T$1153,0))="","",INDEX('Base articles'!$Q$2:$Q$1153,MATCH(24,'Base articles'!$T$2:$T$1153,0))),"") | J30: =IFERROR(IF(INDEX('Base articles'!$B$2:$B$1153,MATCH(24,'Base articles'!$T$2:$T$1153,0))="","",INDEX('Base articles'!$B$2:$B$1153,MATCH(24,'Base articles'!$T$2:$T$1153,0))),"")
A31: =IFERROR(IF(INDEX('Base articles'!$D$2:$D$1153,MATCH(25,'Base articles'!$T$2:$T$1153,0))="","",INDEX('Base articles'!$D$2:$D$1153,MATCH(25,'Base articles'!$T$2:$T$1153,0))),"") | B31: =IFERROR(IF(INDEX('Base articles'!$F$2:$F$1153,MATCH(25,'Base articles'!$T$2:$T$1153,0))="","",INDEX('Base articles'!$F$2:$F$1153,MATCH(25,'Base articles'!$T$2:$T$1153,0))),"") | C31: =IFERROR(INDEX('Base articles'!$H$2:$H$1153,MATCH(25,'Base articles'!$T$2:$T$1153,0)),"") | D31: =IFERROR(IF(INDEX('Base articles'!$G$2:$G$1153,MATCH(25,'Base articles'!$T$2:$T$1153,0))="","",INDEX('Base articles'!$G$2:$G$1153,MATCH(25,'Base articles'!$T$2:$T$1153,0))),"") | E31: =IFERROR(IF(INDEX('Base articles'!$K$2:$K$1153,MATCH(25,'Base articles'!$T$2:$T$1153,0))="","",INDEX('Base articles'!$K$2:$K$1153,MATCH(25,'Base articles'!$T$2:$T$1153,0))),"") | F31: =IFERROR(IF(INDEX('Base articles'!$M$2:$M$1153,MATCH(25,'Base articles'!$T$2:$T$1153,0))="","",INDEX('Base articles'!$M$2:$M$1153,MATCH(25,'Base articles'!$T$2:$T$1153,0))),"") | G31: =IFERROR(IF(INDEX('Base articles'!$N$2:$N$1153,MATCH(25,'Base articles'!$T$2:$T$1153,0))="","",INDEX('Base articles'!$N$2:$N$1153,MATCH(25,'Base articles'!$T$2:$T$1153,0))),"") | H31: =IFERROR(IF(INDEX('Base articles'!$P$2:$P$1153,MATCH(25,'Base articles'!$T$2:$T$1153,0))="","",INDEX('Base articles'!$P$2:$P$1153,MATCH(25,'Base articles'!$T$2:$T$1153,0))),"") | I31: =IFERROR(IF(INDEX('Base articles'!$Q$2:$Q$1153,MATCH(25,'Base articles'!$T$2:$T$1153,0))="","",INDEX('Base articles'!$Q$2:$Q$1153,MATCH(25,'Base articles'!$T$2:$T$1153,0))),"") | J31: =IFERROR(IF(INDEX('Base articles'!$B$2:$B$1153,MATCH(25,'Base articles'!$T$2:$T$1153,0))="","",INDEX('Base articles'!$B$2:$B$1153,MATCH(25,'Base articles'!$T$2:$T$1153,0))),"")
A32: =IFERROR(IF(INDEX('Base articles'!$D$2:$D$1153,MATCH(26,'Base articles'!$T$2:$T$1153,0))="","",INDEX('Base articles'!$D$2:$D$1153,MATCH(26,'Base articles'!$T$2:$T$1153,0))),"") | B32: =IFERROR(IF(INDEX('Base articles'!$F$2:$F$1153,MATCH(26,'Base articles'!$T$2:$T$1153,0))="","",INDEX('Base articles'!$F$2:$F$1153,MATCH(26,'Base articles'!$T$2:$T$1153,0))),"") | C32: =IFERROR(INDEX('Base articles'!$H$2:$H$1153,MATCH(26,'Base articles'!$T$2:$T$1153,0)),"") | D32: =IFERROR(IF(INDEX('Base articles'!$G$2:$G$1153,MATCH(26,'Base articles'!$T$2:$T$1153,0))="","",INDEX('Base articles'!$G$2:$G$1153,MATCH(26,'Base articles'!$T$2:$T$1153,0))),"") | E32: =IFERROR(IF(INDEX('Base articles'!$K$2:$K$1153,MATCH(26,'Base articles'!$T$2:$T$1153,0))="","",INDEX('Base articles'!$K$2:$K$1153,MATCH(26,'Base articles'!$T$2:$T$1153,0))),"") | F32: =IFERROR(IF(INDEX('Base articles'!$M$2:$M$1153,MATCH(26,'Base articles'!$T$2:$T$1153,0))="","",INDEX('Base articles'!$M$2:$M$1153,MATCH(26,'Base articles'!$T$2:$T$1153,0))),"") | G32: =IFERROR(IF(INDEX('Base articles'!$N$2:$N$1153,MATCH(26,'Base articles'!$T$2:$T$1153,0))="","",INDEX('Base articles'!$N$2:$N$1153,MATCH(26,'Base articles'!$T$2:$T$1153,0))),"") | H32: =IFERROR(IF(INDEX('Base articles'!$P$2:$P$1153,MATCH(26,'Base articles'!$T$2:$T$1153,0))="","",INDEX('Base articles'!$P$2:$P$1153,MATCH(26,'Base articles'!$T$2:$T$1153,0))),"") | I32: =IFERROR(IF(INDEX('Base articles'!$Q$2:$Q$1153,MATCH(26,'Base articles'!$T$2:$T$1153,0))="","",INDEX('Base articles'!$Q$2:$Q$1153,MATCH(26,'Base articles'!$T$2:$T$1153,0))),"") | J32: =IFERROR(IF(INDEX('Base articles'!$B$2:$B$1153,MATCH(26,'Base articles'!$T$2:$T$1153,0))="","",INDEX('Base articles'!$B$2:$B$1153,MATCH(26,'Base articles'!$T$2:$T$1153,0))),"")
A33: =IFERROR(IF(INDEX('Base articles'!$D$2:$D$1153,MATCH(27,'Base articles'!$T$2:$T$1153,0))="","",INDEX('Base articles'!$D$2:$D$1153,MATCH(27,'Base articles'!$T$2:$T$1153,0))),"") | B33: =IFERROR(IF(INDEX('Base articles'!$F$2:$F$1153,MATCH(27,'Base articles'!$T$2:$T$1153,0))="","",INDEX('Base articles'!$F$2:$F$1153,MATCH(27,'Base articles'!$T$2:$T$1153,0))),"") | C33: =IFERROR(INDEX('Base articles'!$H$2:$H$1153,MATCH(27,'Base articles'!$T$2:$T$1153,0)),"") | D33: =IFERROR(IF(INDEX('Base articles'!$G$2:$G$1153,MATCH(27,'Base articles'!$T$2:$T$1153,0))="","",INDEX('Base articles'!$G$2:$G$1153,MATCH(27,'Base articles'!$T$2:$T$1153,0))),"") | E33: =IFERROR(IF(INDEX('Base articles'!$K$2:$K$1153,MATCH(27,'Base articles'!$T$2:$T$1153,0))="","",INDEX('Base articles'!$K$2:$K$1153,MATCH(27,'Base articles'!$T$2:$T$1153,0))),"") | F33: =IFERROR(IF(INDEX('Base articles'!$M$2:$M$1153,MATCH(27,'Base articles'!$T$2:$T$1153,0))="","",INDEX('Base articles'!$M$2:$M$1153,MATCH(27,'Base articles'!$T$2:$T$1153,0))),"") | G33: =IFERROR(IF(INDEX('Base articles'!$N$2:$N$1153,MATCH(27,'Base articles'!$T$2:$T$1153,0))="","",INDEX('Base articles'!$N$2:$N$1153,MATCH(27,'Base articles'!$T$2:$T$1153,0))),"") | H33: =IFERROR(IF(INDEX('Base articles'!$P$2:$P$1153,MATCH(27,'Base articles'!$T$2:$T$1153,0))="","",INDEX('Base articles'!$P$2:$P$1153,MATCH(27,'Base articles'!$T$2:$T$1153,0))),"") | I33: =IFERROR(IF(INDEX('Base articles'!$Q$2:$Q$1153,MATCH(27,'Base articles'!$T$2:$T$1153,0))="","",INDEX('Base articles'!$Q$2:$Q$1153,MATCH(27,'Base articles'!$T$2:$T$1153,0))),"") | J33: =IFERROR(IF(INDEX('Base articles'!$B$2:$B$1153,MATCH(27,'Base articles'!$T$2:$T$1153,0))="","",INDEX('Base articles'!$B$2:$B$1153,MATCH(27,'Base articles'!$T$2:$T$1153,0))),"")
A34: =IFERROR(IF(INDEX('Base articles'!$D$2:$D$1153,MATCH(28,'Base articles'!$T$2:$T$1153,0))="","",INDEX('Base articles'!$D$2:$D$1153,MATCH(28,'Base articles'!$T$2:$T$1153,0))),"") | B34: =IFERROR(IF(INDEX('Base articles'!$F$2:$F$1153,MATCH(28,'Base articles'!$T$2:$T$1153,0))="","",INDEX('Base articles'!$F$2:$F$1153,MATCH(28,'Base articles'!$T$2:$T$1153,0))),"") | C34: =IFERROR(INDEX('Base articles'!$H$2:$H$1153,MATCH(28,'Base articles'!$T$2:$T$1153,0)),"") | D34: =IFERROR(IF(INDEX('Base articles'!$G$2:$G$1153,MATCH(28,'Base articles'!$T$2:$T$1153,0))="","",INDEX('Base articles'!$G$2:$G$1153,MATCH(28,'Base articles'!$T$2:$T$1153,0))),"") | E34: =IFERROR(IF(INDEX('Base articles'!$K$2:$K$1153,MATCH(28,'Base articles'!$T$2:$T$1153,0))="","",INDEX('Base articles'!$K$2:$K$1153,MATCH(28,'Base articles'!$T$2:$T$1153,0))),"") | F34: =IFERROR(IF(INDEX('Base articles'!$M$2:$M$1153,MATCH(28,'Base articles'!$T$2:$T$1153,0))="","",INDEX('Base articles'!$M$2:$M$1153,MATCH(28,'Base articles'!$T$2:$T$1153,0))),"") | G34: =IFERROR(IF(INDEX('Base articles'!$N$2:$N$1153,MATCH(28,'Base articles'!$T$2:$T$1153,0))="","",INDEX('Base articles'!$N$2:$N$1153,MATCH(28,'Base articles'!$T$2:$T$1153,0))),"") | H34: =IFERROR(IF(INDEX('Base articles'!$P$2:$P$1153,MATCH(28,'Base articles'!$T$2:$T$1153,0))="","",INDEX('Base articles'!$P$2:$P$1153,MATCH(28,'Base articles'!$T$2:$T$1153,0))),"") | I34: =IFERROR(IF(INDEX('Base articles'!$Q$2:$Q$1153,MATCH(28,'Base articles'!$T$2:$T$1153,0))="","",INDEX('Base articles'!$Q$2:$Q$1153,MATCH(28,'Base articles'!$T$2:$T$1153,0))),"") | J34: =IFERROR(IF(INDEX('Base articles'!$B$2:$B$1153,MATCH(28,'Base articles'!$T$2:$T$1153,0))="","",INDEX('Base articles'!$B$2:$B$1153,MATCH(28,'Base articles'!$T$2:$T$1153,0))),"")
A35: =IFERROR(IF(INDEX('Base articles'!$D$2:$D$1153,MATCH(29,'Base articles'!$T$2:$T$1153,0))="","",INDEX('Base articles'!$D$2:$D$1153,MATCH(29,'Base articles'!$T$2:$T$1153,0))),"") | B35: =IFERROR(IF(INDEX('Base articles'!$F$2:$F$1153,MATCH(29,'Base articles'!$T$2:$T$1153,0))="","",INDEX('Base articles'!$F$2:$F$1153,MATCH(29,'Base articles'!$T$2:$T$1153,0))),"") | C35: =IFERROR(INDEX('Base articles'!$H$2:$H$1153,MATCH(29,'Base articles'!$T$2:$T$1153,0)),"") | D35: =IFERROR(IF(INDEX('Base articles'!$G$2:$G$1153,MATCH(29,'Base articles'!$T$2:$T$1153,0))="","",INDEX('Base articles'!$G$2:$G$1153,MATCH(29,'Base articles'!$T$2:$T$1153,0))),"") | E35: =IFERROR(IF(INDEX('Base articles'!$K$2:$K$1153,MATCH(29,'Base articles'!$T$2:$T$1153,0))="","",INDEX('Base articles'!$K$2:$K$1153,MATCH(29,'Base articles'!$T$2:$T$1153,0))),"") | F35: =IFERROR(IF(INDEX('Base articles'!$M$2:$M$1153,MATCH(29,'Base articles'!$T$2:$T$1153,0))="","",INDEX('Base articles'!$M$2:$M$1153,MATCH(29,'Base articles'!$T$2:$T$1153,0))),"") | G35: =IFERROR(IF(INDEX('Base articles'!$N$2:$N$1153,MATCH(29,'Base articles'!$T$2:$T$1153,0))="","",INDEX('Base articles'!$N$2:$N$1153,MATCH(29,'Base articles'!$T$2:$T$1153,0))),"") | H35: =IFERROR(IF(INDEX('Base articles'!$P$2:$P$1153,MATCH(29,'Base articles'!$T$2:$T$1153,0))="","",INDEX('Base articles'!$P$2:$P$1153,MATCH(29,'Base articles'!$T$2:$T$1153,0))),"") | I35: =IFERROR(IF(INDEX('Base articles'!$Q$2:$Q$1153,MATCH(29,'Base articles'!$T$2:$T$1153,0))="","",INDEX('Base articles'!$Q$2:$Q$1153,MATCH(29,'Base articles'!$T$2:$T$1153,0))),"") | J35: =IFERROR(IF(INDEX('Base articles'!$B$2:$B$1153,MATCH(29,'Base articles'!$T$2:$T$1153,0))="","",INDEX('Base articles'!$B$2:$B$1153,MATCH(29,'Base articles'!$T$2:$T$1153,0))),"")
A36: =IFERROR(IF(INDEX('Base articles'!$D$2:$D$1153,MATCH(30,'Base articles'!$T$2:$T$1153,0))="","",INDEX('Base articles'!$D$2:$D$1153,MATCH(30,'Base articles'!$T$2:$T$1153,0))),"") | B36: =IFERROR(IF(INDEX('Base articles'!$F$2:$F$1153,MATCH(30,'Base articles'!$T$2:$T$1153,0))="","",INDEX('Base articles'!$F$2:$F$1153,MATCH(30,'Base articles'!$T$2:$T$1153,0))),"") | C36: =IFERROR(INDEX('Base articles'!$H$2:$H$1153,MATCH(30,'Base articles'!$T$2:$T$1153,0)),"") | D36: =IFERROR(IF(INDEX('Base articles'!$G$2:$G$1153,MATCH(30,'Base articles'!$T$2:$T$1153,0))="","",INDEX('Base articles'!$G$2:$G$1153,MATCH(30,'Base articles'!$T$2:$T$1153,0))),"") | E36: =IFERROR(IF(INDEX('Base articles'!$K$2:$K$1153,MATCH(30,'Base articles'!$T$2:$T$1153,0))="","",INDEX('Base articles'!$K$2:$K$1153,MATCH(30,'Base articles'!$T$2:$T$1153,0))),"") | F36: =IFERROR(IF(INDEX('Base articles'!$M$2:$M$1153,MATCH(30,'Base articles'!$T$2:$T$1153,0))="","",INDEX('Base articles'!$M$2:$M$1153,MATCH(30,'Base articles'!$T$2:$T$1153,0))),"") | G36: =IFERROR(IF(INDEX('Base articles'!$N$2:$N$1153,MATCH(30,'Base articles'!$T$2:$T$1153,0))="","",INDEX('Base articles'!$N$2:$N$1153,MATCH(30,'Base articles'!$T$2:$T$1153,0))),"") | H36: =IFERROR(IF(INDEX('Base articles'!$P$2:$P$1153,MATCH(30,'Base articles'!$T$2:$T$1153,0))="","",INDEX('Base articles'!$P$2:$P$1153,MATCH(30,'Base articles'!$T$2:$T$1153,0))),"") | I36: =IFERROR(IF(INDEX('Base articles'!$Q$2:$Q$1153,MATCH(30,'Base articles'!$T$2:$T$1153,0))="","",INDEX('Base articles'!$Q$2:$Q$1153,MATCH(30,'Base articles'!$T$2:$T$1153,0))),"") | J36: =IFERROR(IF(INDEX('Base articles'!$B$2:$B$1153,MATCH(30,'Base articles'!$T$2:$T$1153,0))="","",INDEX('Base articles'!$B$2:$B$1153,MATCH(30,'Base articles'!$T$2:$T$1153,0))),"")
A37: =IFERROR(IF(INDEX('Base articles'!$D$2:$D$1153,MATCH(31,'Base articles'!$T$2:$T$1153,0))="","",INDEX('Base articles'!$D$2:$D$1153,MATCH(31,'Base articles'!$T$2:$T$1153,0))),"") | B37: =IFERROR(IF(INDEX('Base articles'!$F$2:$F$1153,MATCH(31,'Base articles'!$T$2:$T$1153,0))="","",INDEX('Base articles'!$F$2:$F$1153,MATCH(31,'Base articles'!$T$2:$T$1153,0))),"") | C37: =IFERROR(INDEX('Base articles'!$H$2:$H$1153,MATCH(31,'Base articles'!$T$2:$T$1153,0)),"") | D37: =IFERROR(IF(INDEX('Base articles'!$G$2:$G$1153,MATCH(31,'Base articles'!$T$2:$T$1153,0))="","",INDEX('Base articles'!$G$2:$G$1153,MATCH(31,'Base articles'!$T$2:$T$1153,0))),"") | E37: =IFERROR(IF(INDEX('Base articles'!$K$2:$K$1153,MATCH(31,'Base articles'!$T$2:$T$1153,0))="","",INDEX('Base articles'!$K$2:$K$1153,MATCH(31,'Base articles'!$T$2:$T$1153,0))),"") | F37: =IFERROR(IF(INDEX('Base articles'!$M$2:$M$1153,MATCH(31,'Base articles'!$T$2:$T$1153,0))="","",INDEX('Base articles'!$M$2:$M$1153,MATCH(31,'Base articles'!$T$2:$T$1153,0))),"") | G37: =IFERROR(IF(INDEX('Base articles'!$N$2:$N$1153,MATCH(31,'Base articles'!$T$2:$T$1153,0))="","",INDEX('Base articles'!$N$2:$N$1153,MATCH(31,'Base articles'!$T$2:$T$1153,0))),"") | H37: =IFERROR(IF(INDEX('Base articles'!$P$2:$P$1153,MATCH(31,'Base articles'!$T$2:$T$1153,0))="","",INDEX('Base articles'!$P$2:$P$1153,MATCH(31,'Base articles'!$T$2:$T$1153,0))),"") | I37: =IFERROR(IF(INDEX('Base articles'!$Q$2:$Q$1153,MATCH(31,'Base articles'!$T$2:$T$1153,0))="","",INDEX('Base articles'!$Q$2:$Q$1153,MATCH(31,'Base articles'!$T$2:$T$1153,0))),"") | J37: =IFERROR(IF(INDEX('Base articles'!$B$2:$B$1153,MATCH(31,'Base articles'!$T$2:$T$1153,0))="","",INDEX('Base articles'!$B$2:$B$1153,MATCH(31,'Base articles'!$T$2:$T$1153,0))),"")
A38: =IFERROR(IF(INDEX('Base articles'!$D$2:$D$1153,MATCH(32,'Base articles'!$T$2:$T$1153,0))="","",INDEX('Base articles'!$D$2:$D$1153,MATCH(32,'Base articles'!$T$2:$T$1153,0))),"") | B38: =IFERROR(IF(INDEX('Base articles'!$F$2:$F$1153,MATCH(32,'Base articles'!$T$2:$T$1153,0))="","",INDEX('Base articles'!$F$2:$F$1153,MATCH(32,'Base articles'!$T$2:$T$1153,0))),"") | C38: =IFERROR(INDEX('Base articles'!$H$2:$H$1153,MATCH(32,'Base articles'!$T$2:$T$1153,0)),"") | D38: =IFERROR(IF(INDEX('Base articles'!$G$2:$G$1153,MATCH(32,'Base articles'!$T$2:$T$1153,0))="","",INDEX('Base articles'!$G$2:$G$1153,MATCH(32,'Base articles'!$T$2:$T$1153,0))),"") | E38: =IFERROR(IF(INDEX('Base articles'!$K$2:$K$1153,MATCH(32,'Base articles'!$T$2:$T$1153,0))="","",INDEX('Base articles'!$K$2:$K$1153,MATCH(32,'Base articles'!$T$2:$T$1153,0))),"") | F38: =IFERROR(IF(INDEX('Base articles'!$M$2:$M$1153,MATCH(32,'Base articles'!$T$2:$T$1153,0))="","",INDEX('Base articles'!$M$2:$M$1153,MATCH(32,'Base articles'!$T$2:$T$1153,0))),"") | G38: =IFERROR(IF(INDEX('Base articles'!$N$2:$N$1153,MATCH(32,'Base articles'!$T$2:$T$1153,0))="","",INDEX('Base articles'!$N$2:$N$1153,MATCH(32,'Base articles'!$T$2:$T$1153,0))),"") | H38: =IFERROR(IF(INDEX('Base articles'!$P$2:$P$1153,MATCH(32,'Base articles'!$T$2:$T$1153,0))="","",INDEX('Base articles'!$P$2:$P$1153,MATCH(32,'Base articles'!$T$2:$T$1153,0))),"") | I38: =IFERROR(IF(INDEX('Base articles'!$Q$2:$Q$1153,MATCH(32,'Base articles'!$T$2:$T$1153,0))="","",INDEX('Base articles'!$Q$2:$Q$1153,MATCH(32,'Base articles'!$T$2:$T$1153,0))),"") | J38: =IFERROR(IF(INDEX('Base articles'!$B$2:$B$1153,MATCH(32,'Base articles'!$T$2:$T$1153,0))="","",INDEX('Base articles'!$B$2:$B$1153,MATCH(32,'Base articles'!$T$2:$T$1153,0))),"")
A39: =IFERROR(IF(INDEX('Base articles'!$D$2:$D$1153,MATCH(33,'Base articles'!$T$2:$T$1153,0))="","",INDEX('Base articles'!$D$2:$D$1153,MATCH(33,'Base articles'!$T$2:$T$1153,0))),"") | B39: =IFERROR(IF(INDEX('Base articles'!$F$2:$F$1153,MATCH(33,'Base articles'!$T$2:$T$1153,0))="","",INDEX('Base articles'!$F$2:$F$1153,MATCH(33,'Base articles'!$T$2:$T$1153,0))),"") | C39: =IFERROR(INDEX('Base articles'!$H$2:$H$1153,MATCH(33,'Base articles'!$T$2:$T$1153,0)),"") | D39: =IFERROR(IF(INDEX('Base articles'!$G$2:$G$1153,MATCH(33,'Base articles'!$T$2:$T$1153,0))="","",INDEX('Base articles'!$G$2:$G$1153,MATCH(33,'Base articles'!$T$2:$T$1153,0))),"") | E39: =IFERROR(IF(INDEX('Base articles'!$K$2:$K$1153,MATCH(33,'Base articles'!$T$2:$T$1153,0))="","",INDEX('Base articles'!$K$2:$K$1153,MATCH(33,'Base articles'!$T$2:$T$1153,0))),"") | F39: =IFERROR(IF(INDEX('Base articles'!$M$2:$M$1153,MATCH(33,'Base articles'!$T$2:$T$1153,0))="","",INDEX('Base articles'!$M$2:$M$1153,MATCH(33,'Base articles'!$T$2:$T$1153,0))),"") | G39: =IFERROR(IF(INDEX('Base articles'!$N$2:$N$1153,MATCH(33,'Base articles'!$T$2:$T$1153,0))="","",INDEX('Base articles'!$N$2:$N$1153,MATCH(33,'Base articles'!$T$2:$T$1153,0))),"") | H39: =IFERROR(IF(INDEX('Base articles'!$P$2:$P$1153,MATCH(33,'Base articles'!$T$2:$T$1153,0))="","",INDEX('Base articles'!$P$2:$P$1153,MATCH(33,'Base articles'!$T$2:$T$1153,0))),"") | I39: =IFERROR(IF(INDEX('Base articles'!$Q$2:$Q$1153,MATCH(33,'Base articles'!$T$2:$T$1153,0))="","",INDEX('Base articles'!$Q$2:$Q$1153,MATCH(33,'Base articles'!$T$2:$T$1153,0))),"") | J39: =IFERROR(IF(INDEX('Base articles'!$B$2:$B$1153,MATCH(33,'Base articles'!$T$2:$T$1153,0))="","",INDEX('Base articles'!$B$2:$B$1153,MATCH(33,'Base articles'!$T$2:$T$1153,0))),"")
A40: =IFERROR(IF(INDEX('Base articles'!$D$2:$D$1153,MATCH(34,'Base articles'!$T$2:$T$1153,0))="","",INDEX('Base articles'!$D$2:$D$1153,MATCH(34,'Base articles'!$T$2:$T$1153,0))),"") | B40: =IFERROR(IF(INDEX('Base articles'!$F$2:$F$1153,MATCH(34,'Base articles'!$T$2:$T$1153,0))="","",INDEX('Base articles'!$F$2:$F$1153,MATCH(34,'Base articles'!$T$2:$T$1153,0))),"") | C40: =IFERROR(INDEX('Base articles'!$H$2:$H$1153,MATCH(34,'Base articles'!$T$2:$T$1153,0)),"") | D40: =IFERROR(IF(INDEX('Base articles'!$G$2:$G$1153,MATCH(34,'Base articles'!$T$2:$T$1153,0))="","",INDEX('Base articles'!$G$2:$G$1153,MATCH(34,'Base articles'!$T$2:$T$1153,0))),"") | E40: =IFERROR(IF(INDEX('Base articles'!$K$2:$K$1153,MATCH(34,'Base articles'!$T$2:$T$1153,0))="","",INDEX('Base articles'!$K$2:$K$1153,MATCH(34,'Base articles'!$T$2:$T$1153,0))),"") | F40: =IFERROR(IF(INDEX('Base articles'!$M$2:$M$1153,MATCH(34,'Base articles'!$T$2:$T$1153,0))="","",INDEX('Base articles'!$M$2:$M$1153,MATCH(34,'Base articles'!$T$2:$T$1153,0))),"") | G40: =IFERROR(IF(INDEX('Base articles'!$N$2:$N$1153,MATCH(34,'Base articles'!$T$2:$T$1153,0))="","",INDEX('Base articles'!$N$2:$N$1153,MATCH(34,'Base articles'!$T$2:$T$1153,0))),"") | H40: =IFERROR(IF(INDEX('Base articles'!$P$2:$P$1153,MATCH(34,'Base articles'!$T$2:$T$1153,0))="","",INDEX('Base articles'!$P$2:$P$1153,MATCH(34,'Base articles'!$T$2:$T$1153,0))),"") | I40: =IFERROR(IF(INDEX('Base articles'!$Q$2:$Q$1153,MATCH(34,'Base articles'!$T$2:$T$1153,0))="","",INDEX('Base articles'!$Q$2:$Q$1153,MATCH(34,'Base articles'!$T$2:$T$1153,0))),"") | J40: =IFERROR(IF(INDEX('Base articles'!$B$2:$B$1153,MATCH(34,'Base articles'!$T$2:$T$1153,0))="","",INDEX('Base articles'!$B$2:$B$1153,MATCH(34,'Base articles'!$T$2:$T$1153,0))),"")
A41: =IFERROR(IF(INDEX('Base articles'!$D$2:$D$1153,MATCH(35,'Base articles'!$T$2:$T$1153,0))="","",INDEX('Base articles'!$D$2:$D$1153,MATCH(35,'Base articles'!$T$2:$T$1153,0))),"") | B41: =IFERROR(IF(INDEX('Base articles'!$F$2:$F$1153,MATCH(35,'Base articles'!$T$2:$T$1153,0))="","",INDEX('Base articles'!$F$2:$F$1153,MATCH(35,'Base articles'!$T$2:$T$1153,0))),"") | C41: =IFERROR(INDEX('Base articles'!$H$2:$H$1153,MATCH(35,'Base articles'!$T$2:$T$1153,0)),"") | D41: =IFERROR(IF(INDEX('Base articles'!$G$2:$G$1153,MATCH(35,'Base articles'!$T$2:$T$1153,0))="","",INDEX('Base articles'!$G$2:$G$1153,MATCH(35,'Base articles'!$T$2:$T$1153,0))),"") | E41: =IFERROR(IF(INDEX('Base articles'!$K$2:$K$1153,MATCH(35,'Base articles'!$T$2:$T$1153,0))="","",INDEX('Base articles'!$K$2:$K$1153,MATCH(35,'Base articles'!$T$2:$T$1153,0))),"") | F41: =IFERROR(IF(INDEX('Base articles'!$M$2:$M$1153,MATCH(35,'Base articles'!$T$2:$T$1153,0))="","",INDEX('Base articles'!$M$2:$M$1153,MATCH(35,'Base articles'!$T$2:$T$1153,0))),"") | G41: =IFERROR(IF(INDEX('Base articles'!$N$2:$N$1153,MATCH(35,'Base articles'!$T$2:$T$1153,0))="","",INDEX('Base articles'!$N$2:$N$1153,MATCH(35,'Base articles'!$T$2:$T$1153,0))),"") | H41: =IFERROR(IF(INDEX('Base articles'!$P$2:$P$1153,MATCH(35,'Base articles'!$T$2:$T$1153,0))="","",INDEX('Base articles'!$P$2:$P$1153,MATCH(35,'Base articles'!$T$2:$T$1153,0))),"") | I41: =IFERROR(IF(INDEX('Base articles'!$Q$2:$Q$1153,MATCH(35,'Base articles'!$T$2:$T$1153,0))="","",INDEX('Base articles'!$Q$2:$Q$1153,MATCH(35,'Base articles'!$T$2:$T$1153,0))),"") | J41: =IFERROR(IF(INDEX('Base articles'!$B$2:$B$1153,MATCH(35,'Base articles'!$T$2:$T$1153,0))="","",INDEX('Base articles'!$B$2:$B$1153,MATCH(35,'Base articles'!$T$2:$T$1153,0))),"")
A42: =IFERROR(IF(INDEX('Base articles'!$D$2:$D$1153,MATCH(36,'Base articles'!$T$2:$T$1153,0))="","",INDEX('Base articles'!$D$2:$D$1153,MATCH(36,'Base articles'!$T$2:$T$1153,0))),"") | B42: =IFERROR(IF(INDEX('Base articles'!$F$2:$F$1153,MATCH(36,'Base articles'!$T$2:$T$1153,0))="","",INDEX('Base articles'!$F$2:$F$1153,MATCH(36,'Base articles'!$T$2:$T$1153,0))),"") | C42: =IFERROR(INDEX('Base articles'!$H$2:$H$1153,MATCH(36,'Base articles'!$T$2:$T$1153,0)),"") | D42: =IFERROR(IF(INDEX('Base articles'!$G$2:$G$1153,MATCH(36,'Base articles'!$T$2:$T$1153,0))="","",INDEX('Base articles'!$G$2:$G$1153,MATCH(36,'Base articles'!$T$2:$T$1153,0))),"") | E42: =IFERROR(IF(INDEX('Base articles'!$K$2:$K$1153,MATCH(36,'Base articles'!$T$2:$T$1153,0))="","",INDEX('Base articles'!$K$2:$K$1153,MATCH(36,'Base articles'!$T$2:$T$1153,0))),"") | F42: =IFERROR(IF(INDEX('Base articles'!$M$2:$M$1153,MATCH(36,'Base articles'!$T$2:$T$1153,0))="","",INDEX('Base articles'!$M$2:$M$1153,MATCH(36,'Base articles'!$T$2:$T$1153,0))),"") | G42: =IFERROR(IF(INDEX('Base articles'!$N$2:$N$1153,MATCH(36,'Base articles'!$T$2:$T$1153,0))="","",INDEX('Base articles'!$N$2:$N$1153,MATCH(36,'Base articles'!$T$2:$T$1153,0))),"") | H42: =IFERROR(IF(INDEX('Base articles'!$P$2:$P$1153,MATCH(36,'Base articles'!$T$2:$T$1153,0))="","",INDEX('Base articles'!$P$2:$P$1153,MATCH(36,'Base articles'!$T$2:$T$1153,0))),"") | I42: =IFERROR(IF(INDEX('Base articles'!$Q$2:$Q$1153,MATCH(36,'Base articles'!$T$2:$T$1153,0))="","",INDEX('Base articles'!$Q$2:$Q$1153,MATCH(36,'Base articles'!$T$2:$T$1153,0))),"") | J42: =IFERROR(IF(INDEX('Base articles'!$B$2:$B$1153,MATCH(36,'Base articles'!$T$2:$T$1153,0))="","",INDEX('Base articles'!$B$2:$B$1153,MATCH(36,'Base articles'!$T$2:$T$1153,0))),"")
A43: =IFERROR(IF(INDEX('Base articles'!$D$2:$D$1153,MATCH(37,'Base articles'!$T$2:$T$1153,0))="","",INDEX('Base articles'!$D$2:$D$1153,MATCH(37,'Base articles'!$T$2:$T$1153,0))),"") | B43: =IFERROR(IF(INDEX('Base articles'!$F$2:$F$1153,MATCH(37,'Base articles'!$T$2:$T$1153,0))="","",INDEX('Base articles'!$F$2:$F$1153,MATCH(37,'Base articles'!$T$2:$T$1153,0))),"") | C43: =IFERROR(INDEX('Base articles'!$H$2:$H$1153,MATCH(37,'Base articles'!$T$2:$T$1153,0)),"") | D43: =IFERROR(IF(INDEX('Base articles'!$G$2:$G$1153,MATCH(37,'Base articles'!$T$2:$T$1153,0))="","",INDEX('Base articles'!$G$2:$G$1153,MATCH(37,'Base articles'!$T$2:$T$1153,0))),"") | E43: =IFERROR(IF(INDEX('Base articles'!$K$2:$K$1153,MATCH(37,'Base articles'!$T$2:$T$1153,0))="","",INDEX('Base articles'!$K$2:$K$1153,MATCH(37,'Base articles'!$T$2:$T$1153,0))),"") | F43: =IFERROR(IF(INDEX('Base articles'!$M$2:$M$1153,MATCH(37,'Base articles'!$T$2:$T$1153,0))="","",INDEX('Base articles'!$M$2:$M$1153,MATCH(37,'Base articles'!$T$2:$T$1153,0))),"") | G43: =IFERROR(IF(INDEX('Base articles'!$N$2:$N$1153,MATCH(37,'Base articles'!$T$2:$T$1153,0))="","",INDEX('Base articles'!$N$2:$N$1153,MATCH(37,'Base articles'!$T$2:$T$1153,0))),"") | H43: =IFERROR(IF(INDEX('Base articles'!$P$2:$P$1153,MATCH(37,'Base articles'!$T$2:$T$1153,0))="","",INDEX('Base articles'!$P$2:$P$1153,MATCH(37,'Base articles'!$T$2:$T$1153,0))),"") | I43: =IFERROR(IF(INDEX('Base articles'!$Q$2:$Q$1153,MATCH(37,'Base articles'!$T$2:$T$1153,0))="","",INDEX('Base articles'!$Q$2:$Q$1153,MATCH(37,'Base articles'!$T$2:$T$1153,0))),"") | J43: =IFERROR(IF(INDEX('Base articles'!$B$2:$B$1153,MATCH(37,'Base articles'!$T$2:$T$1153,0))="","",INDEX('Base articles'!$B$2:$B$1153,MATCH(37,'Base articles'!$T$2:$T$1153,0))),"")
A44: =IFERROR(IF(INDEX('Base articles'!$D$2:$D$1153,MATCH(38,'Base articles'!$T$2:$T$1153,0))="","",INDEX('Base articles'!$D$2:$D$1153,MATCH(38,'Base articles'!$T$2:$T$1153,0))),"") | B44: =IFERROR(IF(INDEX('Base articles'!$F$2:$F$1153,MATCH(38,'Base articles'!$T$2:$T$1153,0))="","",INDEX('Base articles'!$F$2:$F$1153,MATCH(38,'Base articles'!$T$2:$T$1153,0))),"") | C44: =IFERROR(INDEX('Base articles'!$H$2:$H$1153,MATCH(38,'Base articles'!$T$2:$T$1153,0)),"") | D44: =IFERROR(IF(INDEX('Base articles'!$G$2:$G$1153,MATCH(38,'Base articles'!$T$2:$T$1153,0))="","",INDEX('Base articles'!$G$2:$G$1153,MATCH(38,'Base articles'!$T$2:$T$1153,0))),"") | E44: =IFERROR(IF(INDEX('Base articles'!$K$2:$K$1153,MATCH(38,'Base articles'!$T$2:$T$1153,0))="","",INDEX('Base articles'!$K$2:$K$1153,MATCH(38,'Base articles'!$T$2:$T$1153,0))),"") | F44: =IFERROR(IF(INDEX('Base articles'!$M$2:$M$1153,MATCH(38,'Base articles'!$T$2:$T$1153,0))="","",INDEX('Base articles'!$M$2:$M$1153,MATCH(38,'Base articles'!$T$2:$T$1153,0))),"") | G44: =IFERROR(IF(INDEX('Base articles'!$N$2:$N$1153,MATCH(38,'Base articles'!$T$2:$T$1153,0))="","",INDEX('Base articles'!$N$2:$N$1153,MATCH(38,'Base articles'!$T$2:$T$1153,0))),"") | H44: =IFERROR(IF(INDEX('Base articles'!$P$2:$P$1153,MATCH(38,'Base articles'!$T$2:$T$1153,0))="","",INDEX('Base articles'!$P$2:$P$1153,MATCH(38,'Base articles'!$T$2:$T$1153,0))),"") | I44: =IFERROR(IF(INDEX('Base articles'!$Q$2:$Q$1153,MATCH(38,'Base articles'!$T$2:$T$1153,0))="","",INDEX('Base articles'!$Q$2:$Q$1153,MATCH(38,'Base articles'!$T$2:$T$1153,0))),"") | J44: =IFERROR(IF(INDEX('Base articles'!$B$2:$B$1153,MATCH(38,'Base articles'!$T$2:$T$1153,0))="","",INDEX('Base articles'!$B$2:$B$1153,MATCH(38,'Base articles'!$T$2:$T$1153,0))),"")
A45: =IFERROR(IF(INDEX('Base articles'!$D$2:$D$1153,MATCH(39,'Base articles'!$T$2:$T$1153,0))="","",INDEX('Base articles'!$D$2:$D$1153,MATCH(39,'Base articles'!$T$2:$T$1153,0))),"") | B45: =IFERROR(IF(INDEX('Base articles'!$F$2:$F$1153,MATCH(39,'Base articles'!$T$2:$T$1153,0))="","",INDEX('Base articles'!$F$2:$F$1153,MATCH(39,'Base articles'!$T$2:$T$1153,0))),"") | C45: =IFERROR(INDEX('Base articles'!$H$2:$H$1153,MATCH(39,'Base articles'!$T$2:$T$1153,0)),"") | D45: =IFERROR(IF(INDEX('Base articles'!$G$2:$G$1153,MATCH(39,'Base articles'!$T$2:$T$1153,0))="","",INDEX('Base articles'!$G$2:$G$1153,MATCH(39,'Base articles'!$T$2:$T$1153,0))),"") | E45: =IFERROR(IF(INDEX('Base articles'!$K$2:$K$1153,MATCH(39,'Base articles'!$T$2:$T$1153,0))="","",INDEX('Base articles'!$K$2:$K$1153,MATCH(39,'Base articles'!$T$2:$T$1153,0))),"") | F45: =IFERROR(IF(INDEX('Base articles'!$M$2:$M$1153,MATCH(39,'Base articles'!$T$2:$T$1153,0))="","",INDEX('Base articles'!$M$2:$M$1153,MATCH(39,'Base articles'!$T$2:$T$1153,0))),"") | G45: =IFERROR(IF(INDEX('Base articles'!$N$2:$N$1153,MATCH(39,'Base articles'!$T$2:$T$1153,0))="","",INDEX('Base articles'!$N$2:$N$1153,MATCH(39,'Base articles'!$T$2:$T$1153,0))),"") | H45: =IFERROR(IF(INDEX('Base articles'!$P$2:$P$1153,MATCH(39,'Base articles'!$T$2:$T$1153,0))="","",INDEX('Base articles'!$P$2:$P$1153,MATCH(39,'Base articles'!$T$2:$T$1153,0))),"") | I45: =IFERROR(IF(INDEX('Base articles'!$Q$2:$Q$1153,MATCH(39,'Base articles'!$T$2:$T$1153,0))="","",INDEX('Base articles'!$Q$2:$Q$1153,MATCH(39,'Base articles'!$T$2:$T$1153,0))),"") | J45: =IFERROR(IF(INDEX('Base articles'!$B$2:$B$1153,MATCH(39,'Base articles'!$T$2:$T$1153,0))="","",INDEX('Base articles'!$B$2:$B$1153,MATCH(39,'Base articles'!$T$2:$T$1153,0))),"")
A46: =IFERROR(IF(INDEX('Base articles'!$D$2:$D$1153,MATCH(40,'Base articles'!$T$2:$T$1153,0))="","",INDEX('Base articles'!$D$2:$D$1153,MATCH(40,'Base articles'!$T$2:$T$1153,0))),"") | B46: =IFERROR(IF(INDEX('Base articles'!$F$2:$F$1153,MATCH(40,'Base articles'!$T$2:$T$1153,0))="","",INDEX('Base articles'!$F$2:$F$1153,MATCH(40,'Base articles'!$T$2:$T$1153,0))),"") | C46: =IFERROR(INDEX('Base articles'!$H$2:$H$1153,MATCH(40,'Base articles'!$T$2:$T$1153,0)),"") | D46: =IFERROR(IF(INDEX('Base articles'!$G$2:$G$1153,MATCH(40,'Base articles'!$T$2:$T$1153,0))="","",INDEX('Base articles'!$G$2:$G$1153,MATCH(40,'Base articles'!$T$2:$T$1153,0))),"") | E46: =IFERROR(IF(INDEX('Base articles'!$K$2:$K$1153,MATCH(40,'Base articles'!$T$2:$T$1153,0))="","",INDEX('Base articles'!$K$2:$K$1153,MATCH(40,'Base articles'!$T$2:$T$1153,0))),"") | F46: =IFERROR(IF(INDEX('Base articles'!$M$2:$M$1153,MATCH(40,'Base articles'!$T$2:$T$1153,0))="","",INDEX('Base articles'!$M$2:$M$1153,MATCH(40,'Base articles'!$T$2:$T$1153,0))),"") | G46: =IFERROR(IF(INDEX('Base articles'!$N$2:$N$1153,MATCH(40,'Base articles'!$T$2:$T$1153,0))="","",INDEX('Base articles'!$N$2:$N$1153,MATCH(40,'Base articles'!$T$2:$T$1153,0))),"") | H46: =IFERROR(IF(INDEX('Base articles'!$P$2:$P$1153,MATCH(40,'Base articles'!$T$2:$T$1153,0))="","",INDEX('Base articles'!$P$2:$P$1153,MATCH(40,'Base articles'!$T$2:$T$1153,0))),"") | I46: =IFERROR(IF(INDEX('Base articles'!$Q$2:$Q$1153,MATCH(40,'Base articles'!$T$2:$T$1153,0))="","",INDEX('Base articles'!$Q$2:$Q$1153,MATCH(40,'Base articles'!$T$2:$T$1153,0))),"") | J46: =IFERROR(IF(INDEX('Base articles'!$B$2:$B$1153,MATCH(40,'Base articles'!$T$2:$T$1153,0))="","",INDEX('Base articles'!$B$2:$B$1153,MATCH(40,'Base articles'!$T$2:$T$1153,0))),"")
A47: =IFERROR(IF(INDEX('Base articles'!$D$2:$D$1153,MATCH(41,'Base articles'!$T$2:$T$1153,0))="","",INDEX('Base articles'!$D$2:$D$1153,MATCH(41,'Base articles'!$T$2:$T$1153,0))),"") | B47: =IFERROR(IF(INDEX('Base articles'!$F$2:$F$1153,MATCH(41,'Base articles'!$T$2:$T$1153,0))="","",INDEX('Base articles'!$F$2:$F$1153,MATCH(41,'Base articles'!$T$2:$T$1153,0))),"") | C47: =IFERROR(INDEX('Base articles'!$H$2:$H$1153,MATCH(41,'Base articles'!$T$2:$T$1153,0)),"") | D47: =IFERROR(IF(INDEX('Base articles'!$G$2:$G$1153,MATCH(41,'Base articles'!$T$2:$T$1153,0))="","",INDEX('Base articles'!$G$2:$G$1153,MATCH(41,'Base articles'!$T$2:$T$1153,0))),"") | E47: =IFERROR(IF(INDEX('Base articles'!$K$2:$K$1153,MATCH(41,'Base articles'!$T$2:$T$1153,0))="","",INDEX('Base articles'!$K$2:$K$1153,MATCH(41,'Base articles'!$T$2:$T$1153,0))),"") | F47: =IFERROR(IF(INDEX('Base articles'!$M$2:$M$1153,MATCH(41,'Base articles'!$T$2:$T$1153,0))="","",INDEX('Base articles'!$M$2:$M$1153,MATCH(41,'Base articles'!$T$2:$T$1153,0))),"") | G47: =IFERROR(IF(INDEX('Base articles'!$N$2:$N$1153,MATCH(41,'Base articles'!$T$2:$T$1153,0))="","",INDEX('Base articles'!$N$2:$N$1153,MATCH(41,'Base articles'!$T$2:$T$1153,0))),"") | H47: =IFERROR(IF(INDEX('Base articles'!$P$2:$P$1153,MATCH(41,'Base articles'!$T$2:$T$1153,0))="","",INDEX('Base articles'!$P$2:$P$1153,MATCH(41,'Base articles'!$T$2:$T$1153,0))),"") | I47: =IFERROR(IF(INDEX('Base articles'!$Q$2:$Q$1153,MATCH(41,'Base articles'!$T$2:$T$1153,0))="","",INDEX('Base articles'!$Q$2:$Q$1153,MATCH(41,'Base articles'!$T$2:$T$1153,0))),"") | J47: =IFERROR(IF(INDEX('Base articles'!$B$2:$B$1153,MATCH(41,'Base articles'!$T$2:$T$1153,0))="","",INDEX('Base articles'!$B$2:$B$1153,MATCH(41,'Base articles'!$T$2:$T$1153,0))),"")
A48: =IFERROR(IF(INDEX('Base articles'!$D$2:$D$1153,MATCH(42,'Base articles'!$T$2:$T$1153,0))="","",INDEX('Base articles'!$D$2:$D$1153,MATCH(42,'Base articles'!$T$2:$T$1153,0))),"") | B48: =IFERROR(IF(INDEX('Base articles'!$F$2:$F$1153,MATCH(42,'Base articles'!$T$2:$T$1153,0))="","",INDEX('Base articles'!$F$2:$F$1153,MATCH(42,'Base articles'!$T$2:$T$1153,0))),"") | C48: =IFERROR(INDEX('Base articles'!$H$2:$H$1153,MATCH(42,'Base articles'!$T$2:$T$1153,0)),"") | D48: =IFERROR(IF(INDEX('Base articles'!$G$2:$G$1153,MATCH(42,'Base articles'!$T$2:$T$1153,0))="","",INDEX('Base articles'!$G$2:$G$1153,MATCH(42,'Base articles'!$T$2:$T$1153,0))),"") | E48: =IFERROR(IF(INDEX('Base articles'!$K$2:$K$1153,MATCH(42,'Base articles'!$T$2:$T$1153,0))="","",INDEX('Base articles'!$K$2:$K$1153,MATCH(42,'Base articles'!$T$2:$T$1153,0))),"") | F48: =IFERROR(IF(INDEX('Base articles'!$M$2:$M$1153,MATCH(42,'Base articles'!$T$2:$T$1153,0))="","",INDEX('Base articles'!$M$2:$M$1153,MATCH(42,'Base articles'!$T$2:$T$1153,0))),"") | G48: =IFERROR(IF(INDEX('Base articles'!$N$2:$N$1153,MATCH(42,'Base articles'!$T$2:$T$1153,0))="","",INDEX('Base articles'!$N$2:$N$1153,MATCH(42,'Base articles'!$T$2:$T$1153,0))),"") | H48: =IFERROR(IF(INDEX('Base articles'!$P$2:$P$1153,MATCH(42,'Base articles'!$T$2:$T$1153,0))="","",INDEX('Base articles'!$P$2:$P$1153,MATCH(42,'Base articles'!$T$2:$T$1153,0))),"") | I48: =IFERROR(IF(INDEX('Base articles'!$Q$2:$Q$1153,MATCH(42,'Base articles'!$T$2:$T$1153,0))="","",INDEX('Base articles'!$Q$2:$Q$1153,MATCH(42,'Base articles'!$T$2:$T$1153,0))),"") | J48: =IFERROR(IF(INDEX('Base articles'!$B$2:$B$1153,MATCH(42,'Base articles'!$T$2:$T$1153,0))="","",INDEX('Base articles'!$B$2:$B$1153,MATCH(42,'Base articles'!$T$2:$T$1153,0))),"")
A49: =IFERROR(IF(INDEX('Base articles'!$D$2:$D$1153,MATCH(43,'Base articles'!$T$2:$T$1153,0))="","",INDEX('Base articles'!$D$2:$D$1153,MATCH(43,'Base articles'!$T$2:$T$1153,0))),"") | B49: =IFERROR(IF(INDEX('Base articles'!$F$2:$F$1153,MATCH(43,'Base articles'!$T$2:$T$1153,0))="","",INDEX('Base articles'!$F$2:$F$1153,MATCH(43,'Base articles'!$T$2:$T$1153,0))),"") | C49: =IFERROR(INDEX('Base articles'!$H$2:$H$1153,MATCH(43,'Base articles'!$T$2:$T$1153,0)),"") | D49: =IFERROR(IF(INDEX('Base articles'!$G$2:$G$1153,MATCH(43,'Base articles'!$T$2:$T$1153,0))="","",INDEX('Base articles'!$G$2:$G$1153,MATCH(43,'Base articles'!$T$2:$T$1153,0))),"") | E49: =IFERROR(IF(INDEX('Base articles'!$K$2:$K$1153,MATCH(43,'Base articles'!$T$2:$T$1153,0))="","",INDEX('Base articles'!$K$2:$K$1153,MATCH(43,'Base articles'!$T$2:$T$1153,0))),"") | F49: =IFERROR(IF(INDEX('Base articles'!$M$2:$M$1153,MATCH(43,'Base articles'!$T$2:$T$1153,0))="","",INDEX('Base articles'!$M$2:$M$1153,MATCH(43,'Base articles'!$T$2:$T$1153,0))),"") | G49: =IFERROR(IF(INDEX('Base articles'!$N$2:$N$1153,MATCH(43,'Base articles'!$T$2:$T$1153,0))="","",INDEX('Base articles'!$N$2:$N$1153,MATCH(43,'Base articles'!$T$2:$T$1153,0))),"") | H49: =IFERROR(IF(INDEX('Base articles'!$P$2:$P$1153,MATCH(43,'Base articles'!$T$2:$T$1153,0))="","",INDEX('Base articles'!$P$2:$P$1153,MATCH(43,'Base articles'!$T$2:$T$1153,0))),"") | I49: =IFERROR(IF(INDEX('Base articles'!$Q$2:$Q$1153,MATCH(43,'Base articles'!$T$2:$T$1153,0))="","",INDEX('Base articles'!$Q$2:$Q$1153,MATCH(43,'Base articles'!$T$2:$T$1153,0))),"") | J49: =IFERROR(IF(INDEX('Base articles'!$B$2:$B$1153,MATCH(43,'Base articles'!$T$2:$T$1153,0))="","",INDEX('Base articles'!$B$2:$B$1153,MATCH(43,'Base articles'!$T$2:$T$1153,0))),"")
A50: =IFERROR(IF(INDEX('Base articles'!$D$2:$D$1153,MATCH(44,'Base articles'!$T$2:$T$1153,0))="","",INDEX('Base articles'!$D$2:$D$1153,MATCH(44,'Base articles'!$T$2:$T$1153,0))),"") | B50: =IFERROR(IF(INDEX('Base articles'!$F$2:$F$1153,MATCH(44,'Base articles'!$T$2:$T$1153,0))="","",INDEX('Base articles'!$F$2:$F$1153,MATCH(44,'Base articles'!$T$2:$T$1153,0))),"") | C50: =IFERROR(INDEX('Base articles'!$H$2:$H$1153,MATCH(44,'Base articles'!$T$2:$T$1153,0)),"") | D50: =IFERROR(IF(INDEX('Base articles'!$G$2:$G$1153,MATCH(44,'Base articles'!$T$2:$T$1153,0))="","",INDEX('Base articles'!$G$2:$G$1153,MATCH(44,'Base articles'!$T$2:$T$1153,0))),"") | E50: =IFERROR(IF(INDEX('Base articles'!$K$2:$K$1153,MATCH(44,'Base articles'!$T$2:$T$1153,0))="","",INDEX('Base articles'!$K$2:$K$1153,MATCH(44,'Base articles'!$T$2:$T$1153,0))),"") | F50: =IFERROR(IF(INDEX('Base articles'!$M$2:$M$1153,MATCH(44,'Base articles'!$T$2:$T$1153,0))="","",INDEX('Base articles'!$M$2:$M$1153,MATCH(44,'Base articles'!$T$2:$T$1153,0))),"") | G50: =IFERROR(IF(INDEX('Base articles'!$N$2:$N$1153,MATCH(44,'Base articles'!$T$2:$T$1153,0))="","",INDEX('Base articles'!$N$2:$N$1153,MATCH(44,'Base articles'!$T$2:$T$1153,0))),"") | H50: =IFERROR(IF(INDEX('Base articles'!$P$2:$P$1153,MATCH(44,'Base articles'!$T$2:$T$1153,0))="","",INDEX('Base articles'!$P$2:$P$1153,MATCH(44,'Base articles'!$T$2:$T$1153,0))),"") | I50: =IFERROR(IF(INDEX('Base articles'!$Q$2:$Q$1153,MATCH(44,'Base articles'!$T$2:$T$1153,0))="","",INDEX('Base articles'!$Q$2:$Q$1153,MATCH(44,'Base articles'!$T$2:$T$1153,0))),"") | J50: =IFERROR(IF(INDEX('Base articles'!$B$2:$B$1153,MATCH(44,'Base articles'!$T$2:$T$1153,0))="","",INDEX('Base articles'!$B$2:$B$1153,MATCH(44,'Base articles'!$T$2:$T$1153,0))),"")
A51: =IFERROR(IF(INDEX('Base articles'!$D$2:$D$1153,MATCH(45,'Base articles'!$T$2:$T$1153,0))="","",INDEX('Base articles'!$D$2:$D$1153,MATCH(45,'Base articles'!$T$2:$T$1153,0))),"") | B51: =IFERROR(IF(INDEX('Base articles'!$F$2:$F$1153,MATCH(45,'Base articles'!$T$2:$T$1153,0))="","",INDEX('Base articles'!$F$2:$F$1153,MATCH(45,'Base articles'!$T$2:$T$1153,0))),"") | C51: =IFERROR(INDEX('Base articles'!$H$2:$H$1153,MATCH(45,'Base articles'!$T$2:$T$1153,0)),"") | D51: =IFERROR(IF(INDEX('Base articles'!$G$2:$G$1153,MATCH(45,'Base articles'!$T$2:$T$1153,0))="","",INDEX('Base articles'!$G$2:$G$1153,MATCH(45,'Base articles'!$T$2:$T$1153,0))),"") | E51: =IFERROR(IF(INDEX('Base articles'!$K$2:$K$1153,MATCH(45,'Base articles'!$T$2:$T$1153,0))="","",INDEX('Base articles'!$K$2:$K$1153,MATCH(45,'Base articles'!$T$2:$T$1153,0))),"") | F51: =IFERROR(IF(INDEX('Base articles'!$M$2:$M$1153,MATCH(45,'Base articles'!$T$2:$T$1153,0))="","",INDEX('Base articles'!$M$2:$M$1153,MATCH(45,'Base articles'!$T$2:$T$1153,0))),"") | G51: =IFERROR(IF(INDEX('Base articles'!$N$2:$N$1153,MATCH(45,'Base articles'!$T$2:$T$1153,0))="","",INDEX('Base articles'!$N$2:$N$1153,MATCH(45,'Base articles'!$T$2:$T$1153,0))),"") | H51: =IFERROR(IF(INDEX('Base articles'!$P$2:$P$1153,MATCH(45,'Base articles'!$T$2:$T$1153,0))="","",INDEX('Base articles'!$P$2:$P$1153,MATCH(45,'Base articles'!$T$2:$T$1153,0))),"") | I51: =IFERROR(IF(INDEX('Base articles'!$Q$2:$Q$1153,MATCH(45,'Base articles'!$T$2:$T$1153,0))="","",INDEX('Base articles'!$Q$2:$Q$1153,MATCH(45,'Base articles'!$T$2:$T$1153,0))),"") | J51: =IFERROR(IF(INDEX('Base articles'!$B$2:$B$1153,MATCH(45,'Base articles'!$T$2:$T$1153,0))="","",INDEX('Base articles'!$B$2:$B$1153,MATCH(45,'Base articles'!$T$2:$T$1153,0))),"")
A52: =IFERROR(IF(INDEX('Base articles'!$D$2:$D$1153,MATCH(46,'Base articles'!$T$2:$T$1153,0))="","",INDEX('Base articles'!$D$2:$D$1153,MATCH(46,'Base articles'!$T$2:$T$1153,0))),"") | B52: =IFERROR(IF(INDEX('Base articles'!$F$2:$F$1153,MATCH(46,'Base articles'!$T$2:$T$1153,0))="","",INDEX('Base articles'!$F$2:$F$1153,MATCH(46,'Base articles'!$T$2:$T$1153,0))),"") | C52: =IFERROR(INDEX('Base articles'!$H$2:$H$1153,MATCH(46,'Base articles'!$T$2:$T$1153,0)),"") | D52: =IFERROR(IF(INDEX('Base articles'!$G$2:$G$1153,MATCH(46,'Base articles'!$T$2:$T$1153,0))="","",INDEX('Base articles'!$G$2:$G$1153,MATCH(46,'Base articles'!$T$2:$T$1153,0))),"") | E52: =IFERROR(IF(INDEX('Base articles'!$K$2:$K$1153,MATCH(46,'Base articles'!$T$2:$T$1153,0))="","",INDEX('Base articles'!$K$2:$K$1153,MATCH(46,'Base articles'!$T$2:$T$1153,0))),"") | F52: =IFERROR(IF(INDEX('Base articles'!$M$2:$M$1153,MATCH(46,'Base articles'!$T$2:$T$1153,0))="","",INDEX('Base articles'!$M$2:$M$1153,MATCH(46,'Base articles'!$T$2:$T$1153,0))),"") | G52: =IFERROR(IF(INDEX('Base articles'!$N$2:$N$1153,MATCH(46,'Base articles'!$T$2:$T$1153,0))="","",INDEX('Base articles'!$N$2:$N$1153,MATCH(46,'Base articles'!$T$2:$T$1153,0))),"") | H52: =IFERROR(IF(INDEX('Base articles'!$P$2:$P$1153,MATCH(46,'Base articles'!$T$2:$T$1153,0))="","",INDEX('Base articles'!$P$2:$P$1153,MATCH(46,'Base articles'!$T$2:$T$1153,0))),"") | I52: =IFERROR(IF(INDEX('Base articles'!$Q$2:$Q$1153,MATCH(46,'Base articles'!$T$2:$T$1153,0))="","",INDEX('Base articles'!$Q$2:$Q$1153,MATCH(46,'Base articles'!$T$2:$T$1153,0))),"") | J52: =IFERROR(IF(INDEX('Base articles'!$B$2:$B$1153,MATCH(46,'Base articles'!$T$2:$T$1153,0))="","",INDEX('Base articles'!$B$2:$B$1153,MATCH(46,'Base articles'!$T$2:$T$1153,0))),"")
A53: =IFERROR(IF(INDEX('Base articles'!$D$2:$D$1153,MATCH(47,'Base articles'!$T$2:$T$1153,0))="","",INDEX('Base articles'!$D$2:$D$1153,MATCH(47,'Base articles'!$T$2:$T$1153,0))),"") | B53: =IFERROR(IF(INDEX('Base articles'!$F$2:$F$1153,MATCH(47,'Base articles'!$T$2:$T$1153,0))="","",INDEX('Base articles'!$F$2:$F$1153,MATCH(47,'Base articles'!$T$2:$T$1153,0))),"") | C53: =IFERROR(INDEX('Base articles'!$H$2:$H$1153,MATCH(47,'Base articles'!$T$2:$T$1153,0)),"") | D53: =IFERROR(IF(INDEX('Base articles'!$G$2:$G$1153,MATCH(47,'Base articles'!$T$2:$T$1153,0))="","",INDEX('Base articles'!$G$2:$G$1153,MATCH(47,'Base articles'!$T$2:$T$1153,0))),"") | E53: =IFERROR(IF(INDEX('Base articles'!$K$2:$K$1153,MATCH(47,'Base articles'!$T$2:$T$1153,0))="","",INDEX('Base articles'!$K$2:$K$1153,MATCH(47,'Base articles'!$T$2:$T$1153,0))),"") | F53: =IFERROR(IF(INDEX('Base articles'!$M$2:$M$1153,MATCH(47,'Base articles'!$T$2:$T$1153,0))="","",INDEX('Base articles'!$M$2:$M$1153,MATCH(47,'Base articles'!$T$2:$T$1153,0))),"") | G53: =IFERROR(IF(INDEX('Base articles'!$N$2:$N$1153,MATCH(47,'Base articles'!$T$2:$T$1153,0))="","",INDEX('Base articles'!$N$2:$N$1153,MATCH(47,'Base articles'!$T$2:$T$1153,0))),"") | H53: =IFERROR(IF(INDEX('Base articles'!$P$2:$P$1153,MATCH(47,'Base articles'!$T$2:$T$1153,0))="","",INDEX('Base articles'!$P$2:$P$1153,MATCH(47,'Base articles'!$T$2:$T$1153,0))),"") | I53: =IFERROR(IF(INDEX('Base articles'!$Q$2:$Q$1153,MATCH(47,'Base articles'!$T$2:$T$1153,0))="","",INDEX('Base articles'!$Q$2:$Q$1153,MATCH(47,'Base articles'!$T$2:$T$1153,0))),"") | J53: =IFERROR(IF(INDEX('Base articles'!$B$2:$B$1153,MATCH(47,'Base articles'!$T$2:$T$1153,0))="","",INDEX('Base articles'!$B$2:$B$1153,MATCH(47,'Base articles'!$T$2:$T$1153,0))),"")
A54: =IFERROR(IF(INDEX('Base articles'!$D$2:$D$1153,MATCH(48,'Base articles'!$T$2:$T$1153,0))="","",INDEX('Base articles'!$D$2:$D$1153,MATCH(48,'Base articles'!$T$2:$T$1153,0))),"") | B54: =IFERROR(IF(INDEX('Base articles'!$F$2:$F$1153,MATCH(48,'Base articles'!$T$2:$T$1153,0))="","",INDEX('Base articles'!$F$2:$F$1153,MATCH(48,'Base articles'!$T$2:$T$1153,0))),"") | C54: =IFERROR(INDEX('Base articles'!$H$2:$H$1153,MATCH(48,'Base articles'!$T$2:$T$1153,0)),"") | D54: =IFERROR(IF(INDEX('Base articles'!$G$2:$G$1153,MATCH(48,'Base articles'!$T$2:$T$1153,0))="","",INDEX('Base articles'!$G$2:$G$1153,MATCH(48,'Base articles'!$T$2:$T$1153,0))),"") | E54: =IFERROR(IF(INDEX('Base articles'!$K$2:$K$1153,MATCH(48,'Base articles'!$T$2:$T$1153,0))="","",INDEX('Base articles'!$K$2:$K$1153,MATCH(48,'Base articles'!$T$2:$T$1153,0))),"") | F54: =IFERROR(IF(INDEX('Base articles'!$M$2:$M$1153,MATCH(48,'Base articles'!$T$2:$T$1153,0))="","",INDEX('Base articles'!$M$2:$M$1153,MATCH(48,'Base articles'!$T$2:$T$1153,0))),"") | G54: =IFERROR(IF(INDEX('Base articles'!$N$2:$N$1153,MATCH(48,'Base articles'!$T$2:$T$1153,0))="","",INDEX('Base articles'!$N$2:$N$1153,MATCH(48,'Base articles'!$T$2:$T$1153,0))),"") | H54: =IFERROR(IF(INDEX('Base articles'!$P$2:$P$1153,MATCH(48,'Base articles'!$T$2:$T$1153,0))="","",INDEX('Base articles'!$P$2:$P$1153,MATCH(48,'Base articles'!$T$2:$T$1153,0))),"") | I54: =IFERROR(IF(INDEX('Base articles'!$Q$2:$Q$1153,MATCH(48,'Base articles'!$T$2:$T$1153,0))="","",INDEX('Base articles'!$Q$2:$Q$1153,MATCH(48,'Base articles'!$T$2:$T$1153,0))),"") | J54: =IFERROR(IF(INDEX('Base articles'!$B$2:$B$1153,MATCH(48,'Base articles'!$T$2:$T$1153,0))="","",INDEX('Base articles'!$B$2:$B$1153,MATCH(48,'Base articles'!$T$2:$T$1153,0))),"")
A55: =IFERROR(IF(INDEX('Base articles'!$D$2:$D$1153,MATCH(49,'Base articles'!$T$2:$T$1153,0))="","",INDEX('Base articles'!$D$2:$D$1153,MATCH(49,'Base articles'!$T$2:$T$1153,0))),"") | B55: =IFERROR(IF(INDEX('Base articles'!$F$2:$F$1153,MATCH(49,'Base articles'!$T$2:$T$1153,0))="","",INDEX('Base articles'!$F$2:$F$1153,MATCH(49,'Base articles'!$T$2:$T$1153,0))),"") | C55: =IFERROR(INDEX('Base articles'!$H$2:$H$1153,MATCH(49,'Base articles'!$T$2:$T$1153,0)),"") | D55: =IFERROR(IF(INDEX('Base articles'!$G$2:$G$1153,MATCH(49,'Base articles'!$T$2:$T$1153,0))="","",INDEX('Base articles'!$G$2:$G$1153,MATCH(49,'Base articles'!$T$2:$T$1153,0))),"") | E55: =IFERROR(IF(INDEX('Base articles'!$K$2:$K$1153,MATCH(49,'Base articles'!$T$2:$T$1153,0))="","",INDEX('Base articles'!$K$2:$K$1153,MATCH(49,'Base articles'!$T$2:$T$1153,0))),"") | F55: =IFERROR(IF(INDEX('Base articles'!$M$2:$M$1153,MATCH(49,'Base articles'!$T$2:$T$1153,0))="","",INDEX('Base articles'!$M$2:$M$1153,MATCH(49,'Base articles'!$T$2:$T$1153,0))),"") | G55: =IFERROR(IF(INDEX('Base articles'!$N$2:$N$1153,MATCH(49,'Base articles'!$T$2:$T$1153,0))="","",INDEX('Base articles'!$N$2:$N$1153,MATCH(49,'Base articles'!$T$2:$T$1153,0))),"") | H55: =IFERROR(IF(INDEX('Base articles'!$P$2:$P$1153,MATCH(49,'Base articles'!$T$2:$T$1153,0))="","",INDEX('Base articles'!$P$2:$P$1153,MATCH(49,'Base articles'!$T$2:$T$1153,0))),"") | I55: =IFERROR(IF(INDEX('Base articles'!$Q$2:$Q$1153,MATCH(49,'Base articles'!$T$2:$T$1153,0))="","",INDEX('Base articles'!$Q$2:$Q$1153,MATCH(49,'Base articles'!$T$2:$T$1153,0))),"") | J55: =IFERROR(IF(INDEX('Base articles'!$B$2:$B$1153,MATCH(49,'Base articles'!$T$2:$T$1153,0))="","",INDEX('Base articles'!$B$2:$B$1153,MATCH(49,'Base articles'!$T$2:$T$1153,0))),"")
A56: =IFERROR(IF(INDEX('Base articles'!$D$2:$D$1153,MATCH(50,'Base articles'!$T$2:$T$1153,0))="","",INDEX('Base articles'!$D$2:$D$1153,MATCH(50,'Base articles'!$T$2:$T$1153,0))),"") | B56: =IFERROR(IF(INDEX('Base articles'!$F$2:$F$1153,MATCH(50,'Base articles'!$T$2:$T$1153,0))="","",INDEX('Base articles'!$F$2:$F$1153,MATCH(50,'Base articles'!$T$2:$T$1153,0))),"") | C56: =IFERROR(INDEX('Base articles'!$H$2:$H$1153,MATCH(50,'Base articles'!$T$2:$T$1153,0)),"") | D56: =IFERROR(IF(INDEX('Base articles'!$G$2:$G$1153,MATCH(50,'Base articles'!$T$2:$T$1153,0))="","",INDEX('Base articles'!$G$2:$G$1153,MATCH(50,'Base articles'!$T$2:$T$1153,0))),"") | E56: =IFERROR(IF(INDEX('Base articles'!$K$2:$K$1153,MATCH(50,'Base articles'!$T$2:$T$1153,0))="","",INDEX('Base articles'!$K$2:$K$1153,MATCH(50,'Base articles'!$T$2:$T$1153,0))),"") | F56: =IFERROR(IF(INDEX('Base articles'!$M$2:$M$1153,MATCH(50,'Base articles'!$T$2:$T$1153,0))="","",INDEX('Base articles'!$M$2:$M$1153,MATCH(50,'Base articles'!$T$2:$T$1153,0))),"") | G56: =IFERROR(IF(INDEX('Base articles'!$N$2:$N$1153,MATCH(50,'Base articles'!$T$2:$T$1153,0))="","",INDEX('Base articles'!$N$2:$N$1153,MATCH(50,'Base articles'!$T$2:$T$1153,0))),"") | H56: =IFERROR(IF(INDEX('Base articles'!$P$2:$P$1153,MATCH(50,'Base articles'!$T$2:$T$1153,0))="","",INDEX('Base articles'!$P$2:$P$1153,MATCH(50,'Base articles'!$T$2:$T$1153,0))),"") | I56: =IFERROR(IF(INDEX('Base articles'!$Q$2:$Q$1153,MATCH(50,'Base articles'!$T$2:$T$1153,0))="","",INDEX('Base articles'!$Q$2:$Q$1153,MATCH(50,'Base articles'!$T$2:$T$1153,0))),"") | J56: =IFERROR(IF(INDEX('Base articles'!$B$2:$B$1153,MATCH(50,'Base articles'!$T$2:$T$1153,0))="","",INDEX('Base articles'!$B$2:$B$1153,MATCH(50,'Base articles'!$T$2:$T$1153,0))),"")
A57: =IFERROR(IF(INDEX('Base articles'!$D$2:$D$1153,MATCH(51,'Base articles'!$T$2:$T$1153,0))="","",INDEX('Base articles'!$D$2:$D$1153,MATCH(51,'Base articles'!$T$2:$T$1153,0))),"") | B57: =IFERROR(IF(INDEX('Base articles'!$F$2:$F$1153,MATCH(51,'Base articles'!$T$2:$T$1153,0))="","",INDEX('Base articles'!$F$2:$F$1153,MATCH(51,'Base articles'!$T$2:$T$1153,0))),"") | C57: =IFERROR(INDEX('Base articles'!$H$2:$H$1153,MATCH(51,'Base articles'!$T$2:$T$1153,0)),"") | D57: =IFERROR(IF(INDEX('Base articles'!$G$2:$G$1153,MATCH(51,'Base articles'!$T$2:$T$1153,0))="","",INDEX('Base articles'!$G$2:$G$1153,MATCH(51,'Base articles'!$T$2:$T$1153,0))),"") | E57: =IFERROR(IF(INDEX('Base articles'!$K$2:$K$1153,MATCH(51,'Base articles'!$T$2:$T$1153,0))="","",INDEX('Base articles'!$K$2:$K$1153,MATCH(51,'Base articles'!$T$2:$T$1153,0))),"") | F57: =IFERROR(IF(INDEX('Base articles'!$M$2:$M$1153,MATCH(51,'Base articles'!$T$2:$T$1153,0))="","",INDEX('Base articles'!$M$2:$M$1153,MATCH(51,'Base articles'!$T$2:$T$1153,0))),"") | G57: =IFERROR(IF(INDEX('Base articles'!$N$2:$N$1153,MATCH(51,'Base articles'!$T$2:$T$1153,0))="","",INDEX('Base articles'!$N$2:$N$1153,MATCH(51,'Base articles'!$T$2:$T$1153,0))),"") | H57: =IFERROR(IF(INDEX('Base articles'!$P$2:$P$1153,MATCH(51,'Base articles'!$T$2:$T$1153,0))="","",INDEX('Base articles'!$P$2:$P$1153,MATCH(51,'Base articles'!$T$2:$T$1153,0))),"") | I57: =IFERROR(IF(INDEX('Base articles'!$Q$2:$Q$1153,MATCH(51,'Base articles'!$T$2:$T$1153,0))="","",INDEX('Base articles'!$Q$2:$Q$1153,MATCH(51,'Base articles'!$T$2:$T$1153,0))),"") | J57: =IFERROR(IF(INDEX('Base articles'!$B$2:$B$1153,MATCH(51,'Base articles'!$T$2:$T$1153,0))="","",INDEX('Base articles'!$B$2:$B$1153,MATCH(51,'Base articles'!$T$2:$T$1153,0))),"")
A58: =IFERROR(IF(INDEX('Base articles'!$D$2:$D$1153,MATCH(52,'Base articles'!$T$2:$T$1153,0))="","",INDEX('Base articles'!$D$2:$D$1153,MATCH(52,'Base articles'!$T$2:$T$1153,0))),"") | B58: =IFERROR(IF(INDEX('Base articles'!$F$2:$F$1153,MATCH(52,'Base articles'!$T$2:$T$1153,0))="","",INDEX('Base articles'!$F$2:$F$1153,MATCH(52,'Base articles'!$T$2:$T$1153,0))),"") | C58: =IFERROR(INDEX('Base articles'!$H$2:$H$1153,MATCH(52,'Base articles'!$T$2:$T$1153,0)),"") | D58: =IFERROR(IF(INDEX('Base articles'!$G$2:$G$1153,MATCH(52,'Base articles'!$T$2:$T$1153,0))="","",INDEX('Base articles'!$G$2:$G$1153,MATCH(52,'Base articles'!$T$2:$T$1153,0))),"") | E58: =IFERROR(IF(INDEX('Base articles'!$K$2:$K$1153,MATCH(52,'Base articles'!$T$2:$T$1153,0))="","",INDEX('Base articles'!$K$2:$K$1153,MATCH(52,'Base articles'!$T$2:$T$1153,0))),"") | F58: =IFERROR(IF(INDEX('Base articles'!$M$2:$M$1153,MATCH(52,'Base articles'!$T$2:$T$1153,0))="","",INDEX('Base articles'!$M$2:$M$1153,MATCH(52,'Base articles'!$T$2:$T$1153,0))),"") | G58: =IFERROR(IF(INDEX('Base articles'!$N$2:$N$1153,MATCH(52,'Base articles'!$T$2:$T$1153,0))="","",INDEX('Base articles'!$N$2:$N$1153,MATCH(52,'Base articles'!$T$2:$T$1153,0))),"") | H58: =IFERROR(IF(INDEX('Base articles'!$P$2:$P$1153,MATCH(52,'Base articles'!$T$2:$T$1153,0))="","",INDEX('Base articles'!$P$2:$P$1153,MATCH(52,'Base articles'!$T$2:$T$1153,0))),"") | I58: =IFERROR(IF(INDEX('Base articles'!$Q$2:$Q$1153,MATCH(52,'Base articles'!$T$2:$T$1153,0))="","",INDEX('Base articles'!$Q$2:$Q$1153,MATCH(52,'Base articles'!$T$2:$T$1153,0))),"") | J58: =IFERROR(IF(INDEX('Base articles'!$B$2:$B$1153,MATCH(52,'Base articles'!$T$2:$T$1153,0))="","",INDEX('Base articles'!$B$2:$B$1153,MATCH(52,'Base articles'!$T$2:$T$1153,0))),"")
A59: =IFERROR(IF(INDEX('Base articles'!$D$2:$D$1153,MATCH(53,'Base articles'!$T$2:$T$1153,0))="","",INDEX('Base articles'!$D$2:$D$1153,MATCH(53,'Base articles'!$T$2:$T$1153,0))),"") | B59: =IFERROR(IF(INDEX('Base articles'!$F$2:$F$1153,MATCH(53,'Base articles'!$T$2:$T$1153,0))="","",INDEX('Base articles'!$F$2:$F$1153,MATCH(53,'Base articles'!$T$2:$T$1153,0))),"") | C59: =IFERROR(INDEX('Base articles'!$H$2:$H$1153,MATCH(53,'Base articles'!$T$2:$T$1153,0)),"") | D59: =IFERROR(IF(INDEX('Base articles'!$G$2:$G$1153,MATCH(53,'Base articles'!$T$2:$T$1153,0))="","",INDEX('Base articles'!$G$2:$G$1153,MATCH(53,'Base articles'!$T$2:$T$1153,0))),"") | E59: =IFERROR(IF(INDEX('Base articles'!$K$2:$K$1153,MATCH(53,'Base articles'!$T$2:$T$1153,0))="","",INDEX('Base articles'!$K$2:$K$1153,MATCH(53,'Base articles'!$T$2:$T$1153,0))),"") | F59: =IFERROR(IF(INDEX('Base articles'!$M$2:$M$1153,MATCH(53,'Base articles'!$T$2:$T$1153,0))="","",INDEX('Base articles'!$M$2:$M$1153,MATCH(53,'Base articles'!$T$2:$T$1153,0))),"") | G59: =IFERROR(IF(INDEX('Base articles'!$N$2:$N$1153,MATCH(53,'Base articles'!$T$2:$T$1153,0))="","",INDEX('Base articles'!$N$2:$N$1153,MATCH(53,'Base articles'!$T$2:$T$1153,0))),"") | H59: =IFERROR(IF(INDEX('Base articles'!$P$2:$P$1153,MATCH(53,'Base articles'!$T$2:$T$1153,0))="","",INDEX('Base articles'!$P$2:$P$1153,MATCH(53,'Base articles'!$T$2:$T$1153,0))),"") | I59: =IFERROR(IF(INDEX('Base articles'!$Q$2:$Q$1153,MATCH(53,'Base articles'!$T$2:$T$1153,0))="","",INDEX('Base articles'!$Q$2:$Q$1153,MATCH(53,'Base articles'!$T$2:$T$1153,0))),"") | J59: =IFERROR(IF(INDEX('Base articles'!$B$2:$B$1153,MATCH(53,'Base articles'!$T$2:$T$1153,0))="","",INDEX('Base articles'!$B$2:$B$1153,MATCH(53,'Base articles'!$T$2:$T$1153,0))),"")
A60: =IFERROR(IF(INDEX('Base articles'!$D$2:$D$1153,MATCH(54,'Base articles'!$T$2:$T$1153,0))="","",INDEX('Base articles'!$D$2:$D$1153,MATCH(54,'Base articles'!$T$2:$T$1153,0))),"") | B60: =IFERROR(IF(INDEX('Base articles'!$F$2:$F$1153,MATCH(54,'Base articles'!$T$2:$T$1153,0))="","",INDEX('Base articles'!$F$2:$F$1153,MATCH(54,'Base articles'!$T$2:$T$1153,0))),"") | C60: =IFERROR(INDEX('Base articles'!$H$2:$H$1153,MATCH(54,'Base articles'!$T$2:$T$1153,0)),"") | D60: =IFERROR(IF(INDEX('Base articles'!$G$2:$G$1153,MATCH(54,'Base articles'!$T$2:$T$1153,0))="","",INDEX('Base articles'!$G$2:$G$1153,MATCH(54,'Base articles'!$T$2:$T$1153,0))),"") | E60: =IFERROR(IF(INDEX('Base articles'!$K$2:$K$1153,MATCH(54,'Base articles'!$T$2:$T$1153,0))="","",INDEX('Base articles'!$K$2:$K$1153,MATCH(54,'Base articles'!$T$2:$T$1153,0))),"") | F60: =IFERROR(IF(INDEX('Base articles'!$M$2:$M$1153,MATCH(54,'Base articles'!$T$2:$T$1153,0))="","",INDEX('Base articles'!$M$2:$M$1153,MATCH(54,'Base articles'!$T$2:$T$1153,0))),"") | G60: =IFERROR(IF(INDEX('Base articles'!$N$2:$N$1153,MATCH(54,'Base articles'!$T$2:$T$1153,0))="","",INDEX('Base articles'!$N$2:$N$1153,MATCH(54,'Base articles'!$T$2:$T$1153,0))),"") | H60: =IFERROR(IF(INDEX('Base articles'!$P$2:$P$1153,MATCH(54,'Base articles'!$T$2:$T$1153,0))="","",INDEX('Base articles'!$P$2:$P$1153,MATCH(54,'Base articles'!$T$2:$T$1153,0))),"") | I60: =IFERROR(IF(INDEX('Base articles'!$Q$2:$Q$1153,MATCH(54,'Base articles'!$T$2:$T$1153,0))="","",INDEX('Base articles'!$Q$2:$Q$1153,MATCH(54,'Base articles'!$T$2:$T$1153,0))),"") | J60: =IFERROR(IF(INDEX('Base articles'!$B$2:$B$1153,MATCH(54,'Base articles'!$T$2:$T$1153,0))="","",INDEX('Base articles'!$B$2:$B$1153,MATCH(54,'Base articles'!$T$2:$T$1153,0))),"")
A61: =IFERROR(IF(INDEX('Base articles'!$D$2:$D$1153,MATCH(55,'Base articles'!$T$2:$T$1153,0))="","",INDEX('Base articles'!$D$2:$D$1153,MATCH(55,'Base articles'!$T$2:$T$1153,0))),"") | B61: =IFERROR(IF(INDEX('Base articles'!$F$2:$F$1153,MATCH(55,'Base articles'!$T$2:$T$1153,0))="","",INDEX('Base articles'!$F$2:$F$1153,MATCH(55,'Base articles'!$T$2:$T$1153,0))),"") | C61: =IFERROR(INDEX('Base articles'!$H$2:$H$1153,MATCH(55,'Base articles'!$T$2:$T$1153,0)),"") | D61: =IFERROR(IF(INDEX('Base articles'!$G$2:$G$1153,MATCH(55,'Base articles'!$T$2:$T$1153,0))="","",INDEX('Base articles'!$G$2:$G$1153,MATCH(55,'Base articles'!$T$2:$T$1153,0))),"") | E61: =IFERROR(IF(INDEX('Base articles'!$K$2:$K$1153,MATCH(55,'Base articles'!$T$2:$T$1153,0))="","",INDEX('Base articles'!$K$2:$K$1153,MATCH(55,'Base articles'!$T$2:$T$1153,0))),"") | F61: =IFERROR(IF(INDEX('Base articles'!$M$2:$M$1153,MATCH(55,'Base articles'!$T$2:$T$1153,0))="","",INDEX('Base articles'!$M$2:$M$1153,MATCH(55,'Base articles'!$T$2:$T$1153,0))),"") | G61: =IFERROR(IF(INDEX('Base articles'!$N$2:$N$1153,MATCH(55,'Base articles'!$T$2:$T$1153,0))="","",INDEX('Base articles'!$N$2:$N$1153,MATCH(55,'Base articles'!$T$2:$T$1153,0))),"") | H61: =IFERROR(IF(INDEX('Base articles'!$P$2:$P$1153,MATCH(55,'Base articles'!$T$2:$T$1153,0))="","",INDEX('Base articles'!$P$2:$P$1153,MATCH(55,'Base articles'!$T$2:$T$1153,0))),"") | I61: =IFERROR(IF(INDEX('Base articles'!$Q$2:$Q$1153,MATCH(55,'Base articles'!$T$2:$T$1153,0))="","",INDEX('Base articles'!$Q$2:$Q$1153,MATCH(55,'Base articles'!$T$2:$T$1153,0))),"") | J61: =IFERROR(IF(INDEX('Base articles'!$B$2:$B$1153,MATCH(55,'Base articles'!$T$2:$T$1153,0))="","",INDEX('Base articles'!$B$2:$B$1153,MATCH(55,'Base articles'!$T$2:$T$1153,0))),"")
A62: =IFERROR(IF(INDEX('Base articles'!$D$2:$D$1153,MATCH(56,'Base articles'!$T$2:$T$1153,0))="","",INDEX('Base articles'!$D$2:$D$1153,MATCH(56,'Base articles'!$T$2:$T$1153,0))),"") | B62: =IFERROR(IF(INDEX('Base articles'!$F$2:$F$1153,MATCH(56,'Base articles'!$T$2:$T$1153,0))="","",INDEX('Base articles'!$F$2:$F$1153,MATCH(56,'Base articles'!$T$2:$T$1153,0))),"") | C62: =IFERROR(INDEX('Base articles'!$H$2:$H$1153,MATCH(56,'Base articles'!$T$2:$T$1153,0)),"") | D62: =IFERROR(IF(INDEX('Base articles'!$G$2:$G$1153,MATCH(56,'Base articles'!$T$2:$T$1153,0))="","",INDEX('Base articles'!$G$2:$G$1153,MATCH(56,'Base articles'!$T$2:$T$1153,0))),"") | E62: =IFERROR(IF(INDEX('Base articles'!$K$2:$K$1153,MATCH(56,'Base articles'!$T$2:$T$1153,0))="","",INDEX('Base articles'!$K$2:$K$1153,MATCH(56,'Base articles'!$T$2:$T$1153,0))),"") | F62: =IFERROR(IF(INDEX('Base articles'!$M$2:$M$1153,MATCH(56,'Base articles'!$T$2:$T$1153,0))="","",INDEX('Base articles'!$M$2:$M$1153,MATCH(56,'Base articles'!$T$2:$T$1153,0))),"") | G62: =IFERROR(IF(INDEX('Base articles'!$N$2:$N$1153,MATCH(56,'Base articles'!$T$2:$T$1153,0))="","",INDEX('Base articles'!$N$2:$N$1153,MATCH(56,'Base articles'!$T$2:$T$1153,0))),"") | H62: =IFERROR(IF(INDEX('Base articles'!$P$2:$P$1153,MATCH(56,'Base articles'!$T$2:$T$1153,0))="","",INDEX('Base articles'!$P$2:$P$1153,MATCH(56,'Base articles'!$T$2:$T$1153,0))),"") | I62: =IFERROR(IF(INDEX('Base articles'!$Q$2:$Q$1153,MATCH(56,'Base articles'!$T$2:$T$1153,0))="","",INDEX('Base articles'!$Q$2:$Q$1153,MATCH(56,'Base articles'!$T$2:$T$1153,0))),"") | J62: =IFERROR(IF(INDEX('Base articles'!$B$2:$B$1153,MATCH(56,'Base articles'!$T$2:$T$1153,0))="","",INDEX('Base articles'!$B$2:$B$1153,MATCH(56,'Base articles'!$T$2:$T$1153,0))),"")
A63: =IFERROR(IF(INDEX('Base articles'!$D$2:$D$1153,MATCH(57,'Base articles'!$T$2:$T$1153,0))="","",INDEX('Base articles'!$D$2:$D$1153,MATCH(57,'Base articles'!$T$2:$T$1153,0))),"") | B63: =IFERROR(IF(INDEX('Base articles'!$F$2:$F$1153,MATCH(57,'Base articles'!$T$2:$T$1153,0))="","",INDEX('Base articles'!$F$2:$F$1153,MATCH(57,'Base articles'!$T$2:$T$1153,0))),"") | C63: =IFERROR(INDEX('Base articles'!$H$2:$H$1153,MATCH(57,'Base articles'!$T$2:$T$1153,0)),"") | D63: =IFERROR(IF(INDEX('Base articles'!$G$2:$G$1153,MATCH(57,'Base articles'!$T$2:$T$1153,0))="","",INDEX('Base articles'!$G$2:$G$1153,MATCH(57,'Base articles'!$T$2:$T$1153,0))),"") | E63: =IFERROR(IF(INDEX('Base articles'!$K$2:$K$1153,MATCH(57,'Base articles'!$T$2:$T$1153,0))="","",INDEX('Base articles'!$K$2:$K$1153,MATCH(57,'Base articles'!$T$2:$T$1153,0))),"") | F63: =IFERROR(IF(INDEX('Base articles'!$M$2:$M$1153,MATCH(57,'Base articles'!$T$2:$T$1153,0))="","",INDEX('Base articles'!$M$2:$M$1153,MATCH(57,'Base articles'!$T$2:$T$1153,0))),"") | G63: =IFERROR(IF(INDEX('Base articles'!$N$2:$N$1153,MATCH(57,'Base articles'!$T$2:$T$1153,0))="","",INDEX('Base articles'!$N$2:$N$1153,MATCH(57,'Base articles'!$T$2:$T$1153,0))),"") | H63: =IFERROR(IF(INDEX('Base articles'!$P$2:$P$1153,MATCH(57,'Base articles'!$T$2:$T$1153,0))="","",INDEX('Base articles'!$P$2:$P$1153,MATCH(57,'Base articles'!$T$2:$T$1153,0))),"") | I63: =IFERROR(IF(INDEX('Base articles'!$Q$2:$Q$1153,MATCH(57,'Base articles'!$T$2:$T$1153,0))="","",INDEX('Base articles'!$Q$2:$Q$1153,MATCH(57,'Base articles'!$T$2:$T$1153,0))),"") | J63: =IFERROR(IF(INDEX('Base articles'!$B$2:$B$1153,MATCH(57,'Base articles'!$T$2:$T$1153,0))="","",INDEX('Base articles'!$B$2:$B$1153,MATCH(57,'Base articles'!$T$2:$T$1153,0))),"")
A64: =IFERROR(IF(INDEX('Base articles'!$D$2:$D$1153,MATCH(58,'Base articles'!$T$2:$T$1153,0))="","",INDEX('Base articles'!$D$2:$D$1153,MATCH(58,'Base articles'!$T$2:$T$1153,0))),"") | B64: =IFERROR(IF(INDEX('Base articles'!$F$2:$F$1153,MATCH(58,'Base articles'!$T$2:$T$1153,0))="","",INDEX('Base articles'!$F$2:$F$1153,MATCH(58,'Base articles'!$T$2:$T$1153,0))),"") | C64: =IFERROR(INDEX('Base articles'!$H$2:$H$1153,MATCH(58,'Base articles'!$T$2:$T$1153,0)),"") | D64: =IFERROR(IF(INDEX('Base articles'!$G$2:$G$1153,MATCH(58,'Base articles'!$T$2:$T$1153,0))="","",INDEX('Base articles'!$G$2:$G$1153,MATCH(58,'Base articles'!$T$2:$T$1153,0))),"") | E64: =IFERROR(IF(INDEX('Base articles'!$K$2:$K$1153,MATCH(58,'Base articles'!$T$2:$T$1153,0))="","",INDEX('Base articles'!$K$2:$K$1153,MATCH(58,'Base articles'!$T$2:$T$1153,0))),"") | F64: =IFERROR(IF(INDEX('Base articles'!$M$2:$M$1153,MATCH(58,'Base articles'!$T$2:$T$1153,0))="","",INDEX('Base articles'!$M$2:$M$1153,MATCH(58,'Base articles'!$T$2:$T$1153,0))),"") | G64: =IFERROR(IF(INDEX('Base articles'!$N$2:$N$1153,MATCH(58,'Base articles'!$T$2:$T$1153,0))="","",INDEX('Base articles'!$N$2:$N$1153,MATCH(58,'Base articles'!$T$2:$T$1153,0))),"") | H64: =IFERROR(IF(INDEX('Base articles'!$P$2:$P$1153,MATCH(58,'Base articles'!$T$2:$T$1153,0))="","",INDEX('Base articles'!$P$2:$P$1153,MATCH(58,'Base articles'!$T$2:$T$1153,0))),"") | I64: =IFERROR(IF(INDEX('Base articles'!$Q$2:$Q$1153,MATCH(58,'Base articles'!$T$2:$T$1153,0))="","",INDEX('Base articles'!$Q$2:$Q$1153,MATCH(58,'Base articles'!$T$2:$T$1153,0))),"") | J64: =IFERROR(IF(INDEX('Base articles'!$B$2:$B$1153,MATCH(58,'Base articles'!$T$2:$T$1153,0))="","",INDEX('Base articles'!$B$2:$B$1153,MATCH(58,'Base articles'!$T$2:$T$1153,0))),"")
A65: =IFERROR(IF(INDEX('Base articles'!$D$2:$D$1153,MATCH(59,'Base articles'!$T$2:$T$1153,0))="","",INDEX('Base articles'!$D$2:$D$1153,MATCH(59,'Base articles'!$T$2:$T$1153,0))),"") | B65: =IFERROR(IF(INDEX('Base articles'!$F$2:$F$1153,MATCH(59,'Base articles'!$T$2:$T$1153,0))="","",INDEX('Base articles'!$F$2:$F$1153,MATCH(59,'Base articles'!$T$2:$T$1153,0))),"") | C65: =IFERROR(INDEX('Base articles'!$H$2:$H$1153,MATCH(59,'Base articles'!$T$2:$T$1153,0)),"") | D65: =IFERROR(IF(INDEX('Base articles'!$G$2:$G$1153,MATCH(59,'Base articles'!$T$2:$T$1153,0))="","",INDEX('Base articles'!$G$2:$G$1153,MATCH(59,'Base articles'!$T$2:$T$1153,0))),"") | E65: =IFERROR(IF(INDEX('Base articles'!$K$2:$K$1153,MATCH(59,'Base articles'!$T$2:$T$1153,0))="","",INDEX('Base articles'!$K$2:$K$1153,MATCH(59,'Base articles'!$T$2:$T$1153,0))),"") | F65: =IFERROR(IF(INDEX('Base articles'!$M$2:$M$1153,MATCH(59,'Base articles'!$T$2:$T$1153,0))="","",INDEX('Base articles'!$M$2:$M$1153,MATCH(59,'Base articles'!$T$2:$T$1153,0))),"") | G65: =IFERROR(IF(INDEX('Base articles'!$N$2:$N$1153,MATCH(59,'Base articles'!$T$2:$T$1153,0))="","",INDEX('Base articles'!$N$2:$N$1153,MATCH(59,'Base articles'!$T$2:$T$1153,0))),"") | H65: =IFERROR(IF(INDEX('Base articles'!$P$2:$P$1153,MATCH(59,'Base articles'!$T$2:$T$1153,0))="","",INDEX('Base articles'!$P$2:$P$1153,MATCH(59,'Base articles'!$T$2:$T$1153,0))),"") | I65: =IFERROR(IF(INDEX('Base articles'!$Q$2:$Q$1153,MATCH(59,'Base articles'!$T$2:$T$1153,0))="","",INDEX('Base articles'!$Q$2:$Q$1153,MATCH(59,'Base articles'!$T$2:$T$1153,0))),"") | J65: =IFERROR(IF(INDEX('Base articles'!$B$2:$B$1153,MATCH(59,'Base articles'!$T$2:$T$1153,0))="","",INDEX('Base articles'!$B$2:$B$1153,MATCH(59,'Base articles'!$T$2:$T$1153,0))),"")
A66: =IFERROR(IF(INDEX('Base articles'!$D$2:$D$1153,MATCH(60,'Base articles'!$T$2:$T$1153,0))="","",INDEX('Base articles'!$D$2:$D$1153,MATCH(60,'Base articles'!$T$2:$T$1153,0))),"") | B66: =IFERROR(IF(INDEX('Base articles'!$F$2:$F$1153,MATCH(60,'Base articles'!$T$2:$T$1153,0))="","",INDEX('Base articles'!$F$2:$F$1153,MATCH(60,'Base articles'!$T$2:$T$1153,0))),"") | C66: =IFERROR(INDEX('Base articles'!$H$2:$H$1153,MATCH(60,'Base articles'!$T$2:$T$1153,0)),"") | D66: =IFERROR(IF(INDEX('Base articles'!$G$2:$G$1153,MATCH(60,'Base articles'!$T$2:$T$1153,0))="","",INDEX('Base articles'!$G$2:$G$1153,MATCH(60,'Base articles'!$T$2:$T$1153,0))),"") | E66: =IFERROR(IF(INDEX('Base articles'!$K$2:$K$1153,MATCH(60,'Base articles'!$T$2:$T$1153,0))="","",INDEX('Base articles'!$K$2:$K$1153,MATCH(60,'Base articles'!$T$2:$T$1153,0))),"") | F66: =IFERROR(IF(INDEX('Base articles'!$M$2:$M$1153,MATCH(60,'Base articles'!$T$2:$T$1153,0))="","",INDEX('Base articles'!$M$2:$M$1153,MATCH(60,'Base articles'!$T$2:$T$1153,0))),"") | G66: =IFERROR(IF(INDEX('Base articles'!$N$2:$N$1153,MATCH(60,'Base articles'!$T$2:$T$1153,0))="","",INDEX('Base articles'!$N$2:$N$1153,MATCH(60,'Base articles'!$T$2:$T$1153,0))),"") | H66: =IFERROR(IF(INDEX('Base articles'!$P$2:$P$1153,MATCH(60,'Base articles'!$T$2:$T$1153,0))="","",INDEX('Base articles'!$P$2:$P$1153,MATCH(60,'Base articles'!$T$2:$T$1153,0))),"") | I66: =IFERROR(IF(INDEX('Base articles'!$Q$2:$Q$1153,MATCH(60,'Base articles'!$T$2:$T$1153,0))="","",INDEX('Base articles'!$Q$2:$Q$1153,MATCH(60,'Base articles'!$T$2:$T$1153,0))),"") | J66: =IFERROR(IF(INDEX('Base articles'!$B$2:$B$1153,MATCH(60,'Base articles'!$T$2:$T$1153,0))="","",INDEX('Base articles'!$B$2:$B$1153,MATCH(60,'Base articles'!$T$2:$T$1153,0))),"")
A67: =IFERROR(IF(INDEX('Base articles'!$D$2:$D$1153,MATCH(61,'Base articles'!$T$2:$T$1153,0))="","",INDEX('Base articles'!$D$2:$D$1153,MATCH(61,'Base articles'!$T$2:$T$1153,0))),"") | B67: =IFERROR(IF(INDEX('Base articles'!$F$2:$F$1153,MATCH(61,'Base articles'!$T$2:$T$1153,0))="","",INDEX('Base articles'!$F$2:$F$1153,MATCH(61,'Base articles'!$T$2:$T$1153,0))),"") | C67: =IFERROR(INDEX('Base articles'!$H$2:$H$1153,MATCH(61,'Base articles'!$T$2:$T$1153,0)),"") | D67: =IFERROR(IF(INDEX('Base articles'!$G$2:$G$1153,MATCH(61,'Base articles'!$T$2:$T$1153,0))="","",INDEX('Base articles'!$G$2:$G$1153,MATCH(61,'Base articles'!$T$2:$T$1153,0))),"") | E67: =IFERROR(IF(INDEX('Base articles'!$K$2:$K$1153,MATCH(61,'Base articles'!$T$2:$T$1153,0))="","",INDEX('Base articles'!$K$2:$K$1153,MATCH(61,'Base articles'!$T$2:$T$1153,0))),"") | F67: =IFERROR(IF(INDEX('Base articles'!$M$2:$M$1153,MATCH(61,'Base articles'!$T$2:$T$1153,0))="","",INDEX('Base articles'!$M$2:$M$1153,MATCH(61,'Base articles'!$T$2:$T$1153,0))),"") | G67: =IFERROR(IF(INDEX('Base articles'!$N$2:$N$1153,MATCH(61,'Base articles'!$T$2:$T$1153,0))="","",INDEX('Base articles'!$N$2:$N$1153,MATCH(61,'Base articles'!$T$2:$T$1153,0))),"") | H67: =IFERROR(IF(INDEX('Base articles'!$P$2:$P$1153,MATCH(61,'Base articles'!$T$2:$T$1153,0))="","",INDEX('Base articles'!$P$2:$P$1153,MATCH(61,'Base articles'!$T$2:$T$1153,0))),"") | I67: =IFERROR(IF(INDEX('Base articles'!$Q$2:$Q$1153,MATCH(61,'Base articles'!$T$2:$T$1153,0))="","",INDEX('Base articles'!$Q$2:$Q$1153,MATCH(61,'Base articles'!$T$2:$T$1153,0))),"") | J67: =IFERROR(IF(INDEX('Base articles'!$B$2:$B$1153,MATCH(61,'Base articles'!$T$2:$T$1153,0))="","",INDEX('Base articles'!$B$2:$B$1153,MATCH(61,'Base articles'!$T$2:$T$1153,0))),"")
A68: =IFERROR(IF(INDEX('Base articles'!$D$2:$D$1153,MATCH(62,'Base articles'!$T$2:$T$1153,0))="","",INDEX('Base articles'!$D$2:$D$1153,MATCH(62,'Base articles'!$T$2:$T$1153,0))),"") | B68: =IFERROR(IF(INDEX('Base articles'!$F$2:$F$1153,MATCH(62,'Base articles'!$T$2:$T$1153,0))="","",INDEX('Base articles'!$F$2:$F$1153,MATCH(62,'Base articles'!$T$2:$T$1153,0))),"") | C68: =IFERROR(INDEX('Base articles'!$H$2:$H$1153,MATCH(62,'Base articles'!$T$2:$T$1153,0)),"") | D68: =IFERROR(IF(INDEX('Base articles'!$G$2:$G$1153,MATCH(62,'Base articles'!$T$2:$T$1153,0))="","",INDEX('Base articles'!$G$2:$G$1153,MATCH(62,'Base articles'!$T$2:$T$1153,0))),"") | E68: =IFERROR(IF(INDEX('Base articles'!$K$2:$K$1153,MATCH(62,'Base articles'!$T$2:$T$1153,0))="","",INDEX('Base articles'!$K$2:$K$1153,MATCH(62,'Base articles'!$T$2:$T$1153,0))),"") | F68: =IFERROR(IF(INDEX('Base articles'!$M$2:$M$1153,MATCH(62,'Base articles'!$T$2:$T$1153,0))="","",INDEX('Base articles'!$M$2:$M$1153,MATCH(62,'Base articles'!$T$2:$T$1153,0))),"") | G68: =IFERROR(IF(INDEX('Base articles'!$N$2:$N$1153,MATCH(62,'Base articles'!$T$2:$T$1153,0))="","",INDEX('Base articles'!$N$2:$N$1153,MATCH(62,'Base articles'!$T$2:$T$1153,0))),"") | H68: =IFERROR(IF(INDEX('Base articles'!$P$2:$P$1153,MATCH(62,'Base articles'!$T$2:$T$1153,0))="","",INDEX('Base articles'!$P$2:$P$1153,MATCH(62,'Base articles'!$T$2:$T$1153,0))),"") | I68: =IFERROR(IF(INDEX('Base articles'!$Q$2:$Q$1153,MATCH(62,'Base articles'!$T$2:$T$1153,0))="","",INDEX('Base articles'!$Q$2:$Q$1153,MATCH(62,'Base articles'!$T$2:$T$1153,0))),"") | J68: =IFERROR(IF(INDEX('Base articles'!$B$2:$B$1153,MATCH(62,'Base articles'!$T$2:$T$1153,0))="","",INDEX('Base articles'!$B$2:$B$1153,MATCH(62,'Base articles'!$T$2:$T$1153,0))),"")
A69: =IFERROR(IF(INDEX('Base articles'!$D$2:$D$1153,MATCH(63,'Base articles'!$T$2:$T$1153,0))="","",INDEX('Base articles'!$D$2:$D$1153,MATCH(63,'Base articles'!$T$2:$T$1153,0))),"") | B69: =IFERROR(IF(INDEX('Base articles'!$F$2:$F$1153,MATCH(63,'Base articles'!$T$2:$T$1153,0))="","",INDEX('Base articles'!$F$2:$F$1153,MATCH(63,'Base articles'!$T$2:$T$1153,0))),"") | C69: =IFERROR(INDEX('Base articles'!$H$2:$H$1153,MATCH(63,'Base articles'!$T$2:$T$1153,0)),"") | D69: =IFERROR(IF(INDEX('Base articles'!$G$2:$G$1153,MATCH(63,'Base articles'!$T$2:$T$1153,0))="","",INDEX('Base articles'!$G$2:$G$1153,MATCH(63,'Base articles'!$T$2:$T$1153,0))),"") | E69: =IFERROR(IF(INDEX('Base articles'!$K$2:$K$1153,MATCH(63,'Base articles'!$T$2:$T$1153,0))="","",INDEX('Base articles'!$K$2:$K$1153,MATCH(63,'Base articles'!$T$2:$T$1153,0))),"") | F69: =IFERROR(IF(INDEX('Base articles'!$M$2:$M$1153,MATCH(63,'Base articles'!$T$2:$T$1153,0))="","",INDEX('Base articles'!$M$2:$M$1153,MATCH(63,'Base articles'!$T$2:$T$1153,0))),"") | G69: =IFERROR(IF(INDEX('Base articles'!$N$2:$N$1153,MATCH(63,'Base articles'!$T$2:$T$1153,0))="","",INDEX('Base articles'!$N$2:$N$1153,MATCH(63,'Base articles'!$T$2:$T$1153,0))),"") | H69: =IFERROR(IF(INDEX('Base articles'!$P$2:$P$1153,MATCH(63,'Base articles'!$T$2:$T$1153,0))="","",INDEX('Base articles'!$P$2:$P$1153,MATCH(63,'Base articles'!$T$2:$T$1153,0))),"") | I69: =IFERROR(IF(INDEX('Base articles'!$Q$2:$Q$1153,MATCH(63,'Base articles'!$T$2:$T$1153,0))="","",INDEX('Base articles'!$Q$2:$Q$1153,MATCH(63,'Base articles'!$T$2:$T$1153,0))),"") | J69: =IFERROR(IF(INDEX('Base articles'!$B$2:$B$1153,MATCH(63,'Base articles'!$T$2:$T$1153,0))="","",INDEX('Base articles'!$B$2:$B$1153,MATCH(63,'Base articles'!$T$2:$T$1153,0))),"")
A70: =IFERROR(IF(INDEX('Base articles'!$D$2:$D$1153,MATCH(64,'Base articles'!$T$2:$T$1153,0))="","",INDEX('Base articles'!$D$2:$D$1153,MATCH(64,'Base articles'!$T$2:$T$1153,0))),"") | B70: =IFERROR(IF(INDEX('Base articles'!$F$2:$F$1153,MATCH(64,'Base articles'!$T$2:$T$1153,0))="","",INDEX('Base articles'!$F$2:$F$1153,MATCH(64,'Base articles'!$T$2:$T$1153,0))),"") | C70: =IFERROR(INDEX('Base articles'!$H$2:$H$1153,MATCH(64,'Base articles'!$T$2:$T$1153,0)),"") | D70: =IFERROR(IF(INDEX('Base articles'!$G$2:$G$1153,MATCH(64,'Base articles'!$T$2:$T$1153,0))="","",INDEX('Base articles'!$G$2:$G$1153,MATCH(64,'Base articles'!$T$2:$T$1153,0))),"") | E70: =IFERROR(IF(INDEX('Base articles'!$K$2:$K$1153,MATCH(64,'Base articles'!$T$2:$T$1153,0))="","",INDEX('Base articles'!$K$2:$K$1153,MATCH(64,'Base articles'!$T$2:$T$1153,0))),"") | F70: =IFERROR(IF(INDEX('Base articles'!$M$2:$M$1153,MATCH(64,'Base articles'!$T$2:$T$1153,0))="","",INDEX('Base articles'!$M$2:$M$1153,MATCH(64,'Base articles'!$T$2:$T$1153,0))),"") | G70: =IFERROR(IF(INDEX('Base articles'!$N$2:$N$1153,MATCH(64,'Base articles'!$T$2:$T$1153,0))="","",INDEX('Base articles'!$N$2:$N$1153,MATCH(64,'Base articles'!$T$2:$T$1153,0))),"") | H70: =IFERROR(IF(INDEX('Base articles'!$P$2:$P$1153,MATCH(64,'Base articles'!$T$2:$T$1153,0))="","",INDEX('Base articles'!$P$2:$P$1153,MATCH(64,'Base articles'!$T$2:$T$1153,0))),"") | I70: =IFERROR(IF(INDEX('Base articles'!$Q$2:$Q$1153,MATCH(64,'Base articles'!$T$2:$T$1153,0))="","",INDEX('Base articles'!$Q$2:$Q$1153,MATCH(64,'Base articles'!$T$2:$T$1153,0))),"") | J70: =IFERROR(IF(INDEX('Base articles'!$B$2:$B$1153,MATCH(64,'Base articles'!$T$2:$T$1153,0))="","",INDEX('Base articles'!$B$2:$B$1153,MATCH(64,'Base articles'!$T$2:$T$1153,0))),"")
A71: =IFERROR(IF(INDEX('Base articles'!$D$2:$D$1153,MATCH(65,'Base articles'!$T$2:$T$1153,0))="","",INDEX('Base articles'!$D$2:$D$1153,MATCH(65,'Base articles'!$T$2:$T$1153,0))),"") | B71: =IFERROR(IF(INDEX('Base articles'!$F$2:$F$1153,MATCH(65,'Base articles'!$T$2:$T$1153,0))="","",INDEX('Base articles'!$F$2:$F$1153,MATCH(65,'Base articles'!$T$2:$T$1153,0))),"") | C71: =IFERROR(INDEX('Base articles'!$H$2:$H$1153,MATCH(65,'Base articles'!$T$2:$T$1153,0)),"") | D71: =IFERROR(IF(INDEX('Base articles'!$G$2:$G$1153,MATCH(65,'Base articles'!$T$2:$T$1153,0))="","",INDEX('Base articles'!$G$2:$G$1153,MATCH(65,'Base articles'!$T$2:$T$1153,0))),"") | E71: =IFERROR(IF(INDEX('Base articles'!$K$2:$K$1153,MATCH(65,'Base articles'!$T$2:$T$1153,0))="","",INDEX('Base articles'!$K$2:$K$1153,MATCH(65,'Base articles'!$T$2:$T$1153,0))),"") | F71: =IFERROR(IF(INDEX('Base articles'!$M$2:$M$1153,MATCH(65,'Base articles'!$T$2:$T$1153,0))="","",INDEX('Base articles'!$M$2:$M$1153,MATCH(65,'Base articles'!$T$2:$T$1153,0))),"") | G71: =IFERROR(IF(INDEX('Base articles'!$N$2:$N$1153,MATCH(65,'Base articles'!$T$2:$T$1153,0))="","",INDEX('Base articles'!$N$2:$N$1153,MATCH(65,'Base articles'!$T$2:$T$1153,0))),"") | H71: =IFERROR(IF(INDEX('Base articles'!$P$2:$P$1153,MATCH(65,'Base articles'!$T$2:$T$1153,0))="","",INDEX('Base articles'!$P$2:$P$1153,MATCH(65,'Base articles'!$T$2:$T$1153,0))),"") | I71: =IFERROR(IF(INDEX('Base articles'!$Q$2:$Q$1153,MATCH(65,'Base articles'!$T$2:$T$1153,0))="","",INDEX('Base articles'!$Q$2:$Q$1153,MATCH(65,'Base articles'!$T$2:$T$1153,0))),"") | J71: =IFERROR(IF(INDEX('Base articles'!$B$2:$B$1153,MATCH(65,'Base articles'!$T$2:$T$1153,0))="","",INDEX('Base articles'!$B$2:$B$1153,MATCH(65,'Base articles'!$T$2:$T$1153,0))),"")
A72: =IFERROR(IF(INDEX('Base articles'!$D$2:$D$1153,MATCH(66,'Base articles'!$T$2:$T$1153,0))="","",INDEX('Base articles'!$D$2:$D$1153,MATCH(66,'Base articles'!$T$2:$T$1153,0))),"") | B72: =IFERROR(IF(INDEX('Base articles'!$F$2:$F$1153,MATCH(66,'Base articles'!$T$2:$T$1153,0))="","",INDEX('Base articles'!$F$2:$F$1153,MATCH(66,'Base articles'!$T$2:$T$1153,0))),"") | C72: =IFERROR(INDEX('Base articles'!$H$2:$H$1153,MATCH(66,'Base articles'!$T$2:$T$1153,0)),"") | D72: =IFERROR(IF(INDEX('Base articles'!$G$2:$G$1153,MATCH(66,'Base articles'!$T$2:$T$1153,0))="","",INDEX('Base articles'!$G$2:$G$1153,MATCH(66,'Base articles'!$T$2:$T$1153,0))),"") | E72: =IFERROR(IF(INDEX('Base articles'!$K$2:$K$1153,MATCH(66,'Base articles'!$T$2:$T$1153,0))="","",INDEX('Base articles'!$K$2:$K$1153,MATCH(66,'Base articles'!$T$2:$T$1153,0))),"") | F72: =IFERROR(IF(INDEX('Base articles'!$M$2:$M$1153,MATCH(66,'Base articles'!$T$2:$T$1153,0))="","",INDEX('Base articles'!$M$2:$M$1153,MATCH(66,'Base articles'!$T$2:$T$1153,0))),"") | G72: =IFERROR(IF(INDEX('Base articles'!$N$2:$N$1153,MATCH(66,'Base articles'!$T$2:$T$1153,0))="","",INDEX('Base articles'!$N$2:$N$1153,MATCH(66,'Base articles'!$T$2:$T$1153,0))),"") | H72: =IFERROR(IF(INDEX('Base articles'!$P$2:$P$1153,MATCH(66,'Base articles'!$T$2:$T$1153,0))="","",INDEX('Base articles'!$P$2:$P$1153,MATCH(66,'Base articles'!$T$2:$T$1153,0))),"") | I72: =IFERROR(IF(INDEX('Base articles'!$Q$2:$Q$1153,MATCH(66,'Base articles'!$T$2:$T$1153,0))="","",INDEX('Base articles'!$Q$2:$Q$1153,MATCH(66,'Base articles'!$T$2:$T$1153,0))),"") | J72: =IFERROR(IF(INDEX('Base articles'!$B$2:$B$1153,MATCH(66,'Base articles'!$T$2:$T$1153,0))="","",INDEX('Base articles'!$B$2:$B$1153,MATCH(66,'Base articles'!$T$2:$T$1153,0))),"")
A73: =IFERROR(IF(INDEX('Base articles'!$D$2:$D$1153,MATCH(67,'Base articles'!$T$2:$T$1153,0))="","",INDEX('Base articles'!$D$2:$D$1153,MATCH(67,'Base articles'!$T$2:$T$1153,0))),"") | B73: =IFERROR(IF(INDEX('Base articles'!$F$2:$F$1153,MATCH(67,'Base articles'!$T$2:$T$1153,0))="","",INDEX('Base articles'!$F$2:$F$1153,MATCH(67,'Base articles'!$T$2:$T$1153,0))),"") | C73: =IFERROR(INDEX('Base articles'!$H$2:$H$1153,MATCH(67,'Base articles'!$T$2:$T$1153,0)),"") | D73: =IFERROR(IF(INDEX('Base articles'!$G$2:$G$1153,MATCH(67,'Base articles'!$T$2:$T$1153,0))="","",INDEX('Base articles'!$G$2:$G$1153,MATCH(67,'Base articles'!$T$2:$T$1153,0))),"") | E73: =IFERROR(IF(INDEX('Base articles'!$K$2:$K$1153,MATCH(67,'Base articles'!$T$2:$T$1153,0))="","",INDEX('Base articles'!$K$2:$K$1153,MATCH(67,'Base articles'!$T$2:$T$1153,0))),"") | F73: =IFERROR(IF(INDEX('Base articles'!$M$2:$M$1153,MATCH(67,'Base articles'!$T$2:$T$1153,0))="","",INDEX('Base articles'!$M$2:$M$1153,MATCH(67,'Base articles'!$T$2:$T$1153,0))),"") | G73: =IFERROR(IF(INDEX('Base articles'!$N$2:$N$1153,MATCH(67,'Base articles'!$T$2:$T$1153,0))="","",INDEX('Base articles'!$N$2:$N$1153,MATCH(67,'Base articles'!$T$2:$T$1153,0))),"") | H73: =IFERROR(IF(INDEX('Base articles'!$P$2:$P$1153,MATCH(67,'Base articles'!$T$2:$T$1153,0))="","",INDEX('Base articles'!$P$2:$P$1153,MATCH(67,'Base articles'!$T$2:$T$1153,0))),"") | I73: =IFERROR(IF(INDEX('Base articles'!$Q$2:$Q$1153,MATCH(67,'Base articles'!$T$2:$T$1153,0))="","",INDEX('Base articles'!$Q$2:$Q$1153,MATCH(67,'Base articles'!$T$2:$T$1153,0))),"") | J73: =IFERROR(IF(INDEX('Base articles'!$B$2:$B$1153,MATCH(67,'Base articles'!$T$2:$T$1153,0))="","",INDEX('Base articles'!$B$2:$B$1153,MATCH(67,'Base articles'!$T$2:$T$1153,0))),"")
A74: =IFERROR(IF(INDEX('Base articles'!$D$2:$D$1153,MATCH(68,'Base articles'!$T$2:$T$1153,0))="","",INDEX('Base articles'!$D$2:$D$1153,MATCH(68,'Base articles'!$T$2:$T$1153,0))),"") | B74: =IFERROR(IF(INDEX('Base articles'!$F$2:$F$1153,MATCH(68,'Base articles'!$T$2:$T$1153,0))="","",INDEX('Base articles'!$F$2:$F$1153,MATCH(68,'Base articles'!$T$2:$T$1153,0))),"") | C74: =IFERROR(INDEX('Base articles'!$H$2:$H$1153,MATCH(68,'Base articles'!$T$2:$T$1153,0)),"") | D74: =IFERROR(IF(INDEX('Base articles'!$G$2:$G$1153,MATCH(68,'Base articles'!$T$2:$T$1153,0))="","",INDEX('Base articles'!$G$2:$G$1153,MATCH(68,'Base articles'!$T$2:$T$1153,0))),"") | E74: =IFERROR(IF(INDEX('Base articles'!$K$2:$K$1153,MATCH(68,'Base articles'!$T$2:$T$1153,0))="","",INDEX('Base articles'!$K$2:$K$1153,MATCH(68,'Base articles'!$T$2:$T$1153,0))),"") | F74: =IFERROR(IF(INDEX('Base articles'!$M$2:$M$1153,MATCH(68,'Base articles'!$T$2:$T$1153,0))="","",INDEX('Base articles'!$M$2:$M$1153,MATCH(68,'Base articles'!$T$2:$T$1153,0))),"") | G74: =IFERROR(IF(INDEX('Base articles'!$N$2:$N$1153,MATCH(68,'Base articles'!$T$2:$T$1153,0))="","",INDEX('Base articles'!$N$2:$N$1153,MATCH(68,'Base articles'!$T$2:$T$1153,0))),"") | H74: =IFERROR(IF(INDEX('Base articles'!$P$2:$P$1153,MATCH(68,'Base articles'!$T$2:$T$1153,0))="","",INDEX('Base articles'!$P$2:$P$1153,MATCH(68,'Base articles'!$T$2:$T$1153,0))),"") | I74: =IFERROR(IF(INDEX('Base articles'!$Q$2:$Q$1153,MATCH(68,'Base articles'!$T$2:$T$1153,0))="","",INDEX('Base articles'!$Q$2:$Q$1153,MATCH(68,'Base articles'!$T$2:$T$1153,0))),"") | J74: =IFERROR(IF(INDEX('Base articles'!$B$2:$B$1153,MATCH(68,'Base articles'!$T$2:$T$1153,0))="","",INDEX('Base articles'!$B$2:$B$1153,MATCH(68,'Base articles'!$T$2:$T$1153,0))),"")
A75: =IFERROR(IF(INDEX('Base articles'!$D$2:$D$1153,MATCH(69,'Base articles'!$T$2:$T$1153,0))="","",INDEX('Base articles'!$D$2:$D$1153,MATCH(69,'Base articles'!$T$2:$T$1153,0))),"") | B75: =IFERROR(IF(INDEX('Base articles'!$F$2:$F$1153,MATCH(69,'Base articles'!$T$2:$T$1153,0))="","",INDEX('Base articles'!$F$2:$F$1153,MATCH(69,'Base articles'!$T$2:$T$1153,0))),"") | C75: =IFERROR(INDEX('Base articles'!$H$2:$H$1153,MATCH(69,'Base articles'!$T$2:$T$1153,0)),"") | D75: =IFERROR(IF(INDEX('Base articles'!$G$2:$G$1153,MATCH(69,'Base articles'!$T$2:$T$1153,0))="","",INDEX('Base articles'!$G$2:$G$1153,MATCH(69,'Base articles'!$T$2:$T$1153,0))),"") | E75: =IFERROR(IF(INDEX('Base articles'!$K$2:$K$1153,MATCH(69,'Base articles'!$T$2:$T$1153,0))="","",INDEX('Base articles'!$K$2:$K$1153,MATCH(69,'Base articles'!$T$2:$T$1153,0))),"") | F75: =IFERROR(IF(INDEX('Base articles'!$M$2:$M$1153,MATCH(69,'Base articles'!$T$2:$T$1153,0))="","",INDEX('Base articles'!$M$2:$M$1153,MATCH(69,'Base articles'!$T$2:$T$1153,0))),"") | G75: =IFERROR(IF(INDEX('Base articles'!$N$2:$N$1153,MATCH(69,'Base articles'!$T$2:$T$1153,0))="","",INDEX('Base articles'!$N$2:$N$1153,MATCH(69,'Base articles'!$T$2:$T$1153,0))),"") | H75: =IFERROR(IF(INDEX('Base articles'!$P$2:$P$1153,MATCH(69,'Base articles'!$T$2:$T$1153,0))="","",INDEX('Base articles'!$P$2:$P$1153,MATCH(69,'Base articles'!$T$2:$T$1153,0))),"") | I75: =IFERROR(IF(INDEX('Base articles'!$Q$2:$Q$1153,MATCH(69,'Base articles'!$T$2:$T$1153,0))="","",INDEX('Base articles'!$Q$2:$Q$1153,MATCH(69,'Base articles'!$T$2:$T$1153,0))),"") | J75: =IFERROR(IF(INDEX('Base articles'!$B$2:$B$1153,MATCH(69,'Base articles'!$T$2:$T$1153,0))="","",INDEX('Base articles'!$B$2:$B$1153,MATCH(69,'Base articles'!$T$2:$T$1153,0))),"")
A76: =IFERROR(IF(INDEX('Base articles'!$D$2:$D$1153,MATCH(70,'Base articles'!$T$2:$T$1153,0))="","",INDEX('Base articles'!$D$2:$D$1153,MATCH(70,'Base articles'!$T$2:$T$1153,0))),"") | B76: =IFERROR(IF(INDEX('Base articles'!$F$2:$F$1153,MATCH(70,'Base articles'!$T$2:$T$1153,0))="","",INDEX('Base articles'!$F$2:$F$1153,MATCH(70,'Base articles'!$T$2:$T$1153,0))),"") | C76: =IFERROR(INDEX('Base articles'!$H$2:$H$1153,MATCH(70,'Base articles'!$T$2:$T$1153,0)),"") | D76: =IFERROR(IF(INDEX('Base articles'!$G$2:$G$1153,MATCH(70,'Base articles'!$T$2:$T$1153,0))="","",INDEX('Base articles'!$G$2:$G$1153,MATCH(70,'Base articles'!$T$2:$T$1153,0))),"") | E76: =IFERROR(IF(INDEX('Base articles'!$K$2:$K$1153,MATCH(70,'Base articles'!$T$2:$T$1153,0))="","",INDEX('Base articles'!$K$2:$K$1153,MATCH(70,'Base articles'!$T$2:$T$1153,0))),"") | F76: =IFERROR(IF(INDEX('Base articles'!$M$2:$M$1153,MATCH(70,'Base articles'!$T$2:$T$1153,0))="","",INDEX('Base articles'!$M$2:$M$1153,MATCH(70,'Base articles'!$T$2:$T$1153,0))),"") | G76: =IFERROR(IF(INDEX('Base articles'!$N$2:$N$1153,MATCH(70,'Base articles'!$T$2:$T$1153,0))="","",INDEX('Base articles'!$N$2:$N$1153,MATCH(70,'Base articles'!$T$2:$T$1153,0))),"") | H76: =IFERROR(IF(INDEX('Base articles'!$P$2:$P$1153,MATCH(70,'Base articles'!$T$2:$T$1153,0))="","",INDEX('Base articles'!$P$2:$P$1153,MATCH(70,'Base articles'!$T$2:$T$1153,0))),"") | I76: =IFERROR(IF(INDEX('Base articles'!$Q$2:$Q$1153,MATCH(70,'Base articles'!$T$2:$T$1153,0))="","",INDEX('Base articles'!$Q$2:$Q$1153,MATCH(70,'Base articles'!$T$2:$T$1153,0))),"") | J76: =IFERROR(IF(INDEX('Base articles'!$B$2:$B$1153,MATCH(70,'Base articles'!$T$2:$T$1153,0))="","",INDEX('Base articles'!$B$2:$B$1153,MATCH(70,'Base articles'!$T$2:$T$1153,0))),"")
A77: =IFERROR(IF(INDEX('Base articles'!$D$2:$D$1153,MATCH(71,'Base articles'!$T$2:$T$1153,0))="","",INDEX('Base articles'!$D$2:$D$1153,MATCH(71,'Base articles'!$T$2:$T$1153,0))),"") | B77: =IFERROR(IF(INDEX('Base articles'!$F$2:$F$1153,MATCH(71,'Base articles'!$T$2:$T$1153,0))="","",INDEX('Base articles'!$F$2:$F$1153,MATCH(71,'Base articles'!$T$2:$T$1153,0))),"") | C77: =IFERROR(INDEX('Base articles'!$H$2:$H$1153,MATCH(71,'Base articles'!$T$2:$T$1153,0)),"") | D77: =IFERROR(IF(INDEX('Base articles'!$G$2:$G$1153,MATCH(71,'Base articles'!$T$2:$T$1153,0))="","",INDEX('Base articles'!$G$2:$G$1153,MATCH(71,'Base articles'!$T$2:$T$1153,0))),"") | E77: =IFERROR(IF(INDEX('Base articles'!$K$2:$K$1153,MATCH(71,'Base articles'!$T$2:$T$1153,0))="","",INDEX('Base articles'!$K$2:$K$1153,MATCH(71,'Base articles'!$T$2:$T$1153,0))),"") | F77: =IFERROR(IF(INDEX('Base articles'!$M$2:$M$1153,MATCH(71,'Base articles'!$T$2:$T$1153,0))="","",INDEX('Base articles'!$M$2:$M$1153,MATCH(71,'Base articles'!$T$2:$T$1153,0))),"") | G77: =IFERROR(IF(INDEX('Base articles'!$N$2:$N$1153,MATCH(71,'Base articles'!$T$2:$T$1153,0))="","",INDEX('Base articles'!$N$2:$N$1153,MATCH(71,'Base articles'!$T$2:$T$1153,0))),"") | H77: =IFERROR(IF(INDEX('Base articles'!$P$2:$P$1153,MATCH(71,'Base articles'!$T$2:$T$1153,0))="","",INDEX('Base articles'!$P$2:$P$1153,MATCH(71,'Base articles'!$T$2:$T$1153,0))),"") | I77: =IFERROR(IF(INDEX('Base articles'!$Q$2:$Q$1153,MATCH(71,'Base articles'!$T$2:$T$1153,0))="","",INDEX('Base articles'!$Q$2:$Q$1153,MATCH(71,'Base articles'!$T$2:$T$1153,0))),"") | J77: =IFERROR(IF(INDEX('Base articles'!$B$2:$B$1153,MATCH(71,'Base articles'!$T$2:$T$1153,0))="","",INDEX('Base articles'!$B$2:$B$1153,MATCH(71,'Base articles'!$T$2:$T$1153,0))),"")
A78: =IFERROR(IF(INDEX('Base articles'!$D$2:$D$1153,MATCH(72,'Base articles'!$T$2:$T$1153,0))="","",INDEX('Base articles'!$D$2:$D$1153,MATCH(72,'Base articles'!$T$2:$T$1153,0))),"") | B78: =IFERROR(IF(INDEX('Base articles'!$F$2:$F$1153,MATCH(72,'Base articles'!$T$2:$T$1153,0))="","",INDEX('Base articles'!$F$2:$F$1153,MATCH(72,'Base articles'!$T$2:$T$1153,0))),"") | C78: =IFERROR(INDEX('Base articles'!$H$2:$H$1153,MATCH(72,'Base articles'!$T$2:$T$1153,0)),"") | D78: =IFERROR(IF(INDEX('Base articles'!$G$2:$G$1153,MATCH(72,'Base articles'!$T$2:$T$1153,0))="","",INDEX('Base articles'!$G$2:$G$1153,MATCH(72,'Base articles'!$T$2:$T$1153,0))),"") | E78: =IFERROR(IF(INDEX('Base articles'!$K$2:$K$1153,MATCH(72,'Base articles'!$T$2:$T$1153,0))="","",INDEX('Base articles'!$K$2:$K$1153,MATCH(72,'Base articles'!$T$2:$T$1153,0))),"") | F78: =IFERROR(IF(INDEX('Base articles'!$M$2:$M$1153,MATCH(72,'Base articles'!$T$2:$T$1153,0))="","",INDEX('Base articles'!$M$2:$M$1153,MATCH(72,'Base articles'!$T$2:$T$1153,0))),"") | G78: =IFERROR(IF(INDEX('Base articles'!$N$2:$N$1153,MATCH(72,'Base articles'!$T$2:$T$1153,0))="","",INDEX('Base articles'!$N$2:$N$1153,MATCH(72,'Base articles'!$T$2:$T$1153,0))),"") | H78: =IFERROR(IF(INDEX('Base articles'!$P$2:$P$1153,MATCH(72,'Base articles'!$T$2:$T$1153,0))="","",INDEX('Base articles'!$P$2:$P$1153,MATCH(72,'Base articles'!$T$2:$T$1153,0))),"") | I78: =IFERROR(IF(INDEX('Base articles'!$Q$2:$Q$1153,MATCH(72,'Base articles'!$T$2:$T$1153,0))="","",INDEX('Base articles'!$Q$2:$Q$1153,MATCH(72,'Base articles'!$T$2:$T$1153,0))),"") | J78: =IFERROR(IF(INDEX('Base articles'!$B$2:$B$1153,MATCH(72,'Base articles'!$T$2:$T$1153,0))="","",INDEX('Base articles'!$B$2:$B$1153,MATCH(72,'Base articles'!$T$2:$T$1153,0))),"")
A79: =IFERROR(IF(INDEX('Base articles'!$D$2:$D$1153,MATCH(73,'Base articles'!$T$2:$T$1153,0))="","",INDEX('Base articles'!$D$2:$D$1153,MATCH(73,'Base articles'!$T$2:$T$1153,0))),"") | B79: =IFERROR(IF(INDEX('Base articles'!$F$2:$F$1153,MATCH(73,'Base articles'!$T$2:$T$1153,0))="","",INDEX('Base articles'!$F$2:$F$1153,MATCH(73,'Base articles'!$T$2:$T$1153,0))),"") | C79: =IFERROR(INDEX('Base articles'!$H$2:$H$1153,MATCH(73,'Base articles'!$T$2:$T$1153,0)),"") | D79: =IFERROR(IF(INDEX('Base articles'!$G$2:$G$1153,MATCH(73,'Base articles'!$T$2:$T$1153,0))="","",INDEX('Base articles'!$G$2:$G$1153,MATCH(73,'Base articles'!$T$2:$T$1153,0))),"") | E79: =IFERROR(IF(INDEX('Base articles'!$K$2:$K$1153,MATCH(73,'Base articles'!$T$2:$T$1153,0))="","",INDEX('Base articles'!$K$2:$K$1153,MATCH(73,'Base articles'!$T$2:$T$1153,0))),"") | F79: =IFERROR(IF(INDEX('Base articles'!$M$2:$M$1153,MATCH(73,'Base articles'!$T$2:$T$1153,0))="","",INDEX('Base articles'!$M$2:$M$1153,MATCH(73,'Base articles'!$T$2:$T$1153,0))),"") | G79: =IFERROR(IF(INDEX('Base articles'!$N$2:$N$1153,MATCH(73,'Base articles'!$T$2:$T$1153,0))="","",INDEX('Base articles'!$N$2:$N$1153,MATCH(73,'Base articles'!$T$2:$T$1153,0))),"") | H79: =IFERROR(IF(INDEX('Base articles'!$P$2:$P$1153,MATCH(73,'Base articles'!$T$2:$T$1153,0))="","",INDEX('Base articles'!$P$2:$P$1153,MATCH(73,'Base articles'!$T$2:$T$1153,0))),"") | I79: =IFERROR(IF(INDEX('Base articles'!$Q$2:$Q$1153,MATCH(73,'Base articles'!$T$2:$T$1153,0))="","",INDEX('Base articles'!$Q$2:$Q$1153,MATCH(73,'Base articles'!$T$2:$T$1153,0))),"") | J79: =IFERROR(IF(INDEX('Base articles'!$B$2:$B$1153,MATCH(73,'Base articles'!$T$2:$T$1153,0))="","",INDEX('Base articles'!$B$2:$B$1153,MATCH(73,'Base articles'!$T$2:$T$1153,0))),"")
A80: =IFERROR(IF(INDEX('Base articles'!$D$2:$D$1153,MATCH(74,'Base articles'!$T$2:$T$1153,0))="","",INDEX('Base articles'!$D$2:$D$1153,MATCH(74,'Base articles'!$T$2:$T$1153,0))),"") | B80: =IFERROR(IF(INDEX('Base articles'!$F$2:$F$1153,MATCH(74,'Base articles'!$T$2:$T$1153,0))="","",INDEX('Base articles'!$F$2:$F$1153,MATCH(74,'Base articles'!$T$2:$T$1153,0))),"") | C80: =IFERROR(INDEX('Base articles'!$H$2:$H$1153,MATCH(74,'Base articles'!$T$2:$T$1153,0)),"") | D80: =IFERROR(IF(INDEX('Base articles'!$G$2:$G$1153,MATCH(74,'Base articles'!$T$2:$T$1153,0))="","",INDEX('Base articles'!$G$2:$G$1153,MATCH(74,'Base articles'!$T$2:$T$1153,0))),"") | E80: =IFERROR(IF(INDEX('Base articles'!$K$2:$K$1153,MATCH(74,'Base articles'!$T$2:$T$1153,0))="","",INDEX('Base articles'!$K$2:$K$1153,MATCH(74,'Base articles'!$T$2:$T$1153,0))),"") | F80: =IFERROR(IF(INDEX('Base articles'!$M$2:$M$1153,MATCH(74,'Base articles'!$T$2:$T$1153,0))="","",INDEX('Base articles'!$M$2:$M$1153,MATCH(74,'Base articles'!$T$2:$T$1153,0))),"") | G80: =IFERROR(IF(INDEX('Base articles'!$N$2:$N$1153,MATCH(74,'Base articles'!$T$2:$T$1153,0))="","",INDEX('Base articles'!$N$2:$N$1153,MATCH(74,'Base articles'!$T$2:$T$1153,0))),"") | H80: =IFERROR(IF(INDEX('Base articles'!$P$2:$P$1153,MATCH(74,'Base articles'!$T$2:$T$1153,0))="","",INDEX('Base articles'!$P$2:$P$1153,MATCH(74,'Base articles'!$T$2:$T$1153,0))),"") | I80: =IFERROR(IF(INDEX('Base articles'!$Q$2:$Q$1153,MATCH(74,'Base articles'!$T$2:$T$1153,0))="","",INDEX('Base articles'!$Q$2:$Q$1153,MATCH(74,'Base articles'!$T$2:$T$1153,0))),"") | J80: =IFERROR(IF(INDEX('Base articles'!$B$2:$B$1153,MATCH(74,'Base articles'!$T$2:$T$1153,0))="","",INDEX('Base articles'!$B$2:$B$1153,MATCH(74,'Base articles'!$T$2:$T$1153,0))),"")
A81: =IFERROR(IF(INDEX('Base articles'!$D$2:$D$1153,MATCH(75,'Base articles'!$T$2:$T$1153,0))="","",INDEX('Base articles'!$D$2:$D$1153,MATCH(75,'Base articles'!$T$2:$T$1153,0))),"") | B81: =IFERROR(IF(INDEX('Base articles'!$F$2:$F$1153,MATCH(75,'Base articles'!$T$2:$T$1153,0))="","",INDEX('Base articles'!$F$2:$F$1153,MATCH(75,'Base articles'!$T$2:$T$1153,0))),"") | C81: =IFERROR(INDEX('Base articles'!$H$2:$H$1153,MATCH(75,'Base articles'!$T$2:$T$1153,0)),"") | D81: =IFERROR(IF(INDEX('Base articles'!$G$2:$G$1153,MATCH(75,'Base articles'!$T$2:$T$1153,0))="","",INDEX('Base articles'!$G$2:$G$1153,MATCH(75,'Base articles'!$T$2:$T$1153,0))),"") | E81: =IFERROR(IF(INDEX('Base articles'!$K$2:$K$1153,MATCH(75,'Base articles'!$T$2:$T$1153,0))="","",INDEX('Base articles'!$K$2:$K$1153,MATCH(75,'Base articles'!$T$2:$T$1153,0))),"") | F81: =IFERROR(IF(INDEX('Base articles'!$M$2:$M$1153,MATCH(75,'Base articles'!$T$2:$T$1153,0))="","",INDEX('Base articles'!$M$2:$M$1153,MATCH(75,'Base articles'!$T$2:$T$1153,0))),"") | G81: =IFERROR(IF(INDEX('Base articles'!$N$2:$N$1153,MATCH(75,'Base articles'!$T$2:$T$1153,0))="","",INDEX('Base articles'!$N$2:$N$1153,MATCH(75,'Base articles'!$T$2:$T$1153,0))),"") | H81: =IFERROR(IF(INDEX('Base articles'!$P$2:$P$1153,MATCH(75,'Base articles'!$T$2:$T$1153,0))="","",INDEX('Base articles'!$P$2:$P$1153,MATCH(75,'Base articles'!$T$2:$T$1153,0))),"") | I81: =IFERROR(IF(INDEX('Base articles'!$Q$2:$Q$1153,MATCH(75,'Base articles'!$T$2:$T$1153,0))="","",INDEX('Base articles'!$Q$2:$Q$1153,MATCH(75,'Base articles'!$T$2:$T$1153,0))),"") | J81: =IFERROR(IF(INDEX('Base articles'!$B$2:$B$1153,MATCH(75,'Base articles'!$T$2:$T$1153,0))="","",INDEX('Base articles'!$B$2:$B$1153,MATCH(75,'Base articles'!$T$2:$T$1153,0))),"")
A82: =IFERROR(IF(INDEX('Base articles'!$D$2:$D$1153,MATCH(76,'Base articles'!$T$2:$T$1153,0))="","",INDEX('Base articles'!$D$2:$D$1153,MATCH(76,'Base articles'!$T$2:$T$1153,0))),"") | B82: =IFERROR(IF(INDEX('Base articles'!$F$2:$F$1153,MATCH(76,'Base articles'!$T$2:$T$1153,0))="","",INDEX('Base articles'!$F$2:$F$1153,MATCH(76,'Base articles'!$T$2:$T$1153,0))),"") | C82: =IFERROR(INDEX('Base articles'!$H$2:$H$1153,MATCH(76,'Base articles'!$T$2:$T$1153,0)),"") | D82: =IFERROR(IF(INDEX('Base articles'!$G$2:$G$1153,MATCH(76,'Base articles'!$T$2:$T$1153,0))="","",INDEX('Base articles'!$G$2:$G$1153,MATCH(76,'Base articles'!$T$2:$T$1153,0))),"") | E82: =IFERROR(IF(INDEX('Base articles'!$K$2:$K$1153,MATCH(76,'Base articles'!$T$2:$T$1153,0))="","",INDEX('Base articles'!$K$2:$K$1153,MATCH(76,'Base articles'!$T$2:$T$1153,0))),"") | F82: =IFERROR(IF(INDEX('Base articles'!$M$2:$M$1153,MATCH(76,'Base articles'!$T$2:$T$1153,0))="","",INDEX('Base articles'!$M$2:$M$1153,MATCH(76,'Base articles'!$T$2:$T$1153,0))),"") | G82: =IFERROR(IF(INDEX('Base articles'!$N$2:$N$1153,MATCH(76,'Base articles'!$T$2:$T$1153,0))="","",INDEX('Base articles'!$N$2:$N$1153,MATCH(76,'Base articles'!$T$2:$T$1153,0))),"") | H82: =IFERROR(IF(INDEX('Base articles'!$P$2:$P$1153,MATCH(76,'Base articles'!$T$2:$T$1153,0))="","",INDEX('Base articles'!$P$2:$P$1153,MATCH(76,'Base articles'!$T$2:$T$1153,0))),"") | I82: =IFERROR(IF(INDEX('Base articles'!$Q$2:$Q$1153,MATCH(76,'Base articles'!$T$2:$T$1153,0))="","",INDEX('Base articles'!$Q$2:$Q$1153,MATCH(76,'Base articles'!$T$2:$T$1153,0))),"") | J82: =IFERROR(IF(INDEX('Base articles'!$B$2:$B$1153,MATCH(76,'Base articles'!$T$2:$T$1153,0))="","",INDEX('Base articles'!$B$2:$B$1153,MATCH(76,'Base articles'!$T$2:$T$1153,0))),"")
A83: =IFERROR(IF(INDEX('Base articles'!$D$2:$D$1153,MATCH(77,'Base articles'!$T$2:$T$1153,0))="","",INDEX('Base articles'!$D$2:$D$1153,MATCH(77,'Base articles'!$T$2:$T$1153,0))),"") | B83: =IFERROR(IF(INDEX('Base articles'!$F$2:$F$1153,MATCH(77,'Base articles'!$T$2:$T$1153,0))="","",INDEX('Base articles'!$F$2:$F$1153,MATCH(77,'Base articles'!$T$2:$T$1153,0))),"") | C83: =IFERROR(INDEX('Base articles'!$H$2:$H$1153,MATCH(77,'Base articles'!$T$2:$T$1153,0)),"") | D83: =IFERROR(IF(INDEX('Base articles'!$G$2:$G$1153,MATCH(77,'Base articles'!$T$2:$T$1153,0))="","",INDEX('Base articles'!$G$2:$G$1153,MATCH(77,'Base articles'!$T$2:$T$1153,0))),"") | E83: =IFERROR(IF(INDEX('Base articles'!$K$2:$K$1153,MATCH(77,'Base articles'!$T$2:$T$1153,0))="","",INDEX('Base articles'!$K$2:$K$1153,MATCH(77,'Base articles'!$T$2:$T$1153,0))),"") | F83: =IFERROR(IF(INDEX('Base articles'!$M$2:$M$1153,MATCH(77,'Base articles'!$T$2:$T$1153,0))="","",INDEX('Base articles'!$M$2:$M$1153,MATCH(77,'Base articles'!$T$2:$T$1153,0))),"") | G83: =IFERROR(IF(INDEX('Base articles'!$N$2:$N$1153,MATCH(77,'Base articles'!$T$2:$T$1153,0))="","",INDEX('Base articles'!$N$2:$N$1153,MATCH(77,'Base articles'!$T$2:$T$1153,0))),"") | H83: =IFERROR(IF(INDEX('Base articles'!$P$2:$P$1153,MATCH(77,'Base articles'!$T$2:$T$1153,0))="","",INDEX('Base articles'!$P$2:$P$1153,MATCH(77,'Base articles'!$T$2:$T$1153,0))),"") | I83: =IFERROR(IF(INDEX('Base articles'!$Q$2:$Q$1153,MATCH(77,'Base articles'!$T$2:$T$1153,0))="","",INDEX('Base articles'!$Q$2:$Q$1153,MATCH(77,'Base articles'!$T$2:$T$1153,0))),"") | J83: =IFERROR(IF(INDEX('Base articles'!$B$2:$B$1153,MATCH(77,'Base articles'!$T$2:$T$1153,0))="","",INDEX('Base articles'!$B$2:$B$1153,MATCH(77,'Base articles'!$T$2:$T$1153,0))),"")
A84: =IFERROR(IF(INDEX('Base articles'!$D$2:$D$1153,MATCH(78,'Base articles'!$T$2:$T$1153,0))="","",INDEX('Base articles'!$D$2:$D$1153,MATCH(78,'Base articles'!$T$2:$T$1153,0))),"") | B84: =IFERROR(IF(INDEX('Base articles'!$F$2:$F$1153,MATCH(78,'Base articles'!$T$2:$T$1153,0))="","",INDEX('Base articles'!$F$2:$F$1153,MATCH(78,'Base articles'!$T$2:$T$1153,0))),"") | C84: =IFERROR(INDEX('Base articles'!$H$2:$H$1153,MATCH(78,'Base articles'!$T$2:$T$1153,0)),"") | D84: =IFERROR(IF(INDEX('Base articles'!$G$2:$G$1153,MATCH(78,'Base articles'!$T$2:$T$1153,0))="","",INDEX('Base articles'!$G$2:$G$1153,MATCH(78,'Base articles'!$T$2:$T$1153,0))),"") | E84: =IFERROR(IF(INDEX('Base articles'!$K$2:$K$1153,MATCH(78,'Base articles'!$T$2:$T$1153,0))="","",INDEX('Base articles'!$K$2:$K$1153,MATCH(78,'Base articles'!$T$2:$T$1153,0))),"") | F84: =IFERROR(IF(INDEX('Base articles'!$M$2:$M$1153,MATCH(78,'Base articles'!$T$2:$T$1153,0))="","",INDEX('Base articles'!$M$2:$M$1153,MATCH(78,'Base articles'!$T$2:$T$1153,0))),"") | G84: =IFERROR(IF(INDEX('Base articles'!$N$2:$N$1153,MATCH(78,'Base articles'!$T$2:$T$1153,0))="","",INDEX('Base articles'!$N$2:$N$1153,MATCH(78,'Base articles'!$T$2:$T$1153,0))),"") | H84: =IFERROR(IF(INDEX('Base articles'!$P$2:$P$1153,MATCH(78,'Base articles'!$T$2:$T$1153,0))="","",INDEX('Base articles'!$P$2:$P$1153,MATCH(78,'Base articles'!$T$2:$T$1153,0))),"") | I84: =IFERROR(IF(INDEX('Base articles'!$Q$2:$Q$1153,MATCH(78,'Base articles'!$T$2:$T$1153,0))="","",INDEX('Base articles'!$Q$2:$Q$1153,MATCH(78,'Base articles'!$T$2:$T$1153,0))),"") | J84: =IFERROR(IF(INDEX('Base articles'!$B$2:$B$1153,MATCH(78,'Base articles'!$T$2:$T$1153,0))="","",INDEX('Base articles'!$B$2:$B$1153,MATCH(78,'Base articles'!$T$2:$T$1153,0))),"")
A85: =IFERROR(IF(INDEX('Base articles'!$D$2:$D$1153,MATCH(79,'Base articles'!$T$2:$T$1153,0))="","",INDEX('Base articles'!$D$2:$D$1153,MATCH(79,'Base articles'!$T$2:$T$1153,0))),"") | B85: =IFERROR(IF(INDEX('Base articles'!$F$2:$F$1153,MATCH(79,'Base articles'!$T$2:$T$1153,0))="","",INDEX('Base articles'!$F$2:$F$1153,MATCH(79,'Base articles'!$T$2:$T$1153,0))),"") | C85: =IFERROR(INDEX('Base articles'!$H$2:$H$1153,MATCH(79,'Base articles'!$T$2:$T$1153,0)),"") | D85: =IFERROR(IF(INDEX('Base articles'!$G$2:$G$1153,MATCH(79,'Base articles'!$T$2:$T$1153,0))="","",INDEX('Base articles'!$G$2:$G$1153,MATCH(79,'Base articles'!$T$2:$T$1153,0))),"") | E85: =IFERROR(IF(INDEX('Base articles'!$K$2:$K$1153,MATCH(79,'Base articles'!$T$2:$T$1153,0))="","",INDEX('Base articles'!$K$2:$K$1153,MATCH(79,'Base articles'!$T$2:$T$1153,0))),"") | F85: =IFERROR(IF(INDEX('Base articles'!$M$2:$M$1153,MATCH(79,'Base articles'!$T$2:$T$1153,0))="","",INDEX('Base articles'!$M$2:$M$1153,MATCH(79,'Base articles'!$T$2:$T$1153,0))),"") | G85: =IFERROR(IF(INDEX('Base articles'!$N$2:$N$1153,MATCH(79,'Base articles'!$T$2:$T$1153,0))="","",INDEX('Base articles'!$N$2:$N$1153,MATCH(79,'Base articles'!$T$2:$T$1153,0))),"") | H85: =IFERROR(IF(INDEX('Base articles'!$P$2:$P$1153,MATCH(79,'Base articles'!$T$2:$T$1153,0))="","",INDEX('Base articles'!$P$2:$P$1153,MATCH(79,'Base articles'!$T$2:$T$1153,0))),"") | I85: =IFERROR(IF(INDEX('Base articles'!$Q$2:$Q$1153,MATCH(79,'Base articles'!$T$2:$T$1153,0))="","",INDEX('Base articles'!$Q$2:$Q$1153,MATCH(79,'Base articles'!$T$2:$T$1153,0))),"") | J85: =IFERROR(IF(INDEX('Base articles'!$B$2:$B$1153,MATCH(79,'Base articles'!$T$2:$T$1153,0))="","",INDEX('Base articles'!$B$2:$B$1153,MATCH(79,'Base articles'!$T$2:$T$1153,0))),"")
A86: =IFERROR(IF(INDEX('Base articles'!$D$2:$D$1153,MATCH(80,'Base articles'!$T$2:$T$1153,0))="","",INDEX('Base articles'!$D$2:$D$1153,MATCH(80,'Base articles'!$T$2:$T$1153,0))),"") | B86: =IFERROR(IF(INDEX('Base articles'!$F$2:$F$1153,MATCH(80,'Base articles'!$T$2:$T$1153,0))="","",INDEX('Base articles'!$F$2:$F$1153,MATCH(80,'Base articles'!$T$2:$T$1153,0))),"") | C86: =IFERROR(INDEX('Base articles'!$H$2:$H$1153,MATCH(80,'Base articles'!$T$2:$T$1153,0)),"") | D86: =IFERROR(IF(INDEX('Base articles'!$G$2:$G$1153,MATCH(80,'Base articles'!$T$2:$T$1153,0))="","",INDEX('Base articles'!$G$2:$G$1153,MATCH(80,'Base articles'!$T$2:$T$1153,0))),"") | E86: =IFERROR(IF(INDEX('Base articles'!$K$2:$K$1153,MATCH(80,'Base articles'!$T$2:$T$1153,0))="","",INDEX('Base articles'!$K$2:$K$1153,MATCH(80,'Base articles'!$T$2:$T$1153,0))),"") | F86: =IFERROR(IF(INDEX('Base articles'!$M$2:$M$1153,MATCH(80,'Base articles'!$T$2:$T$1153,0))="","",INDEX('Base articles'!$M$2:$M$1153,MATCH(80,'Base articles'!$T$2:$T$1153,0))),"") | G86: =IFERROR(IF(INDEX('Base articles'!$N$2:$N$1153,MATCH(80,'Base articles'!$T$2:$T$1153,0))="","",INDEX('Base articles'!$N$2:$N$1153,MATCH(80,'Base articles'!$T$2:$T$1153,0))),"") | H86: =IFERROR(IF(INDEX('Base articles'!$P$2:$P$1153,MATCH(80,'Base articles'!$T$2:$T$1153,0))="","",INDEX('Base articles'!$P$2:$P$1153,MATCH(80,'Base articles'!$T$2:$T$1153,0))),"") | I86: =IFERROR(IF(INDEX('Base articles'!$Q$2:$Q$1153,MATCH(80,'Base articles'!$T$2:$T$1153,0))="","",INDEX('Base articles'!$Q$2:$Q$1153,MATCH(80,'Base articles'!$T$2:$T$1153,0))),"") | J86: =IFERROR(IF(INDEX('Base articles'!$B$2:$B$1153,MATCH(80,'Base articles'!$T$2:$T$1153,0))="","",INDEX('Base articles'!$B$2:$B$1153,MATCH(80,'Base articles'!$T$2:$T$1153,0))),"")

Sheet Synthèse
A1: SYNTHÈSE PAR LOT
A2: Collecte du 09/09/2026 — 8 fournisseurs
A4: Lot | B4: Articles | C4: Prix relevés | D4: Dont votre tarif | E4: Comparables (2+) | F4: À compléter | G4: Couverture | H4: Prix moyen HT
A5: 01 · Électricité CFO | B5: 54 | C5: 52 | D5: 42 | E5: 36 | F5: 2 | G5: 0.96296296 | H5: 51.432885
A6: 02 · Courants faibles | B6: 26 | C6: 24 | D6: 17 | E6: 10 | F6: 2 | G6: 0.92307692 | H6: 260.71625
A7: 03 · Éclairage | B7: 19 | C7: 19 | D7: 9 | E7: 6 | F7: 0 | G7: 1 | H7: 93.003158
A8: 04 · Plomberie sanitaire | B8: 45 | C8: 44 | D8: 39 | E8: 40 | F8: 1 | G8: 0.97777778 | H8: 57.330682
A9: 05 · CVC | B9: 28 | C9: 26 | D9: 20 | E9: 18 | F9: 2 | G9: 0.92857143 | H9: 127.10962
A10: 06 · Serrurerie | B10: 36 | C10: 33 | D10: 27 | E10: 29 | F10: 3 | G10: 0.91666667 | H10: 39.379697
A11: 07 · Sécurité incendie | B11: 17 | C11: 12 | D11: 10 | E11: 7 | F11: 5 | G11: 0.70588235 | H11: 157.53
A12: 08 · Plâtrerie isolation | B12: 23 | C12: 23 | D12: 23 | E12: 23 | F12: 0 | G12: 1 | H12: 8.9169565
A13: 09 · Peinture | B13: 23 | C13: 23 | D13: 21 | E13: 21 | F13: 0 | G13: 1 | H13: 13.014348
A14: 10 · Sols et carrelage | B14: 17 | C14: 14 | D14: 14 | E14: 14 | F14: 3 | G14: 0.82352941 | H14: 20.466429
A15: 11 · Menuiserie | B15: 16 | C15: 16 | D15: 13 | E15: 12 | F15: 0 | G15: 1 | H15: 31.914375
A16: 12 · Gros œuvre | B16: 20 | C16: 19 | D16: 16 | E16: 14 | F16: 1 | G16: 0.95 | H16: 4.7794737
... A20: 16 · Maintenance | B20: 18 | C20: 16 | D20: 13 | E20: 11 | F20: 2 | G20: 0.88888889 | H20: 29.776875
A21: 03b · Éclairage Icilux | B21: 150 | C21: 150 | D21: 0 | E21: 0 | F21: 0 | G21: 1
A22: TOTAL | B22: 547 | C22: 526 | D22: 307 | E22: 289 | F22: 21 | G22: 0.96160878

Sheet Comparatif fournisseurs
A1: COMPARATIF FOURNISSEURS
A2: Prix HT par enseigne pour un même article — la cellule verte est la moins chère. Attention aux conditionnements : comparez à unité équivalente.
A4: Lot | B4: Article | C4: Unité | D4: Au Forum du Bâtiment | E4: YESSS Électrique | F4: Rexel | G4: La Plateforme du Bâtiment | H4: Chausson Matériaux | I4: Point.P | J4: Prolians | K4: SFIC | L4: Moins cher | M4: Prix retenu | N4: Écart max | O4: Enseignes | P4: Offres comparables ? | Q4: Retrait / disponibilité | R4: Produit retenu | S4: Fiche produit
A5: 01 · Électricité CFO | B5: Disjoncteur ph+N 10 A courbe C | C5: u | D5: 8.46 | F5: 8.78 | L5: Au Forum du Bâtiment | M5: 8.46 | N5: 3.6 | O5: 2 | P5: Oui — produits proches | Q5: Retrait agence · Livraison selon agence | R5: Disjoncteur FIXMATIC AUTO 10 A courbe C Phase + Neutre GEWISS GW90606F | S5: Voir la fiche
A6: 01 · Électricité CFO | B6: Disjoncteur ph+N 16 A courbe C | C6: u | D6: 8.09 | F6: 6.89 | L6: Rexel | M6: 6.89 | N6: 14.8 | O6: 2 | P6: À vérifier — produits différents | Q6: Retrait agence · Livraison selon agence | R6: ABB SN201L Disjoncteur modulaire - 1P+N - 16A - courbe C - 4500A/6kA - peignable | S6: Voir la fiche
A7: 01 · Électricité CFO | B7: Disjoncteur ph+N 20 A courbe C | C7: u | D7: 5.9 | F7: 6.82 | L7: Au Forum du Bâtiment | M7: 5.9 | N7: 13.5 | O7: 2 | P7: À vérifier — produits différents | Q7: Retrait agence · Livraison selon agence | R7: Disjoncteur 20 A courbe C Phase + neutre GEWISS GW90608 | S7: Voir la fiche
A8: 01 · Électricité CFO | B8: Disjoncteur ph+N 32 A courbe C | C8: u | D8: 10.61 | F8: 13.1 | L8: Au Forum du Bâtiment | M8: 10.61 | N8: 19 | O8: 2 | P8: Oui — produits proches | Q8: Retrait agence · Livraison selon agence | R8: Disjoncteur 32 A courbe C Phase + neutre GEWISS GW90610 | S8: Voir la fiche
A9: 01 · Électricité CFO | B9: Disjoncteur tetrapolaire 4P 32 A courbe C | C9: u | D9: 107.92 | L9: Au Forum du Bâtiment | M9: 107.92 | O9: 1 | Q9: Retrait agence · Livraison selon agence | R9: Disjoncteur ACTI9 IC60N 4P courbe C 32 A SCHNEIDER ELECTRIC A9F77432 | S9: Voir la fiche
A10: 01 · Électricité CFO | B10: Interrupteur differentiel 40 A 30 mA type AC | C10: u | D10: 58 | F10: 47.05 | H10: 50.85 | L10: Rexel | M10: 47.05 | N10: 18.9 | O10: 3 | P10: Oui — produits proches | Q10: Retrait agence · Livraison selon agence | R10: HAGER Interrupteur différentiel 2 poles 40 A 30 mA Type AC à Borne décalée | S10: Voir la fiche
A11: 01 · Électricité CFO | B11: Interrupteur differentiel 63 A 30 mA type A | C11: u | D11: 277.14 | H11: 121.52 | L11: Au Forum du Bâtiment | M11: 277.14 | O11: 2 | P11: Oui — produits proches | Q11: Retrait agence · Livraison selon agence | R11: Interrupteur différentiel DX3-ID 4PG 63 A type A 30 mA LEGRAND 411676 | S11: Voir la fiche
A12: 01 · Électricité CFO | B12: Disjoncteur differentiel 20 A 30 mA | C12: u | D12: 140.64 | E12: 251.34 | F12: 135.9 | L12: Rexel | M12: 135.9 | N12: 45.9 | O12: 3 | P12: À vérifier — produits différents | Q12: Retrait agence · Livraison selon agence | R12: LEGRAND Disjoncteur diff DX³ 4500 - vis/vis -U+N 230V~ 20A - typeAC -30mA -courbe C - 2M | S12: Voir la fiche
A13: 01 · Électricité CFO | B13: Parafoudre modulaire type 2 | C13: u | E13: 92.05 | F13: 60.72 | L13: Rexel | M13: 60.72 | N13: 34 | O13: 2 | P13: À vérifier — produits différents | Q13: Retrait agence · Livraison selon agence | R13: ADEE ELECTRONIC Parafoudre Type 2 modulaire 2P avec déconnecteur intégré, In 5kA Isccr 25kA | S13: Voir la fiche
A14: 01 · Électricité CFO | B14: Interrupteur sectionneur 63 A | C14: u | D14: 83.08 | E14: 74.75 | F14: 80.46 | L14: YESSS Électrique | M14: 74.75 | N14: 10 | O14: 3 | P14: À vérifier — produits différents | Q14: Retrait agence Aubervilliers · Livraison selon agence | R14: Interrupteur sectionneur modulaire IS 63A 2P
A15: 01 · Électricité CFO | B15: Contacteur jour/nuit 20 A | C15: u | E15: 122.01 | F15: 78.77 | H15: 37.79 | L15: Rexel | M15: 78.77 | N15: 35.4 | O15: 3 | P15: Oui — produits proches | Q15: Retrait agence · Livraison selon agence | R15: HAGER Contacteur Jour-Nuit 20A 2F 1 module | S15: Voir la fiche
A16: 01 · Électricité CFO | B16: Telerupteur unipolaire 16 A | C16: u | E16: 66.74 | F16: 56.26 | H16: 28.2 | I16: 43.79 | L16: Point.P | M16: 43.79 | N16: 34.4 | O16: 4 | P16: À vérifier — produits différents | Q16: Retrait agence Aubervilliers · En stock | R16: Télérupteur unipolaire 230 V alternatif - 16A - 1 module | S16: Voir la fiche
A17: 01 · Électricité CFO | B17: Minuterie modulaire d'escalier | C17: u | D17: 45.64 | F17: 46.31 | L17: Au Forum du Bâtiment | M17: 45.64 | N17: 1.4 | O17: 2 | P17: À vérifier — produits différents | Q17: Retrait agence · Livraison selon agence | R17: Minuterie modulaire 230 V 50 / 60 Hz sortie 16 A 250 V 1 module LEGRAND 412602 | S17: Voir la fiche
A18: 01 · Électricité CFO | B18: Horloge programmable modulaire | C18: u | D18: 84.44 | L18: Au Forum du Bâtiment | M18: 84.44 | O18: 1 | Q18: Retrait agence · Livraison selon agence | R18: Horloge programmable analogique SUL 180 a 1 canal THEBEN 1800001 | S18: Voir la fiche
A19: 01 · Électricité CFO | B19: Peigne d'alimentation ph+N 13 modules | C19: u | D19: 4.7 | E19: 27.95 | H19: 5.5 | L19: Au Forum du Bâtiment | M19: 4.7 | N19: 83.2 | O19: 3 | P19: À vérifier — produits différents | Q19: Retrait agence · Livraison selon agence | R19: Peigne d'alimentation universel Phase + Neutre HX³ / VX³ horizontale 1 P 13 modules LEGRAND 404926 | S19: Voir la fiche
A20: 01 · Électricité CFO | B20: Coffret electrique 2 rangees 26 modules | C20: u | E20: 674.69 | L20: YESSS Électrique | M20: 674.69 | O20: 1 | Q20: Retrait agence Aubervilliers · Livraison selon agence | R20: Coffret de distribution métal en saillie hauteur 450mm. équipé de 2 rangées de 24 modules et barreau laiton - pour la distribution électriqu
A21: 01 · Électricité CFO | B21: Coffret electrique 3 rangees 39 modules | C21: u | E21: 674.69 | L21: YESSS Électrique | M21: 674.69 | O21: 1 | Q21: Retrait agence Aubervilliers · Livraison selon agence | R21: Coffret de distribution métal en saillie hauteur 450mm. équipé de 2 rangées de 24 modules et barreau laiton - pour la distribution électriqu
A22: 01 · Électricité CFO | B22: Coffret etanche IP65 12 modules | C22: u | D22: 36.75 | E22: 80.09 | F22: 105.54 | H22: 71.43 | L22: Au Forum du Bâtiment | M22: 36.75 | N22: 65.2 | O22: 4 | P22: Oui — produits proches | Q22: Retrait agence · Livraison selon agence | R22: Coffret étanche IP65 400 V 12 modules GEWISS GW40103 | S22: Voir la fiche
A23: 01 · Électricité CFO | B23: Repartiteur modulaire 4 poles | C23: u | D23: 28.36 | F23: 44.73 | L23: Au Forum du Bâtiment | M23: 28.36 | N23: 36.6 | O23: 2 | P23: Oui — produits proches | Q23: Retrait agence · Livraison selon agence | R23: Répartiteur modulaire à barreaux étagés XL³ IK05 bipolaire 100A 6 départs 4 modules nouveau modèle LEGRAND 400401 | S23: Voir la fiche
A24: 01 · Électricité CFO | B24: Bornier de terre | C24: u | D24: 4.75 | E24: 13.52 | F24: 17.08 | L24: Au Forum du Bâtiment | M24: 4.75 | N24: 72.2 | O24: 3 | P24: Oui — produits proches | Q24: Retrait agence · Livraison selon agence | R24: Bornier de répartition isolé 8 connexions 1,5 mm² à 16 mm² terre LEGRAND 004832 | S24: Voir la fiche
A25: 01 · Électricité CFO | B25: Cable U-1000 R2V 3G1,5 mm2 | C25: ml | D25: 17.82 | I25: 32.04 | L25: Au Forum du Bâtiment | M25: 17.82 | O25: 2 | P25: Non — unités différentes | Q25: Retrait agence · Livraison selon agence | R25: Câble rigide U-1000 R2V 3G1,5 mm² 10 m noir FILS & CÂBLES 20218275C | S25: Voir la fiche
A26: 01 · Électricité CFO | B26: Cable U-1000 R2V 3G2,5 mm2 | C26: ml | D26: 27.43 | I26: 86.67 | L26: Au Forum du Bâtiment | M26: 27.43 | O26: 2 | P26: Non — unités différentes | Q26: Retrait agence · Livraison selon agence | R26: Câble rigide U-1000 R2V 3G2,5 mm² 10 m noir FILS & CÂBLES 20218285C | S26: Voir la fiche
A27: 01 · Électricité CFO | B27: Cable U-1000 R2V 5G6 mm2 | C27: ml | F27: 8.24 | L27: Rexel | M27: 8.24 | O27: 1 | Q27: Retrait agence · Livraison selon agence | R27: Câble rigide Nexans R2V Distingo cuivre 5G6 mm² en couronne de 25 m
A28: 01 · Électricité CFO | B28: Fil H07V-U 1,5 mm2 couronne 100 m | C28: couronne | F28: 25 | I28: 30.3 | L28: Rexel | M28: 25 | N28: 17.5 | O28: 2 | P28: Oui — produits proches | Q28: Retrait agence · Livraison selon agence | R28: Fil rigide H07VU 1,5 mm² Bleu en couronne de 100m
A29: 01 · Électricité CFO | B29: Fil H07V-U 2,5 mm2 couronne 100 m | C29: couronne | F29: 42 | I29: 46.11 | L29: Rexel | M29: 42 | N29: 8.9 | O29: 2 | P29: Oui — produits proches | Q29: Retrait agence · Livraison selon agence | R29: Fil rigide H07VU 2,5 mm² Bleu en couronne de 100m | S29: Voir la fiche
A30: 01 · Électricité CFO | B30: Fil H07V-K souple 6 mm2 | C30: ml | F30: 1.53 | L30: Rexel | M30: 1.53 | O30: 1 | Q30: Retrait agence · Livraison selon agence | R30: Fil souple H07VK 6 mm² Vert/Jaune en couronne de 100m | S30: Voir la fiche
A31: 01 · Électricité CFO | B31: Cable CR1-C1 resistant au feu 3G1,5 | C31: ml | E31: 3.98 | L31: YESSS Électrique | M31: 3.98 | O31: 1 | Q31: Retrait agence Aubervilliers · Livraison selon agence | R31: Câble d'alimentation cuivre anti-feu CR1-C1 3G1,5 - Touret de 500m
A32: 01 · Électricité CFO | B32: Gaine ICTA 20 mm couronne 100 m | C32: couronne | F32: 47 | H32: 59.3 | L32: Rexel | M32: 47 | O32: 2 | P32: Oui — produits proches | Q32: Retrait agence · Livraison selon agence | R32: COURANT Sponsorisé Flexpro+ noir tagp 20/100 - Gaine ICTA 3422 de qualité supérieure | S32: Voir la fiche
A33: 01 · Électricité CFO | B33: Gaine ICTA 25 mm couronne 100 m | C33: couronne | D33: 63.11 | F33: 0.82 | L33: Au Forum du Bâtiment | M33: 63.11 | O33: 2 | P33: Oui — produits proches | Q33: Retrait agence · Livraison selon agence | R33: Gaine électrique ICTA avec tire-fils gris foncé diamètre 25 mm GEWISS DX20525R | S33: Voir la fiche
A34: 01 · Électricité CFO | B34: Tube IRL 3321 gris 20 mm | C34: ml | D34: 1.86 | L34: Au Forum du Bâtiment | M34: 1.86 | O34: 1 | Q34: Retrait agence · Livraison selon agence | R34: Tube IRL tulipé rigide lisse L3 m gris D16 mm GEWISS DX27716 | S34: Voir la fiche
A35: 01 · Électricité CFO | B35: Goulotte PVC 60x40 mm | C35: ml | D35: 22.11 | F35: 16.02 | L35: Au Forum du Bâtiment | M35: 22.11 | O35: 2 | P35: Oui — produits proches | Q35: Retrait agence · Livraison selon agence | R35: Goulotte d'appareillage Obo Bettermann Rapid 45-2 en PVC H 53 mm l 100 - 6113000 | S35: Voir la fiche
A36: 01 · Électricité CFO | B36: Goulotte PVC 100x50 mm | C36: ml | D36: 22.11 | L36: Au Forum du Bâtiment | M36: 22.11 | O36: 1 | Q36: Retrait agence · Livraison selon agence | R36: Goulotte d'appareillage Obo Bettermann Rapid 45-2 en PVC H 53 mm l 100 - 6113000 | S36: Voir la fiche
A37: 01 · Électricité CFO | B37: Moulure PVC 20x12 mm | C37: ml | I37: 2.37 | L37: Point.P | M37: 2.37 | O37: 1 | Q37: Retrait agence Aubervilliers · En stock | R37: Moulure DLPlus avec cloison - PVC blanc - section 20x12,5 mm - L. 2,1 m | S37: Voir la fiche
A38: 01 · Électricité CFO | B38: Chemin de cables tole perforee 100 mm | C38: ml | D38: 24.86 | L38: Au Forum du Bâtiment | M38: 24.86 | O38: 1 | Q38: Retrait agence · Livraison selon agence | R38: Dalle chemin de câble PSN perforée 3 m 147 x 27 mm NIEDAX 001005 | S38: Voir la fiche
A39: 01 · Électricité CFO | B39: Collier de fixation Colson 200 mm | C39: u | F39: 0.39 | L39: Rexel | M39: 0.39 | O39: 1 | Q39: Retrait agence · Livraison selon agence | R39: LEGRAND Lot de 100 colliers Colson SP largeur 9mm - longueur 262mm - noir
A40: 01 · Électricité CFO | B40: Prise de courant 2P+T 16 A encastree | C40: u | D40: 15.8 | E40: 28.88 | F40: 42.97 | H40: 3.57 | I40: 5.18 | L40: Point.P | M40: 5.18 | N40: 87.9 | O40: 5 | P40: Oui — produits proches | Q40: Retrait agence Aubervilliers · Sur commande | R40: Détrompeur Mosaic pour fiche et prise de courant 2P+T | S40: Voir la fiche
A41: 01 · Électricité CFO | B41: Prise de courant 2P+T 16 A etanche IP55 saillie | C41: u | D41: 11.2 | E41: 16.28 | L41: Au Forum du Bâtiment | M41: 11.2 | N41: 31.2 | O41: 2 | P41: Oui — produits proches | Q41: Retrait agence · Livraison selon agence | R41: Prise de courant 2P+T étanche PLEXO Legrand 16 A 250 V pour fixation saillie gris (boîte de 10) - 069731L | S41: Voir la fiche
A42: 01 · Électricité CFO | B42: Prise 32 A tetrapolaire | C42: u | D42: 46.21 | L42: Au Forum du Bâtiment | M42: 46.21 | O42: 1 | Q42: Retrait agence · Livraison selon agence | R42: P17 prise mobile 32A 3P+T 415V IP44 (boite 10) | S42: Voir la fiche
A43: 01 · Électricité CFO | B43: Interrupteur va-et-vient encastre | C43: u | D43: 11.48 | E43: 25.19 | H43: 3.82 | L43: Au Forum du Bâtiment | M43: 11.48 | N43: 54.4 | O43: 3 | P43: Oui — produits proches | Q43: Retrait agence · Livraison selon agence | R43: Interrupteur ou va-et-vient étanche PLEXO complet IP55 encastré gris LEGRAND 069811 | S43: Voir la fiche
A44: 01 · Électricité CFO | B44: Bouton poussoir lumineux | C44: u | D44: 51.33 | E44: 34.09 | H44: 3.97 | I44: 109.88 | L44: YESSS Électrique | M44: 34.09 | N44: 69 | O44: 4 | P44: À vérifier — produits différents | Q44: Retrait agence Aubervilliers · Livraison selon agence | R44: Bouton poussoir lumineux 6A nouveau Céliane avec doigt anneau
A45: 01 · Électricité CFO | B45: Variateur de lumiere LED | C45: u | D45: 75 | E45: 83.6 | H45: 51.23 | L45: Au Forum du Bâtiment | M45: 75 | N45: 10.3 | O45: 3 | P45: À vérifier — produits différents | Q45: Retrait agence · Livraison selon agence | R45: Interrupteur variateur DOOXIE universel 2 fils sans neutre 125 W LED LEGRAND 600060A | S45: Voir la fiche
A46: 01 · Électricité CFO | B46: Detecteur de mouvement mural interieur | C46: u | D46: 34.16 | L46: Au Forum du Bâtiment | M46: 34.16 | O46: 1 | Q46: Retrait agence · Livraison selon agence | R46: Détecteur de mouvement THELUXA mural extérieur S150 WH blanc THEBEN 1010500 | S46: Voir la fiche
A47: 01 · Électricité CFO | B47: Boite d'encastrement simple 1 poste | C47: u | D47: 1.85 | E47: 4.53 | F47: 24.45 | H47: 0.78 | L47: Au Forum du Bâtiment | M47: 1.85 | N47: 92.4 | O47: 4 | P47: Oui — produits proches | Q47: Retrait agence · Livraison selon agence | R47: Boîte d'encastrement BATIBOX pour cloisons sèches 1 poste LEGRAND 080041 | S47: Voir la fiche
A48: 01 · Électricité CFO | B48: Boite de derivation etanche IP55 100x100 | C48: u | D48: 5.55 | E48: 135.25 | F48: 7.47 | L48: Au Forum du Bâtiment | M48: 5.55 | N48: 95.9 | O48: 3 | P48: À vérifier — produits différents | Q48: Retrait agence · Livraison selon agence | R48: Boîte de dérivation étanche 450 V AC IP68 2 entrées MIIDEX LIGHTING 7230 | S48: Voir la fiche
A49: 01 · Électricité CFO | B49: Borne de connexion automatique 3 entrees | C49: sachet | D49: 26.23 | E49: 48.01 | F49: 60.93 | L49: Au Forum du Bâtiment | M49: 26.23 | O49: 3 | P49: Non — unités différentes | Q49: Retrait agence · Livraison selon agence | R49: Boîte de 50 bornes de connexion automatiques transparentes 3 fils (2,5 - 6 mm²) WAGO 773-173 | S49: Voir la fiche
A50: 01 · Électricité CFO | B50: Dominos / barrette de connexion 10 mm2 | C50: u | D50: 4.18 | L50: Au Forum du Bâtiment | M50: 4.18 | O50: 1 | Q50: Retrait agence · Livraison selon agence | R50: Barrette de connexion NYLBLOC avec capacité assignée 10 mm² noir LEGRAND 034215 | S50: Voir la fiche
A51: 01 · Électricité CFO | B51: Plaque de finition simple | C51: u | D51: 0.89 | H51: 1.44 | I51: 114.13 | L51: Au Forum du Bâtiment | M51: 0.89 | N51: 99.2 | O51: 3 | P51: À vérifier — produits différents | Q51: Retrait agence · Livraison selon agence | R51: Plaque CÉLIANE finition blanc Laqué 1 poste LEGRAND 066631 | S51: Voir la fiche
A52: 01 · Électricité CFO | B52: Prise RJ45 categorie 6 | C52: u | D52: 10.27 | E52: 25.93 | H52: 16.16 | I52: 28.6 | L52: Au Forum du Bâtiment | M52: 10.27 | N52: 64.1 | O52: 4 | P52: À vérifier — produits différents | Q52: Retrait agence · Livraison selon agence | R52: Mécanisme prise RJ45 OVALIS catégorie 6 STP grade 3 blanc SCHNEIDER ELECTRIC S320476 | S52: Voir la fiche
A53: 01 · Électricité CFO | B53: Piquet de terre 1,50 m | C53: u | D53: 10.74 | L53: Au Forum du Bâtiment | M53: 10.74 | O53: 1 | Q53: Retrait agence · Livraison selon agence | R53: Piquet de terre | S53: Voir la fiche
A54: 01 · Électricité CFO | B54: Barrette de coupure de terre | C54: u | D54: 8.17 | E54: 29.88 | F54: 14.2 | H54: 4.79 | I54: 16.22 | L54: Au Forum du Bâtiment | M54: 8.17 | N54: 72.7 | O54: 5 | P54: Oui — produits proches | Q54: Retrait agence · Livraison selon agence | R54: Barrette de coupure socle plastique FORSOND BAR-32 | S54: Voir la fiche
A55: 01 · Électricité CFO | B55: Cosse a oeil / cosse de terre | C55: u | F55: 6.64 | H55: 34.75 | L55: Rexel | M55: 6.64 | O55: 2 | P55: Oui — produits proches | Q55: Retrait agence · Livraison selon agence | R55: TE CONNECTIVITY (EX TYCO SIMEL) CDCT 75-10-Cosse cuivre de terre à sertir pour postes HT-75mm²-Bornage: 10mm | S55: Voir la fiche
A56: 01 · Électricité CFO | B56: Gaine thermoretractable assortiment | C56: boite | D56: 27.54 | H56: 9.12 | I56: 108.93 | L56: Au Forum du Bâtiment | M56: 27.54 | N56: 74.7 | O56: 3 | P56: Non — unités différentes | Q56: Retrait agence · Livraison selon agence | R56: Temporisation 12/24VDC 1 contact NF avec gaine thermorétractable SEWOSY TPNC | S56: Voir la fiche
A57: 02 · Courants faibles | B57: Cable F/FTP categorie 6A | C57: ml | D57: 152.8 | F57: 1.05 | L57: Au Forum du Bâtiment | M57: 152.8 | O57: 2 | P57: Oui — produits proches | Q57: Retrait agence · Livraison selon agence | R57: Câble 4 paires S/FTP catégorie 6 LEXCOM HOME bobine 120 m blanc SCHNEIDER ELECTRIC VDIR534810 | S57: Voir la fiche
A58: 02 · Courants faibles | B58: Panneau de brassage 24 ports RJ45 cat 6 | C58: u | F58: 78.64 | L58: Rexel | M58: 78.64 | O58: 1 | Q58: Retrait agence · Livraison selon agence | R58: LEGRAND Panneau de brassage Linkeo C à équiper de 24 connecteurs RJ45 Keystone
A59: 02 · Courants faibles | B59: Cordon de brassage RJ45 cat 6 2 m | C59: u | E59: 24.07 | L59: YESSS Électrique | M59: 24.07 | O59: 1 | Q59: Retrait agence Aubervilliers · Livraison selon agence | R59: Cordon de brassage quadruple RJ45 téléphone pour réseau multimédia
A60: 02 · Courants faibles | B60: Coffret de brassage 9U | C60: u | D60: 145.13 | E60: 212.84 | L60: Au Forum du Bâtiment | M60: 145.13 | N60: 31.8 | O60: 2 | P60: Oui — produits proches | Q60: Retrait agence · Livraison selon agence | R60: Coffret multimédia basique DRIVIA avec brassage équipé et précâblé 4 prises RJ45 LEGRAND 413218 | S60: Voir la fiche
A61: 02 · Courants faibles | B61: Switch ethernet 8 ports PoE | C61: u | E61: 337.88 | L61: YESSS Électrique | M61: 337.88 | O61: 1 | Q61: Retrait agence Aubervilliers · Livraison selon agence | R61: Switch PoE Fast Ethernet 5 ports
A62: 02 · Courants faibles | B62: Camera IP dome interieure | C62: u | D62: 133.8 | E62: 36.99 | L62: YESSS Électrique | M62: 36.99 | N62: 72.4 | O62: 2 | P62: À vérifier — produits différents | Q62: Retrait agence Aubervilliers · Livraison selon agence | R62: CAMERA DOME INTERIEUR FACTICE
A63: 02 · Courants faibles | B63: Camera IP tube exterieure | C63: u | D63: 164.7 | L63: Au Forum du Bâtiment | M63: 164.7 | O63: 1 | Q63: Retrait agence · Livraison selon agence | R63: Caméra extérieure RHEITA100 connectée éclairage intégré THOMSON 512511 | S63: Voir la fiche
A64: 02 · Courants faibles | B64: Disque dur surveillance 4 To | C64: u | D64: 224.6 | F64: 549.98 | L64: Au Forum du Bâtiment | M64: 224.6 | N64: 59.2 | O64: 2 | P64: À vérifier — produits différents | Q64: Retrait agence · Livraison selon agence | R64: Disque diamant pour dalles et carrelage dur 180 x 25,4 mm DIAM INDUSTRIES CR90180/25 | S64: Voir la fiche
A65: 02 · Courants faibles | B65: Platine de rue interphone 2 fils | C65: u | E65: 581.48 | L65: YESSS Électrique | M65: 581.48 | O65: 1 | Q65: Retrait agence Aubervilliers · Livraison selon agence | R65: Kit vidéo SOUL couleur 2 fils non polarisé WIFI 1 appel - contenant : - 1 moniteur mains-libres couleur 7'' tactile WIFI avec mémoire d'ima
A66: 02 · Courants faibles | B66: Combine interphone interieur | C66: u | D66: 30.02 | L66: Au Forum du Bâtiment | M66: 30.02 | O66: 1 | Q66: Retrait agence · Livraison selon agence | R66: Combiné universel T-LINE GOLMAR UAV1407/010 | S66: Voir la fiche
A67: 02 · Courants faibles | B67: Portier video couleur | C67: u | E67: 854.25 | L67: YESSS Électrique | M67: 854.25 | O67: 1 | Q67: Retrait agence Aubervilliers · Livraison selon agence | R67: XTS 7 WH WFBF Portier vidéo mains libres 100% tactile pour système X1, écran tactile TFT 7&quot;, WI-FI et interface utilisateur graphique,
A68: 02 · Courants faibles | B68: Lecteur de badge mural | C68: u | D68: 509.9 | L68: Au Forum du Bâtiment | M68: 509.9 | O68: 1 | Q68: Retrait agence · Livraison selon agence | R68: Lecteur mural XS4 2.0 mifare carré noir - SALTO - WRDM0S4B | S68: Voir la fiche
A69: 02 · Courants faibles | B69: Badge de proximite Mifare | C69: u | D69: 1.14 | F69: 3.03 | L69: Au Forum du Bâtiment | M69: 1.14 | N69: 62.4 | O69: 2 | P69: Oui — produits proches | Q69: Retrait agence · Livraison selon agence | R69: Badge de proximité Salto Mifare Ultralight C | S69: Voir la fiche
A70: 02 · Courants faibles | B70: Clavier a code exterieur | C70: u | D70: 54 | E70: 123.25 | L70: Au Forum du Bâtiment | M70: 54 | N70: 56.2 | O70: 2 | P70: À vérifier — produits différents | Q70: Retrait agence · Livraison selon agence | R70: Clavier aluminium 30 codes FERMAX PL030 | S70: Voir la fiche
A71: 02 · Courants faibles | B71: Bouton de sortie inox | C71: u | D71: 2.2 | E71: 96.53 | I71: 17.33 | L71: Au Forum du Bâtiment | M71: 2.2 | N71: 97.7 | O71: 3 | P71: À vérifier — produits différents | Q71: Retrait agence · Livraison selon agence | R71: Bouton sphérique en inox finition mate Didheya | S71: Voir la fiche
A72: 02 · Courants faibles | B72: Centrale d'alarme intrusion filaire | C72: u | D72: 472.58 | L72: Au Forum du Bâtiment | M72: 472.58 | O72: 1 | Q72: Retrait agence · Livraison selon agence | R72: Kit centrale d'alarme HERACLES ARD-KIT | S72: Voir la fiche
A73: 02 · Courants faibles | B73: Detecteur d'ouverture magnetique | C73: u | D73: 21.13 | L73: Au Forum du Bâtiment | M73: 21.13 | O73: 1 | Q73: Retrait agence · Livraison selon agence | R73: Détecteur d'ouverture de porte pour alarme Skyda HomeSecure AVIDSEN 100723 | S73: Voir la fiche
A74: 02 · Courants faibles | B74: Detecteur infrarouge volumetrique | C74: u | D74: 8.91 | L74: Au Forum du Bâtiment | M74: 8.91 | O74: 1 | Q74: Retrait agence · Livraison selon agence | R74: Détecteur de mouvement infrarouge LUMOS LITE pour projecteur Lumos Lite et Lumos Pro MIIDEX 100861 | S74: Voir la fiche
A75: 02 · Courants faibles | B75: Sirene exterieure autoalimentee | C75: u | D75: 137.91 | L75: Au Forum du Bâtiment | M75: 137.91 | O75: 1 | Q75: Retrait agence · Livraison selon agence | R75: Sirène extérieure solaire pour alarme Skyda et HomeSecure AVIDSEN 100728 | S75: Voir la fiche
A76: 02 · Courants faibles | B76: Prise TV coaxiale | C76: u | E76: 30.81 | L76: YESSS Électrique | M76: 30.81 | O76: 1 | Q76: Retrait agence Aubervilliers · Livraison selon agence | R76: Odace - prise TV/FM - sorties coaxiales - blanc craie
A77: 02 · Courants faibles | B77: Cable coaxial 17 VATC | C77: ml | D77: 2.96 | H77: 114.45 | I77: 19.7 | L77: Au Forum du Bâtiment | M77: 2.96 | O77: 3 | P77: Non — unités différentes | Q77: Retrait agence · Livraison selon agence | R77: Câble coaxial blanc 17VATC T500 5 m 60135013E | S77: Voir la fiche
A78: 02 · Courants faibles | B78: Repartiteur TV 4 sorties | C78: u | D78: 23.65 | E78: 237.86 | I78: 87.85 | L78: Au Forum du Bâtiment | M78: 23.65 | N78: 90.1 | O78: 3 | P78: Oui — produits proches | Q78: Retrait agence · Livraison selon agence | R78: Répartiteur ferrite TV 4 sorties LEBENOID 032528 | S78: Voir la fiche
A79: 02 · Courants faibles | B79: Pince a sertir RJ45 | C79: u | F79: 25.14 | I79: 36.37 | L79: Rexel | M79: 25.14 | N79: 30.9 | O79: 2 | P79: Oui — produits proches | Q79: Retrait agence · Livraison selon agence | R79: GIGAMEDIA Pince à sertir économique pour RJ45 8 points | S79: Voir la fiche
A80: 02 · Courants faibles | B80: Testeur de cable reseau | C80: u | F80: 2488.05 | L80: Rexel | M80: 2488.05 | O80: 1 | Q80: Retrait agence · Livraison selon agence | R80: FLUKE NETWORKS Testeur de câble et de réseau LinkIQ | S80: Voir la fiche
A81: 03 · Éclairage | B81: Spot LED encastre 7 W blanc neutre | C81: u | D81: 11.39 | H81: 118.84 | I81: 37.42 | L81: Au Forum du Bâtiment | M81: 11.39 | N81: 69.6 | O81: 3 | P81: Non — unités différentes | Q81: Retrait agence · Livraison selon agence | R81: Spot encastré à LED intégré YOURHOME 500 lm blanc IP44 4000 K 840 SYLVANIA 90012 | S81: Voir la fiche
A82: 03 · Éclairage | B82: Downlight LED 20 W diametre 200 mm | C82: u | D82: 112.71 | L82: Au Forum du Bâtiment | M82: 112.71 | O82: 1 | Q82: Retrait agence · Livraison selon agence | R82: Downlight LED SIRIUS BASSE LUM blanc rond basse luminance 2000 lm 25 W 4000 K MIIDEX LIGHTING 765482 | S82: Voir la fiche
A83: 03 · Éclairage | B83: Dalle LED 600x600 36 W | C83: u | D83: 27.39 | L83: Au Forum du Bâtiment | M83: 27.39 | O83: 1 | Q83: Retrait agence · Livraison selon agence | R83: Dalle LED ANDROMEDE Backlit 25 W 4000 K prismatique MIIDEX 100998 | S83: Voir la fiche
A84: 03 · Éclairage | B84: Reglette LED etanche 1,20 m 36 W IP65 | C84: u | F84: 41.94 | L84: Rexel | M84: 41.94 | O84: 1 | Q84: Retrait agence · Livraison selon agence | R84: BAILEY LED Réglette étanche Basic Slim 1200 36W 4000K 3960lm IP65 125D 240V
A85: 03 · Éclairage | B85: Reglette LED 0,60 m 18 W | C85: u | D85: 20.6 | L85: Au Forum du Bâtiment | M85: 20.6 | O85: 1 | Q85: Retrait agence · Livraison selon agence | R85: Réglette LED IP20 BATTEN 4000 K 16 W simple L1200 mm SYLVANIA 0045159 | S85: Voir la fiche
A86: 03 · Éclairage | B86: Rail 3 allumages 2 m | C86: u | D86: 39.6 | L86: Au Forum du Bâtiment | M86: 39.6 | O86: 1 | Q86: Retrait agence · Livraison selon agence | R86: Spot LED sur rail noir 35 W 4000 K 3000 lm + adaptateur rail 3 allumages MIIDEX LIGHTING S8358 | S86: Voir la fiche
A87: 03 · Éclairage | B87: Projecteur sur rail LED 30 W | C87: u | F87: 121.28 | H87: 34.34 | I87: 23.4 | L87: Point.P | M87: 23.4 | N87: 80.7 | O87: 3 | P87: À vérifier — produits différents | Q87: Retrait agence Aubervilliers · Sur commande | R87: Projecteur extérieur LED - 10 W | S87: Voir la fiche
A88: 03 · Éclairage | B88: Ruban LED 24 V 14 W/m | C88: ml | F88: 8.9 | L88: Rexel | M88: 8.9 | O88: 1 | Q88: Retrait agence · Livraison selon agence | R88: ARIC Ruban LED COB IP20 24V FREECUT 3000K 9W/m 750lm/m découpe au mm, rouleau 20m
A89: 03 · Éclairage | B89: Alimentation LED 24 V 100 W | C89: u | D89: 158.77 | L89: Au Forum du Bâtiment | M89: 158.77 | O89: 1 | Q89: Retrait agence · Livraison selon agence | R89: Alimentation pour LED IP67 100W 24V DC MIIDEX LIGHTING 75371 | S89: Voir la fiche
A90: 03 · Éclairage | B90: Ampoule LED E27 10 W | C90: u | D90: 50.9 | H90: 1.58 | L90: Au Forum du Bâtiment | M90: 50.9 | O90: 2 | P90: Oui — produits proches | Q90: Retrait agence · Livraison selon agence | R90: Ampoule LED E27 10 W SMD R80 3000 K pack de 2 MIIDEX LIGHTING 76661 | S90: Voir la fiche
A91: 03 · Éclairage | B91: Ampoule LED GU10 5 W | C91: u | D91: 2.58 | L91: Au Forum du Bâtiment | M91: 2.58 | O91: 1 | Q91: Retrait agence · Livraison selon agence | R91: Ampoule LED GU10 spot 5 W 2700 K MIIDEX LIGHTING 78401 | S91: Voir la fiche
A92: 03 · Éclairage | B92: Tube LED T8 1,20 m 18 W | C92: u | D92: 38.38 | L92: Au Forum du Bâtiment | M92: 38.38 | O92: 1 | Q92: Retrait agence · Livraison selon agence | R92: Boitier étanche LED IROISE sans ballast P/N même côté pour 1 TUBE T8 de 600 mm MIIDEX LIGHTING 75891 | S92: Voir la fiche
A93: 03 · Éclairage | B93: Projecteur LED exterieur 50 W IP65 | C93: u | D93: 420.54 | H93: 34.34 | I93: 104.9 | L93: Point.P | M93: 104.9 | N93: 75.1 | O93: 3 | P93: À vérifier — produits différents | Q93: Retrait agence Aubervilliers · En stock | R93: Projecteur Led de chantier Multi Battery System 4000 MA - rechargeable - 40 W - 4500 lm - 6500 K - IP65 - compatible avec 5 standards de bat | S93: Voir la fiche
A94: 03 · Éclairage | B94: Hublot LED exterieur 18 W avec detecteur | C94: u | D94: 36.93 | L94: Au Forum du Bâtiment | M94: 36.93 | O94: 1 | Q94: Retrait agence · Livraison selon agence | R94: Hublot LED RONDO avec détecteur infrarouge + crépusculaire 18 W IP65 3000 K MIIDEX LIGHTING 7790020 | S94: Voir la fiche
A95: 03 · Éclairage | B95: Applique murale exterieure LED | C95: u | D95: 891.91 | L95: Au Forum du Bâtiment | M95: 891.91 | O95: 1 | Q95: Retrait agence · Livraison selon agence | R95: APPLIQUE MURALE EXTERIEUR LED WALLPACK 100 W 4000 K SLIM | S95: Voir la fiche
A96: 03 · Éclairage | B96: BAES evacuation SATI 45 lumens | C96: u | D96: 69.9 | E96: 414.16 | F96: 58.62 | L96: Rexel | M96: 58.62 | N96: 85.8 | O96: 3 | P96: À vérifier — produits différents | Q96: Retrait agence · Livraison selon agence | R96: EATON LUMINOX BAES évacuation SATI - 45lm/1h - IP43 IK07 - Pose mur/plafond - Visibilité+ | S96: Voir la fiche
A97: 03 · Éclairage | B97: BAES ambiance 400 lumens | C97: u | F97: 123.64 | L97: Rexel | M97: 123.64 | O97: 1 | Q97: Retrait agence · Livraison selon agence | R97: EATON LUMINOX BAES ambiance SATI - 400 lm/1h - IP43 IK07 - Design épuré - diffusion uniforme
A98: 03 · Éclairage | B98: Telecommande de mise au repos BAES | C98: u | E98: 234.11 | F98: 120.61 | L98: Rexel | M98: 120.61 | N98: 48.5 | O98: 2 | P98: À vérifier — produits différents | Q98: Retrait agence · Livraison selon agence | R98: EATON LUMINOX Télécommande universelle pour 500 BAES - Fonction Visibilité+/locaux à sommeil
A99: 03 · Éclairage | B99: Etiquette de balisage evacuation | C99: u | J99: 13.77 | L99: Prolians | M99: 13.77 | O99: 1 | Q99: Click & Collect 2 h gratuit · Livraison 24-48 h annoncée sur la fiche | R99: Plaque de signalisation « sortie de secours » souple | S99: Voir la fiche
A100: 04 · Plomberie sanitaire | B100: Tube PER nu 16 mm couronne | C100: couronne | D100: 1.59 | G100: 16.9 | I100: 24.23 | L100: Au Forum du Bâtiment | M100: 1.59 | O100: 3 | P100: Non — unités différentes | Q100: Retrait agence · Livraison selon agence | R100: Raccord droit à souder PER sur tube cuivre 16 TC 14 GARIS 3315-16-14 | S100: Voir la fiche
A101: 04 · Plomberie sanitaire | B101: Tube PER gaine 16 mm couronne | C101: couronne | D101: 91.61 | E101: 68.66 | G101: 16.9 | I101: 24.23 | L101: Au Forum du Bâtiment | M101: 91.61 | O101: 4 | P101: Non — unités différentes | Q101: Retrait agence · Livraison selon agence | R101: Tube PER pré gainé bleu 50 m 16/20 SOMATHERM 1113-20-50A | S101: Voir la fiche
...

Sheet Contrôles qualité
A1: CONTRÔLES DE COHÉRENCE
A2: Chaque ligne signalée demande une vérification avant reprise dans un devis client. Le catalogue ne contient aucun prix estimé : une ligne sans prix vérifié reste vide.
A4: Lot | B4: Article | C4: Fournisseur | D4: Prix HT | E4: Nature du contrôle | F4: Ce qu'il faut faire
A5: 01 · Électricité CFO | B5: Disjoncteur tetrapolaire 4P 32 A courbe C | C5: Au Forum du Bâtiment | D5: 107.92 | E5: Correspondance article/produit à confirmer | F5: Ouvrir la fiche fournisseur et confirmer que le produit correspond bien à l'article
A6: 01 · Électricité CFO | B6: Minuterie modulaire d'escalier | C6: Au Forum du Bâtiment | D6: 45.64 | E6: Correspondance article/produit à confirmer | F6: Ouvrir la fiche fournisseur et confirmer que le produit correspond bien à l'article
A7: 01 · Électricité CFO | B7: Horloge programmable modulaire | C7: Au Forum du Bâtiment | D7: 84.44 | E7: Correspondance article/produit à confirmer | F7: Ouvrir la fiche fournisseur et confirmer que le produit correspond bien à l'article
A8: 01 · Électricité CFO | B8: Repartiteur modulaire 4 poles | C8: Au Forum du Bâtiment | D8: 28.36 | E8: Correspondance article/produit à confirmer | F8: Ouvrir la fiche fournisseur et confirmer que le produit correspond bien à l'article
A9: 01 · Électricité CFO | B9: Cable U-1000 R2V 3G1,5 mm2 | C9: Au Forum du Bâtiment | D9: 17.82 | E9: Correspondance article/produit à confirmer | F9: Ouvrir la fiche fournisseur et confirmer que le produit correspond bien à l'article
A10: 01 · Électricité CFO | B10: Cable U-1000 R2V 3G2,5 mm2 | C10: Au Forum du Bâtiment | D10: 27.43 | E10: Correspondance article/produit à confirmer | F10: Ouvrir la fiche fournisseur et confirmer que le produit correspond bien à l'article
A11: 01 · Électricité CFO | B11: Cable U-1000 R2V 5G6 mm2 | C11: Rexel | D11: 8.24 | E11: Correspondance article/produit à confirmer | F11: Ouvrir la fiche fournisseur et confirmer que le produit correspond bien à l'article
A12: 01 · Électricité CFO | B12: Fil H07V-U 1,5 mm2 couronne 100 m | C12: Rexel | D12: 25 | E12: Correspondance article/produit à confirmer | F12: Ouvrir la fiche fournisseur et confirmer que le produit correspond bien à l'article
A13: 01 · Électricité CFO | B13: Gaine ICTA 25 mm couronne 100 m | C13: Au Forum du Bâtiment | D13: 63.11 | E13: Correspondance article/produit à confirmer | F13: Ouvrir la fiche fournisseur et confirmer que le produit correspond bien à l'article
A14: 01 · Électricité CFO | B14: Tube IRL 3321 gris 20 mm | C14: Au Forum du Bâtiment | D14: 1.86 | E14: Correspondance article/produit à confirmer | F14: Ouvrir la fiche fournisseur et confirmer que le produit correspond bien à l'article
A15: 01 · Électricité CFO | B15: Goulotte PVC 60x40 mm | C15: Au Forum du Bâtiment | D15: 22.11 | E15: Correspondance article/produit à confirmer | F15: Ouvrir la fiche fournisseur et confirmer que le produit correspond bien à l'article
A16: 01 · Électricité CFO | B16: Goulotte PVC 100x50 mm | C16: Au Forum du Bâtiment | D16: 22.11 | E16: Correspondance article/produit à confirmer | F16: Ouvrir la fiche fournisseur et confirmer que le produit correspond bien à l'article
... A24: 01 · Électricité CFO | B24: Plaque de finition simple | C24: Au Forum du Bâtiment | D24: 0.89 | E24: Correspondance article/produit à confirmer | F24: Ouvrir la fiche fournisseur et confirmer que le produit correspond bien à l'article
A25: 01 · Électricité CFO | B25: Prise de courant plan de travail escamotable | C25: — à renseigner — | E25: Aucune offre chez vos 8 fournisseurs — article à sourcer | F25: Sourcer l'article chez un fournisseur spécialisé, ou le retirer de la nomenclature
A26: 01 · Électricité CFO | B26: Piquet de terre 1,50 m | C26: Au Forum du Bâtiment | D26: 10.74 | E26: Correspondance article/produit à confirmer | F26: Ouvrir la fiche fournisseur et confirmer que le produit correspond bien à l'article
A27: 01 · Électricité CFO | B27: Barrette de coupure de terre | C27: Au Forum du Bâtiment | D27: 8.17 | E27: Correspondance article/produit à confirmer | F27: Ouvrir la fiche fournisseur et confirmer que le produit correspond bien à l'article
A28: 01 · Électricité CFO | B28: Repere de cablage / bague de reperage | C28: — à renseigner — | E28: Aucune offre chez vos 8 fournisseurs — article à sourcer | F28: Sourcer l'article chez un fournisseur spécialisé, ou le retirer de la nomenclature
A29: 01 · Électricité CFO | B29: Gaine thermoretractable assortiment | C29: Au Forum du Bâtiment | D29: 27.54 | E29: Correspondance article/produit à confirmer | F29: Ouvrir la fiche fournisseur et confirmer que le produit correspond bien à l'article
A30: 02 · Courants faibles | B30: Cable U/UTP categorie 6 touret 100 m | C30: — à renseigner — | E30: Aucune offre chez vos 8 fournisseurs — article à sourcer | F30: Sourcer l'article chez un fournisseur spécialisé, ou le retirer de la nomenclature
A31: 02 · Courants faibles | B31: Cable F/FTP categorie 6A | C31: Au Forum du Bâtiment | D31: 152.8 | E31: Correspondance article/produit à confirmer | F31: Ouvrir la fiche fournisseur et confirmer que le produit correspond bien à l'article
A32: 02 · Courants faibles | B32: Panneau de brassage 24 ports RJ45 cat 6 | C32: Rexel | D32: 78.64 | E32: Correspondance article/produit à confirmer | F32: Ouvrir la fiche fournisseur et confirmer que le produit correspond bien à l'article
A33: 02 · Courants faibles | B33: Camera IP tube exterieure | C33: Au Forum du Bâtiment | D33: 164.7 | E33: Correspondance article/produit à confirmer | F33: Ouvrir la fiche fournisseur et confirmer que le produit correspond bien à l'article
A34: 02 · Courants faibles | B34: Enregistreur NVR 8 voies | C34: — à renseigner — | E34: Aucune offre chez vos 8 fournisseurs — article à sourcer | F34: Sourcer l'article chez un fournisseur spécialisé, ou le retirer de la nomenclature
A35: 02 · Courants faibles | B35: Disque dur surveillance 4 To | C35: Au Forum du Bâtiment | D35: 224.6 | E35: Correspondance article/produit à confirmer | F35: Ouvrir la fiche fournisseur et confirmer que le produit correspond bien à l'article
A36: 02 · Courants faibles | B36: Lecteur de badge mural | C36: Au Forum du Bâtiment | D36: 509.9 | E36: Correspondance article/produit à confirmer | F36: Ouvrir la fiche fournisseur et confirmer que le produit correspond bien à l'article
A37: 02 · Courants faibles | B37: Clavier a code exterieur | C37: Au Forum du Bâtiment | D37: 54 | E37: Correspondance article/produit à confirmer | F37: Ouvrir la fiche fournisseur et confirmer que le produit correspond bien à l'article
A38: 02 · Courants faibles | B38: Bouton de sortie inox | C38: Au Forum du Bâtiment | D38: 2.2 | E38: Correspondance article/produit à confirmer | F38: Ouvrir la fiche fournisseur et confirmer que le produit correspond bien à l'article
A39: 02 · Courants faibles | B39: Centrale d'alarme intrusion filaire | C39: Au Forum du Bâtiment | D39: 472.58 | E39: Correspondance article/produit à confirmer | F39: Ouvrir la fiche fournisseur et confirmer que le produit correspond bien à l'article
A40: 02 · Courants faibles | B40: Detecteur d'ouverture magnetique | C40: Au Forum du Bâtiment | D40: 21.13 | E40: Correspondance article/produit à confirmer | F40: Ouvrir la fiche fournisseur et confirmer que le produit correspond bien à l'article
A41: 02 · Courants faibles | B41: Detecteur infrarouge volumetrique | C41: Au Forum du Bâtiment | D41: 8.91 | E41: Correspondance article/produit à confirmer | F41: Ouvrir la fiche fournisseur et confirmer que le produit correspond bien à l'article
A42: 02 · Courants faibles | B42: Sirene exterieure autoalimentee | C42: Au Forum du Bâtiment | D42: 137.91 | E42: Correspondance article/produit à confirmer | F42: Ouvrir la fiche fournisseur et confirmer que le produit correspond bien à l'article
A43: 02 · Courants faibles | B43: Cable coaxial 17 VATC | C43: Au Forum du Bâtiment | D43: 2.96 | E43: Correspondance article/produit à confirmer | F43: Ouvrir la fiche fournisseur et confirmer que le produit correspond bien à l'article
A44: 02 · Courants faibles | B44: Testeur de cable reseau | C44: Rexel | D44: 2488.05 | E44: Montant élevé pour une unité « u » — vérifier qu'il ne s'agit pas d'un touret, d'une couronne ou d'un lot complet | F44: Vérifier si le prix porte sur une couronne, un touret ou un lot entier plutôt que sur l'unité
A45: 03 · Éclairage | B45: Dalle LED 600x600 36 W | C45: Au Forum du Bâtiment | D45: 27.39 | E45: Correspondance article/produit à confirmer | F45: Ouvrir la fiche fournisseur et confirmer que le produit correspond bien à l'article
A46: 03 · Éclairage | B46: Reglette LED 0,60 m 18 W | C46: Au Forum du Bâtiment | D46: 20.6 | E46: Correspondance article/produit à confirmer | F46: Ouvrir la fiche fournisseur et confirmer que le produit correspond bien à l'article
... A53: 04 · Plomberie sanitaire | B53: Tube cuivre ecroui 14 mm | C53: Au Forum du Bâtiment | D53: 1.48 | E53: Correspondance article/produit à confirmer | F53: Ouvrir la fiche fournisseur et confirmer que le produit correspond bien à l'article
A54: 04 · Plomberie sanitaire | B54: Tube cuivre recuit 12 mm couronne | C54: — à renseigner — | E54: Aucune offre chez vos 8 fournisseurs — article à sourcer | F54: Sourcer l'article chez un fournisseur spécialisé, ou le retirer de la nomenclature
A55: 04 · Plomberie sanitaire | B55: Raccord a compression PER 16 x 12/17 | C55: Au Forum du Bâtiment | D55: 8.55 | E55: Correspondance article/produit à confirmer | F55: Ouvrir la fiche fournisseur et confirmer que le produit correspond bien à l'article
A56: 04 · Plomberie sanitaire | B56: Te reduit a sertir multicouche | C56: Au Forum du Bâtiment | D56: 1.73 | E56: Correspondance article/produit à confirmer | F56: Ouvrir la fiche fournisseur et confirmer que le produit correspond bien à l'article
A57: 04 · Plomberie sanitaire | B57: Raccord laiton male 15x21 | C57: Au Forum du Bâtiment | D57: 2.75 | E57: Correspondance article/produit à confirmer | F57: Ouvrir la fiche fournisseur et confirmer que le produit correspond bien à l'article
A58: 04 · Plomberie sanitaire | B58: Collecteur sanitaire 4 departs | C58: La Plateforme du Bâtiment | D58: 11.14 | E58: Correspondance article/produit à confirmer | F58: Ouvrir la fiche fournisseur et confirmer que le produit correspond bien à l'article
A59: 04 · Plomberie sanitaire | B59: Culotte PVC simple 100/40 | C59: Au Forum du Bâtiment | D59: 19.45 | E59: Correspondance article/produit à confirmer | F59: Ouvrir la fiche fournisseur et confirmer que le produit correspond bien à l'article
A60: 04 · Plomberie sanitaire | B60: Paroi de douche verre 90 cm | C60: Chausson Matériaux | D60: 21.62 | E60: Prix pour un conditionnement — ramener au prix unitaire | F60: Diviser par la quantité du conditionnement pour obtenir le prix unitaire
A61: 04 · Plomberie sanitaire | B61: Filasse de chanvre | C61: La Plateforme du Bâtiment | D61: 11.09 | E61: Correspondance article/produit à confirmer | F61: Ouvrir la fiche fournisseur et confirmer que le produit correspond bien à l'article
A62: 04 · Plomberie sanitaire | B62: Pate a joint plomberie | C62: Au Forum du Bâtiment | D62: 25.02 | E62: Correspondance article/produit à confirmer | F62: Ouvrir la fiche fournisseur et confirmer que le produit correspond bien à l'article
A63: 04 · Plomberie sanitaire | B63: Collier de fixation simple isophonique 20 | C63: Chausson Matériaux | D63: 5.76 | E63: Prix pour un conditionnement — ramener au prix unitaire | F63: Diviser par la quantité du conditionnement pour obtenir le prix unitaire
A64: 05 · CVC | B64: Radiateur electrique panneau rayonnant 1000 W | C64: Rexel | D64: 150.5 | E64: Correspondance article/produit à confirmer | F64: Ouvrir la fiche fournisseur et confirmer que le produit correspond bien à l'article
A65: 05 · CVC | B65: Radiateur acier eau chaude 1000 W | C65: Au Forum du Bâtiment | D65: 365.33 | E65: Correspondance article/produit à confirmer | F65: Ouvrir la fiche fournisseur et confirmer que le produit correspond bien à l'article
A66: 05 · CVC | B66: Thermostat d'ambiance programmable | C66: Chausson Matériaux | D66: 30.87 | E66: Correspondance article/produit à confirmer | F66: Ouvrir la fiche fournisseur et confirmer que le produit correspond bien à l'article
A67: 05 · CVC | B67: Aerotherme electrique tertiaire | C67: — à renseigner — | E67: Aucune offre chez vos 8 fournisseurs — article à sourcer | F67: Sourcer l'article chez un fournisseur spécialisé, ou le retirer de la nomenclature
A68: 05 · CVC | B68: Rideau d'air chaud entree magasin | C68: Rexel | D68: 1046.81 | E68: Correspondance article/produit à confirmer | F68: Ouvrir la fiche fournisseur et confirmer que le produit correspond bien à l'article
A69: 05 · CVC | B69: Extracteur de gaine 150 mm | C69: Au Forum du Bâtiment | D69: 4.75 | E69: Prix pour un conditionnement — ramener au prix unitaire | F69: Diviser par la quantité du conditionnement pour obtenir le prix unitaire
A70: 05 · CVC | B70: Chapeau de toiture ventilation | C70: Point.P | D70: 33.31 | E70: Correspondance article/produit à confirmer | F70: Ouvrir la fiche fournisseur et confirmer que le produit correspond bien à l'article
A71: 05 · CVC | B71: Split mural reversible 3,5 kW | C71: Au Forum du Bâtiment | D71: 596.37 | E71: Correspondance article/produit à confirmer | F71: Ouvrir la fiche fournisseur et confirmer que le produit correspond bien à l'article
A72: 05 · CVC | B72: Fluide frigorigene R32 bouteille | C72: — à renseigner — | E72: Aucune offre chez vos 8 fournisseurs — article à sourcer | F72: Sourcer l'article chez un fournisseur spécialisé, ou le retirer de la nomenclature
A73: 05 · CVC | B73: Manometre chauffage 0-4 bar | C73: Au Forum du Bâtiment | D73: 8.8 | E73: Correspondance article/produit à confirmer | F73: Ouvrir la fiche fournisseur et confirmer que le produit correspond bien à l'article
A74: 06 · Serrurerie | B74: Serrure a larder axe 50 mm | C74: Prolians | D74: 4.57 | E74: Correspondance article/produit à confirmer | F74: Ouvrir la fiche fournisseur et confirmer que le produit correspond bien à l'article
A75: 06 · Serrurerie | B75: Serrure en applique 3 points | C75: Point.P | D75: 33.45 | E75: Correspondance article/produit à confirmer | F75: Ouvrir la fiche fournisseur et confirmer que le produit correspond bien à l'article
A76: 06 · Serrurerie | B76: Cylindre haute securite A2P | C76: Prolians | D76: 221.62 | E76: Correspondance article/produit à confirmer | F76: Ouvrir la fiche fournisseur et confirmer que le produit correspond bien à l'article
A77: 06 · Serrurerie | B77: Barillet sur organigramme | C77: — à renseigner — | E77: Aucune offre chez vos 8 fournisseurs — article à sourcer | F77: Sourcer l'article chez un fournisseur spécialisé, ou le retirer de la nomenclature
A78: 06 · Serrurerie | B78: Verrou de surete a bouton | C78: Point.P | D78: 15.82 | E78: Correspondance article/produit à confirmer | F78: Ouvrir la fiche fournisseur et confirmer que le produit correspond bien à l'article
A79: 06 · Serrurerie | B79: Gache electrique a rupture 12 V | C79: Chausson Matériaux | D79: 34.39 | E79: Correspondance article/produit à confirmer | F79: Ouvrir la fiche fournisseur et confirmer que le produit correspond bien à l'article
A80: 06 · Serrurerie | B80: Gache electrique a emission | C80: Chausson Matériaux | D80: 34.39 | E80: Correspondance article/produit à confirmer | F80: Ouvrir la fiche fournisseur et confirmer que le produit correspond bien à l'article
A81: 06 · Serrurerie | B81: Ferme-porte a glissiere | C81: Chausson Matériaux | D81: 2.65 | E81: Correspondance article/produit à confirmer | F81: Ouvrir la fiche fournisseur et confirmer que le produit correspond bien à l'article
A82: 06 · Serrurerie | B82: Poignee sur plaque inox | C82: Chausson Matériaux | D82: 9.69 | E82: Correspondance article/produit à confirmer | F82: Ouvrir la fiche fournisseur et confirmer que le produit correspond bien à l'article
A83: 06 · Serrurerie | B83: Bequille double sur rosace | C83: Point.P | D83: 12.39 | E83: Correspondance article/produit à confirmer | F83: Ouvrir la fiche fournisseur et confirmer que le produit correspond bien à l'article
A84: 06 · Serrurerie | B84: Paumelle a visser 120 mm | C84: Au Forum du Bâtiment | D84: 22.09 | E84: Correspondance article/produit à confirmer | F84: Ouvrir la fiche fournisseur et confirmer que le produit correspond bien à l'article
A85: 06 · Serrurerie | B85: Butoir de porte a visser | C85: Chausson Matériaux | D85: 1.76 | E85: Prix pour un conditionnement — ramener au prix unitaire | F85: Diviser par la quantité du conditionnement pour obtenir le prix unitaire
A86: 06 · Serrurerie | B86: Selecteur de fermeture 2 vantaux | C86: Au Forum du Bâtiment | D86: 20.29 | E86: Correspondance article/produit à confirmer | F86: Ouvrir la fiche fournisseur et confirmer que le produit correspond bien à l'article
A87: 06 · Serrurerie | B87: Joint isophonique de porte | C87: Chausson Matériaux | D87: 1.56 | E87: Correspondance article/produit à confirmer | F87: Ouvrir la fiche fournisseur et confirmer que le produit correspond bien à l'article
A88: 06 · Serrurerie | B88: Rideau metallique - lame de rechange | C88: — à renseigner — | E88: Aucune offre chez vos 8 fournisseurs — article à sourcer | F88: Sourcer l'article chez un fournisseur spécialisé, ou le retirer de la nomenclature
A89: 06 · Serrurerie | B89: Cadenas haute securite anse protegee | C89: Au Forum du Bâtiment | D89: 14.98 | E89: Correspondance article/produit à confirmer | F89: Ouvrir la fiche fournisseur et confirmer que le produit correspond bien à l'article
A90: 06 · Serrurerie | B90: Profil acier tube carre 40x40x2 | C90: — à renseigner — | E90: Aucune offre chez vos 8 fournisseurs — article à sourcer | F90: Sourcer l'article chez un fournisseur spécialisé, ou le retirer de la nomenclature
A91: 06 · Serrurerie | B91: Corniere acier 30x30x3 | C91: Au Forum du Bâtiment | D91: 79.4 | E91: Correspondance article/produit à confirmer | F91: Ouvrir la fiche fournisseur et confirmer que le produit correspond bien à l'article
A92: 06 · Serrurerie | B92: Tole acier perforee | C92: Au Forum du Bâtiment | D92: 8.64 | E92: Correspondance article/produit à confirmer | F92: Ouvrir la fiche fournisseur et confirmer que le produit correspond bien à l'article
A93: 06 · Serrurerie | B93: Peinture antirouille metal | C93: Au Forum du Bâtiment | D93: 52.41 | E93: Correspondance article/produit à confirmer | F93: Ouvrir la fiche fournisseur et confirmer que le produit correspond bien à l'article
A94: 07 · Sécurité incendie | B94: Extincteur eau pulverisee 6 L | C94: Au Forum du Bâtiment | D94: 4.7 | E94: Correspondance article/produit à confirmer | F94: Ouvrir la fiche fournisseur et confirmer que le produit correspond bien à l'article
A95: 07 · Sécurité incendie | B95: Extincteur CO2 2 kg | C95: — à renseigner — | E95: Aucune offre chez vos 8 fournisseurs — article à sourcer | F95: Sourcer l'article chez un fournisseur spécialisé, ou le retirer de la nomenclature
A96: 07 · Sécurité incendie | B96: Support mural extincteur | C96: — à renseigner — | E96: Aucune offre chez vos 8 fournisseurs — article à sourcer | F96: Sourcer l'article chez un fournisseur spécialisé, ou le retirer de la nomenclature
A97: 07 · Sécurité incendie | B97: Panneau de signalisation extincteur | C97: Au Forum du Bâtiment | D97: 4.7 | E97: Correspondance article/produit à confirmer | F97: Ouvrir la fiche fournisseur et confirmer que le produit correspond bien à l'article
A98: 07 · Sécurité incendie | B98: Declencheur manuel d'alarme | C98: Au Forum du Bâtiment | D98: 3.93 | E98: Correspondance article/produit à confirmer | F98: Ouvrir la fiche fournisseur et confirmer que le produit correspond bien à l'article
A99: 07 · Sécurité incendie | B99: Centrale d'alarme incendie type 4 | C99: Au Forum du Bâtiment | D99: 472.58 | E99: Correspondance article/produit à confirmer | F99: Ouvrir la fiche fournisseur et confirmer que le produit correspond bien à l'article
A100: 07 · Sécurité incendie | B100: Coffret de commande desenfumage | C100: Prolians | D100: 104.44 | E100: Correspondance article/produit à confirmer | F100: Ouvrir la fiche fournisseur et confirmer que le produit correspond bien à l'article
A101: 07 · Sécurité incendie | B101: Ouvrant de desenfumage - verin | C101: — à renseigner — | E101: Aucune offre chez vos 8 fournisseurs — article à sourcer | F101: Sourcer l'article chez un fournisseur spécialisé, ou le retirer de la nomenclature
